Workbook

Sheet Data
U1: 2020
A2: 23560036 | B2: น.ส. | C2: ทิชากร | D2: ศรีจำปา | E2: Miss Tichakorn Srichampa | F2: Administration Officer | G2: พนักงานบริหารงาน | H2: AFM | J2: ส่วนกลยุทธ์และบริหารทรัพยากรอาคารฯ | L2: ฝ่ายบริหารทรัพยากรอาคาร | N2: สายงานประธานเจ้าหน้าที่ปฏิบัติการ | O2: ปธบ.และกรรมการผู้จัดการใหญ่ | P2: GPSC Rayong | Q2: GPSC RYG : CUP-2 | R2: GPSC CUP2-F | S2: FLEXIBLE2 | T2: Female | U2: 0897494028
A3: 23560043 | B3: น.ส. | C3: บงกช | D3: ยุทธวิสุทธิ | E3: Miss Bongkot Yootawisuti | F3: Senior Administration Officer | G3: พนักงานบริหารงานอาวุโส | H3: AFM | J3: ส่วนกลยุทธ์และบริหารทรัพยากรอาคารฯ | L3: ฝ่ายบริหารทรัพยากรอาคาร | N3: สายงานประธานเจ้าหน้าที่ปฏิบัติการ | O3: ปธบ.และกรรมการผู้จัดการใหญ่ | P3: GPSC Rayong | Q3: GPSC RYG : CUP-2 | R3: GPSC CUP2-F | S3: FLEXIBLE2 | T3: Female
A4: 23560092 | B4: นาย | C4: ภาณุ | D4: โพธิกุล | E4: Mr. Panu Potikul | F4: Facility Management Strategy and Site General Services Division Manager | G4: ผู้จัดการส่วนกลยุทธ์และบริหารทรัพยากรอาคารพื้นที่ปฏิบัติการ | H4: AFM | J4: ส่วนกลยุทธ์และบริหารทรัพยากรอาคารฯ | L4: ฝ่ายบริหารทรัพยากรอาคาร | N4: สายงานประธานเจ้าหน้าที่ปฏิบัติการ | O4: ปธบ.และกรรมการผู้จัดการใหญ่ | P4: GPSC Bangkok | Q4: GPSC RYG : CUP-2 | R4: GPSC HO-F | S4: FLEXIBLE2 | T4: Male
A5: 23560177 | B5: น.ส. | C5: จามจุรี | D5: เกษรสวัสดิ์ | E5: Miss Jamjuree Kasonsavad | F5: Administration Officer | G5: พนักงานบริหารงาน | H5: AFM | J5: ส่วนกลยุทธ์และบริหารทรัพยากรอาคารฯ | L5: ฝ่ายบริหารทรัพยากรอาคาร | N5: สายงานประธานเจ้าหน้าที่ปฏิบัติการ | O5: ปธบ.และกรรมการผู้จัดการใหญ่ | P5: GPSC Rayong | Q5: GPSC RYG : CUP-2 | R5: GPSC CUP2-F | S5: FLEXIBLE2 | T5: Female
A6: 23560197 | B6: นาย | C6: ณรงค์ชัย | D6: พรหมเดชวัฒนา | E6: Mr. Narongchai Promdetwattana | F6: Administration Officer | G6: พนักงานบริหารงาน | H6: AFM | J6: ส่วนกลยุทธ์และบริหารทรัพยากรอาคารฯ | L6: ฝ่ายบริหารทรัพยากรอาคาร | N6: สายงานประธานเจ้าหน้าที่ปฏิบัติการ | O6: ปธบ.และกรรมการผู้จัดการใหญ่ | P6: GPSC Rayong | Q6: GPSC RYG : CUP-2 | R6: GPSC CUP2-F | S6: FLEXIBLE2 | T6: Male | U6: 0905492561
A7: 23630027 | B7: นาง | C7: อุษิตตา | D7: มาลย์มาศภาณุ | E7: Mrs. Usitta Marlmaspanu | F7: Site General Administration Manager | G7: ผู้จัดการบริหารสำนักงานพื้นที่ปฏิบัติการ | H7: AFM | J7: ส่วนกลยุทธ์และบริหารทรัพยากรอาคารฯ | L7: ฝ่ายบริหารทรัพยากรอาคาร | N7: สายงานประธานเจ้าหน้าที่ปฏิบัติการ | O7: ปธบ.และกรรมการผู้จัดการใหญ่ | P7: GPSC Rayong | Q7: GPSC RYG : SPP2/3 | R7: GPSC SPP2/3-F | S7: FLEXIBLE2 | T7: Female | U7: 089-2059179
A8: 23630050 | B8: นาย | C8: บุญชนะ | D8: อินทรโชติ | E8: Mr. Boonchana Intarachote | F8: Administration Officer | G8: พนักงานบริหารงาน | H8: AFM | J8: ส่วนกลยุทธ์และบริหารทรัพยากรอาคารฯ | L8: ฝ่ายบริหารทรัพยากรอาคาร | N8: สายงานประธานเจ้าหน้าที่ปฏิบัติการ | O8: ปธบ.และกรรมการผู้จัดการใหญ่ | P8: GPSC Rayong | Q8: GPSC RYG : SPP2/3 | R8: GPSC SPP2/3-F | S8: FLEXIBLE2 | T8: Male
A9: 23630114 | B9: นาง | C9: พิมลพรรณ | D9: สุวรรณรัตน์ | E9: Mrs. Pimonparn Suwannarat | F9: Administration Officer | G9: พนักงานบริหารงาน | H9: AFM | J9: ส่วนกลยุทธ์และบริหารทรัพยากรอาคารฯ | L9: ฝ่ายบริหารทรัพยากรอาคาร | N9: สายงานประธานเจ้าหน้าที่ปฏิบัติการ | O9: ปธบ.และกรรมการผู้จัดการใหญ่ | P9: GPSC Rayong | Q9: GPSC RYG : SPP2/3 | R9: GPSC SPP2/3-F | S9: FLEXIBLE2 | T9: Female
A10: 23630203 | B10: น.ส. | C10: พาฝัน | D10: ผลดี | E10: Miss Pafhan Pholdee | F10: Administration Officer | G10: พนักงานบริหารงาน | H10: AFM | J10: ส่วนกลยุทธ์และบริหารทรัพยากรอาคารฯ | L10: ฝ่ายบริหารทรัพยากรอาคาร | N10: สายงานประธานเจ้าหน้าที่ปฏิบัติการ | O10: ปธบ.และกรรมการผู้จัดการใหญ่ | P10: GPSC Rayong | Q10: GPSC RYG : SPP2/3 | R10: GPSC SPP2/3-F | S10: FLEXIBLE2 | T10: Female
A11: 23630300 | B11: น.ส. | C11: วรัญญา | D11: มังสังคำ | E11: Miss Waranya Mangsangkam | F11: Administration Officer | G11: พนักงานบริหารงาน | H11: AFM | J11: ส่วนกลยุทธ์และบริหารทรัพยากรอาคารฯ | L11: ฝ่ายบริหารทรัพยากรอาคาร | N11: สายงานประธานเจ้าหน้าที่ปฏิบัติการ | O11: ปธบ.และกรรมการผู้จัดการใหญ่ | P11: GPSC Rayong | Q11: GPSC RYG : SPP2/3 | R11: GPSC SPP2/3-F | S11: FLEXIBLE2 | T11: Female
A12: 23630301 | B12: นาย | C12: ธนาธร | D12: ก่ำแก้ว | E12: Mr. Thanathorn Kamkaew | F12: Administration Officer | G12: พนักงานบริหารงาน | H12: AFM | J12: ส่วนกลยุทธ์และบริหารทรัพยากรอาคารฯ | L12: ฝ่ายบริหารทรัพยากรอาคาร | N12: สายงานประธานเจ้าหน้าที่ปฏิบัติการ | O12: ปธบ.และกรรมการผู้จัดการใหญ่ | P12: GPSC Rayong | Q12: GPSC RYG : SPP2/3 | R12: GPSC SPP2/3-F | S12: FLEXIBLE2 | T12: Male
A13: 23630142 | B13: นาง | C13: มัณทนา | D13: คุณากร | E13: Mrs. Mantana Kunakorn | F13: Senior Vice President Group Facility Management | G13: ผู้จัดการฝ่ายอาวุโสบริหารทรัพยากรอาคาร | H13: AFS | M13: ฝ่ายบริหารทรัพยากรอาคาร | N13: สายงานประธานเจ้าหน้าที่ปฏิบัติการ | O13: บริษัท ปตท. จำกัด (มหาชน) | P13: GPSC Bangkok | Q13: GPSC BKK : Empire Tower - 38th floor | R13: GPSC HO-F | S13: FLEXIBLE4 | T13: Female | U13: 089-2057073
A14: 23630033 | B14: นาง | C14: บัวลอย | D14: เคียนขุนทด | E14: Mrs. Bualoi Kienkhuntod | F14: Maid | G14: แม่บ้าน | H14: AGT | I14: แผนกบริหารสำนักงานและบริหารงานทั่วไป | L14: ฝ่ายบริหารทรัพยากรอาคาร | N14: สายงานประธานเจ้าหน้าที่ปฏิบัติการ | O14: ปธบ.และกรรมการผู้จัดการใหญ่ | P14: GPSC Bangkok | Q14: GPSC BKK : Empire Tower - 38th floor | R14: GPSC HO-F | S14: FLEXIBLE4 | T14: Female
A15: 23630039 | B15: นาง | C15: พรทิพย์ | D15: ชุมนุม | E15: Mrs. Porntip Chumnum | F15: Administration Officer | G15: พนักงานบริหารงาน | H15: AGT | I15: แผนกบริหารสำนักงานและบริหารงานทั่วไป | L15: ฝ่ายบริหารทรัพยากรอาคาร | N15: สายงานประธานเจ้าหน้าที่ปฏิบัติการ | O15: ปธบ.และกรรมการผู้จัดการใหญ่ | P15: GPSC Bangkok | Q15: GPSC BKK : Empire Tower - 38th floor | R15: GPSC HO-F | S15: FLEXIBLE4 | T15: Female | U15: 081-3758406
A16: 23630048 | B16: นาย | C16: ไชยา | D16: จันทร์คง | E16: Mr. Chaiya Chankong | F16: Driver | G16: พนักงานขับรถ | H16: AGT | I16: แผนกบริหารสำนักงานและบริหารงานทั่วไป | L16: ฝ่ายบริหารทรัพยากรอาคาร | N16: สายงานประธานเจ้าหน้าที่ปฏิบัติการ | O16: ปธบ.และกรรมการผู้จัดการใหญ่ | P16: GPSC Bangkok | Q16: GPSC BKK : Empire Tower - 38th floor | R16: GPSC HO-F | S16: FLEXIBLE4 | T16: Male
A17: 23630049 | B17: นาง | C17: วงเดือน | D17: จันปัญญา | E17: Mrs. Wongduen Junpunya | F17: Maid | G17: แม่บ้าน | H17: AGT | I17: แผนกบริหารสำนักงานและบริหารงานทั่วไป | L17: ฝ่ายบริหารทรัพยากรอาคาร | N17: สายงานประธานเจ้าหน้าที่ปฏิบัติการ | O17: ปธบ.และกรรมการผู้จัดการใหญ่ | P17: GPSC Bangkok | Q17: GPSC BKK : Empire Tower - 38th floor | R17: GPSC HO-F | S17: FLEXIBLE4 | T17: Female
A18: 23630127 | B18: นาย | C18: วิเชียร | D18: ปู่เจ๊ก | E18: Mr. Wichein Pujek | F18: Driver | G18: พนักงานขับรถ | H18: AGT | I18: แผนกบริหารสำนักงานและบริหารงานทั่วไป | L18: ฝ่ายบริหารทรัพยากรอาคาร | N18: สายงานประธานเจ้าหน้าที่ปฏิบัติการ | O18: ปธบ.และกรรมการผู้จัดการใหญ่ | P18: GPSC Bangkok | Q18: GPSC BKK : Empire Tower - 38th floor | R18: GPSC HO-F | S18: FLEXIBLE4 | T18: Male
A19: 23630132 | B19: น.ส. | C19: นงลักษณ์ | D19: ชิตมณี | E19: Miss Nonglak Chitmanee | F19: Administration Officer | G19: พนักงานบริหารงาน | H19: AGT | I19: แผนกบริหารสำนักงานและบริหารงานทั่วไป | L19: ฝ่ายบริหารทรัพยากรอาคาร | N19: สายงานประธานเจ้าหน้าที่ปฏิบัติการ | O19: ปธบ.และกรรมการผู้จัดการใหญ่ | P19: GPSC Bangkok | Q19: GPSC BKK : Empire Tower - 38th floor | R19: GPSC HO-F | S19: FLEXIBLE4 | T19: Female | U19: 085-6605019
A20: 23630159 | B20: นาย | C20: สุรศักดิ์ | D20: สูญสิ้นภัย | E20: Mr. Surasak Soonsinpai | F20: Driver | G20: พนักงานขับรถ | H20: AGT | I20: แผนกบริหารสำนักงานและบริหารงานทั่วไป | L20: ฝ่ายบริหารทรัพยากรอาคาร | N20: สายงานประธานเจ้าหน้าที่ปฏิบัติการ | O20: ปธบ.และกรรมการผู้จัดการใหญ่ | P20: GPSC Bangkok | Q20: GPSC BKK : Empire Tower - 38th floor | R20: GPSC HO-F | S20: FLEXIBLE4 | T20: Male
A21: 23630160 | B21: นาย | C21: ธวัช | D21: ภูมิสัทธรรม | E21: Mr. Thawat Phumisatthatham | F21: Driver | G21: พนักงานขับรถ | H21: AGT | I21: แผนกบริหารสำนักงานและบริหารงานทั่วไป | L21: ฝ่ายบริหารทรัพยากรอาคาร | N21: สายงานประธานเจ้าหน้าที่ปฏิบัติการ | O21: ปธบ.และกรรมการผู้จัดการใหญ่ | P21: GPSC Bangkok | Q21: GPSC BKK : Empire Tower - 38th floor | R21: GPSC HO-F | S21: FLEXIBLE4 | T21: Male
A22: 23630171 | B22: นาย | C22: ขาว | D22: ไชยวงค์สาย | E22: Mr. Khao Chaiwongsai | F22: Driver | G22: พนักงานขับรถ | H22: AGT | I22: แผนกบริหารสำนักงานและบริหารงานทั่วไป | L22: ฝ่ายบริหารทรัพยากรอาคาร | N22: สายงานประธานเจ้าหน้าที่ปฏิบัติการ | O22: ปธบ.และกรรมการผู้จัดการใหญ่ | P22: GPSC Bangkok | Q22: GPSC BKK : Empire Tower - 38th floor | R22: GPSC HO-F | S22: FLEXIBLE4 | T22: Male
A23: 23630238 | B23: น.ส. | C23: ณัฐธดา | D23: ธนอัศวกุล | E23: Miss Natthada Thana-assavakul | F23: Office Management and General Services Section Manager | G23: ผู้จัดการแผนกบริหารสำนักงานและบริหารงานทั่วไป | H23: AGT | I23: แผนกบริหารสำนักงานและบริหารงานทั่วไป | L23: ฝ่ายบริหารทรัพยากรอาคาร | N23: สายงานประธานเจ้าหน้าที่ปฏิบัติการ | O23: ปธบ.และกรรมการผู้จัดการใหญ่ | P23: GPSC Bangkok | Q23: GPSC BKK : Empire Tower - 38th floor | R23: GPSC HO-F | S23: FLEXIBLE4 | T23: Female | U23: 084-4390076
A24: 23630243 | B24: นาย | C24: ธีรวัฒน์ | D24: จิรวัฒโนบล | E24: Mr. Teerawat Jirawatnobon | F24: Driver | G24: พนักงานขับรถ | H24: AGT | I24: แผนกบริหารสำนักงานและบริหารงานทั่วไป | L24: ฝ่ายบริหารทรัพยากรอาคาร | N24: สายงานประธานเจ้าหน้าที่ปฏิบัติการ | O24: ปธบ.และกรรมการผู้จัดการใหญ่ | P24: GPSC Bangkok | Q24: GPSC BKK : Empire Tower - 38th floor | R24: GPSC HO-F | S24: FLEXIBLE4 | T24: Male
A25: 23630340 | B25: นาย | C25: ธันวา | D25: ทองคงแก้ว | E25: Mr. Thanwa Thongkongkaew | F25: Driver | G25: พนักงานขับรถ | H25: AGT | I25: แผนกบริหารสำนักงานและบริหารงานทั่วไป | L25: ฝ่ายบริหารทรัพยากรอาคาร | N25: สายงานประธานเจ้าหน้าที่ปฏิบัติการ | O25: ปธบ.และกรรมการผู้จัดการใหญ่ | P25: GPSC Bangkok | Q25: GPSC BKK : Empire Tower - 38th floor | R25: GPSC HO-F | S25: FLEXIBLE4 | T25: Male
A26: 23630023 | B26: นาย | C26: บุญเลิศ | D26: เพ็ชรผุดผ่อง | E26: Mr. Boonlert Petputpong | F26: Driver | G26: พนักงานขับรถ | H26: AGT | I26: แผนกบริหารสำนักงานและบริหารงานทั่วไป | L26: ฝ่ายบริหารทรัพยากรอาคาร | N26: สายงานประธานเจ้าหน้าที่ปฏิบัติการ | O26: ปธบ.และกรรมการผู้จัดการใหญ่ | P26: GPSC Chonburi | Q26: GPSC CBI : GIPP | R26: GPSC GIPP-F | S26: FLEXIBLE2 | T26: Male
A27: 23630064 | B27: นาย | C27: ศราวุธ | D27: ชื่นบาน | E27: Mr. Sarawut Choenban | F27: Driver | G27: พนักงานขับรถ | H27: AGT | I27: แผนกบริหารสำนักงานและบริหารงานทั่วไป | L27: ฝ่ายบริหารทรัพยากรอาคาร | N27: สายงานประธานเจ้าหน้าที่ปฏิบัติการ | O27: ปธบ.และกรรมการผู้จัดการใหญ่ | P27: GPSC Chonburi | Q27: GPSC RYG : SPP11 | R27: GPSC GIPP-F | S27: FLEXIBLE2 | T27: Male
A28: 23630024 | B28: นาย | C28: มาโนช | D28: พูลเล็ก | E28: Mr. Manoch Poollake | F28: Driver | G28: พนักงานขับรถ | H28: AGT | I28: แผนกบริหารสำนักงานและบริหารงานทั่วไป | L28: ฝ่ายบริหารทรัพยากรอาคาร | N28: สายงานประธานเจ้าหน้าที่ปฏิบัติการ | O28: ปธบ.และกรรมการผู้จัดการใหญ่ | P28: GPSC Rayong | Q28: GPSC RYG : SPP2/3 | R28: GPSC SPP2/3-F | S28: FLEXIBLE2 | T28: Male
A29: 23630091 | B29: นาย | C29: คำมี | D29: อันทปัญญา | E29: Mr. Kammee Anthapanya | F29: Driver | G29: พนักงานขับรถ | H29: AGT | I29: แผนกบริหารสำนักงานและบริหารงานทั่วไป | L29: ฝ่ายบริหารทรัพยากรอาคาร | N29: สายงานประธานเจ้าหน้าที่ปฏิบัติการ | O29: ปธบ.และกรรมการผู้จัดการใหญ่ | P29: GPSC Rayong | Q29: GPSC RYG : SPP2/3 | R29: GPSC SPP2/3-F | S29: FLEXIBLE2 | T29: Male
A30: 23630128 | B30: นาย | C30: ประนุ | D30: เทินเกษม | E30: Mr. Pranu Terngasem | F30: Driver | G30: พนักงานขับรถ | H30: AGT | I30: แผนกบริหารสำนักงานและบริหารงานทั่วไป | L30: ฝ่ายบริหารทรัพยากรอาคาร | N30: สายงานประธานเจ้าหน้าที่ปฏิบัติการ | O30: ปธบ.และกรรมการผู้จัดการใหญ่ | P30: GPSC Bangkok | Q30: GPSC RYG : SPP2/3 | R30: GPSC HO-F | S30: FLEXIBLE4 | T30: Male
A31: 23630169 | B31: นาย | C31: ประเดิมชัย | D31: โด่งดัง | E31: Mr. Pradermchai Dongdang | F31: Driver | G31: พนักงานขับรถ | H31: AGT | I31: แผนกบริหารสำนักงานและบริหารงานทั่วไป | L31: ฝ่ายบริหารทรัพยากรอาคาร | N31: สายงานประธานเจ้าหน้าที่ปฏิบัติการ | O31: ปธบ.และกรรมการผู้จัดการใหญ่ | P31: GPSC Rayong | Q31: GPSC RYG : SPP2/3 | R31: GPSC SPP2/3-F | S31: FLEXIBLE2 | T31: Male
A32: 23630170 | B32: นาย | C32: ชำนาญ | D32: บัวนาค | E32: Mr. Chumnan Buanak | F32: Driver | G32: พนักงานขับรถ | H32: AGT | I32: แผนกบริหารสำนักงานและบริหารงานทั่วไป | L32: ฝ่ายบริหารทรัพยากรอาคาร | N32: สายงานประธานเจ้าหน้าที่ปฏิบัติการ | O32: ปธบ.และกรรมการผู้จัดการใหญ่ | P32: GPSC Rayong | Q32: GPSC RYG : SPP2/3 | R32: GPSC SPP2/3-F | S32: FLEXIBLE2 | T32: Male
A33: 23630226 | B33: นาย | C33: อานนท์ | D33: อินศร | E33: Mr. Anon Insorn | F33: Driver | G33: พนักงานขับรถ | H33: AGT | I33: แผนกบริหารสำนักงานและบริหารงานทั่วไป | L33: ฝ่ายบริหารทรัพยากรอาคาร | N33: สายงานประธานเจ้าหน้าที่ปฏิบัติการ | O33: ปธบ.และกรรมการผู้จัดการใหญ่ | P33: GPSC Rayong | Q33: GPSC RYG : SPP2/3 | R33: GPSC SPP2/3-F | S33: FLEXIBLE2 | T33: Male
A34: 23630368 | B34: น.ส. | C34: ตรีชฎา | D34: กิ่งป้อง | E34: Miss Trechada Kingpong | F34: Receptionist | G34: พนักงานต้อนรับ | H34: AGT | I34: แผนกบริหารสำนักงานและบริหารงานทั่วไป | L34: ฝ่ายบริหารทรัพยากรอาคาร | N34: สายงานประธานเจ้าหน้าที่ปฏิบัติการ | O34: ปธบ.และกรรมการผู้จัดการใหญ่ | P34: GPSC Rayong | Q34: GPSC RYG : SPP2/3 | R34: GPSC SPP2/3-F | S34: FLEXIBLE2 | T34: Female
A35: 23630415 | B35: น.ส. | C35: รวิสรา | D35: รุ่งโรจน์ | E35: Miss Rawisara Rungrot | F35: Receptionist | G35: พนักงานต้อนรับ | H35: AGT | I35: แผนกบริหารสำนักงานและบริหารงานทั่วไป | L35: ฝ่ายบริหารทรัพยากรอาคาร | N35: สายงานประธานเจ้าหน้าที่ปฏิบัติการ | O35: ปธบ.และกรรมการผู้จัดการใหญ่ | P35: GPSC Rayong | Q35: GPSC RYG : SPP2/3 | R35: GPSC SPP2/3-F | S35: FLEXIBLE2 | T35: Female
A36: 23620052 | B36: นาง | C36: รสยา | D36: เธียรวรรณ | E36: Mrs. Rosaya Teinwan | F36: Executive Vice President - Business Development | G36: รองกรรมการผู้จัดการใหญ่พัฒนาธุรกิจ | H36: BDE | O36: บริษัท ปตท. จำกัด (มหาชน) | P36: GPSC Bangkok | Q36: GPSC BKK : EnCo B - 18th floor | R36: GPSC HO-F | S36: FLEXIBLE4 | T36: Female
A37: 23630467 | B37: น.ส. | C37: อัสนา | D37: มั่นปกป้อง | E37: Miss Atsana Monpokpong | F37: Secretary | G37: เลขานุการ | H37: BDE | O37: บริษัท ปตท. จำกัด (มหาชน) | P37: GPSC Bangkok | Q37: GPSC BKK : EnCo B - 18th floor | R37: GPSC HO-F | S37: FLEXIBLE1 | T37: Female
A38: 23600027 | B38: นาย | C38: กฤตภาส | D38: วารี | E38: Mr. Krittaphat Waree | F38: Senior Engineer | G38: วิศวกรอาวุโส | H38: BFS | M38: สายงานรองกผญ.พัฒนาธุรกิจ | O38: บริษัท ปตท. จำกัด (มหาชน) | P38: GPSC Rayong | Q38: GPSC BKK : EnCo B - 5th floor | R38: GPSC CUP2-F | S38: FLEXIBLE4 | T38: Male | U38: 0979188063
A39: 23600037 | B39: น.ส. | C39: พิมพ์นภัส | D39: อุตมชาติวัฒน์ | E39: Miss Phimnaphat Utamachatiwat | F39: Division Manager | G39: ผู้จัดการส่วน | H39: BFS | M39: สายงานรองกผญ.พัฒนาธุรกิจ | O39: บริษัท ปตท. จำกัด (มหาชน) | P39: GPSC Bangkok | Q39: GPSC BKK : EnCo B - 5th floor | R39: GPSC HO-F | S39: FLEXIBLE4 | T39: Female
A40: 23630013 | B40: น.ส. | C40: นนทวรรณ | D40: อำนวยมัจฉา | E40: Miss Nontawan Amnuaymucha | F40: Engineer | G40: วิศวกร | H40: BFS | M40: สายงานรองกผญ.พัฒนาธุรกิจ | O40: บริษัท ปตท. จำกัด (มหาชน) | P40: GPSC Rayong | Q40: GPSC BKK : EnCo B - 5th floor | R40: GPSC CUP2-F | S40: FLEXIBLE1 | T40: Female
A41: 23630466 | B41: นาย | C41: ปัณณวิชญ์ | D41: เพี้ยนภักตร์ | E41: Mr. Punnavich Pianpucktr | F41: Project Director of Flash | G41: ผู้อำนวยการโครงการแฟลช | H41: BFS | M41: สายงานรองกผญ.พัฒนาธุรกิจ | O41: บริษัท ปตท. จำกัด (มหาชน) | P41: GPSC Bangkok | Q41: GPSC BKK : EnCo B - 5th floor | R41: GPSC HO-F | S41: FLEXIBLE1 | T41: Male
A42: 23560200 | B42: นาย | C42: กรกฤษณ์ | D42: จันทรวิสุทธิ์ | E42: Mr. Korrakid Chantharawisud | F42: Senior Engineer | G42: วิศวกรอาวุโส | H42: BFS | M42: สายงานรองกผญ.พัฒนาธุรกิจ | O42: บริษัท ปตท. จำกัด (มหาชน) | P42: GPSC Rayong | Q42: GPSC RYG : Energy Storage Factory | R42: GPSC CUP2-F | S42: FLEXIBLE2 | T42: Male | U42: 0894664949
A43: 23610010 | B43: น.ส. | C43: วารุณี | D43: เลื่องชัยเชวง | E43: Miss Warunee Lueangchaichaweng | F43: Senior Engineer | G43: วิศวกรอาวุโส | H43: BFS | M43: สายงานรองกผญ.พัฒนาธุรกิจ | O43: บริษัท ปตท. จำกัด (มหาชน) | P43: GPSC Rayong | Q43: GPSC RYG : Energy Storage Factory | R43: GPSC CUP2-F | S43: FLEXIBLE4 | T43: Female | U43: 094-9139401
A44: 23610014 | B44: นาย | C44: อภิสิทธิ | D44: อรุณนวล | E44: Mr. Apisit Aroonnual | F44: Senior Engineer | G44: วิศวกรอาวุโส | H44: BFS | M44: สายงานรองกผญ.พัฒนาธุรกิจ | O44: บริษัท ปตท. จำกัด (มหาชน) | P44: GPSC Rayong | Q44: GPSC RYG : Energy Storage Factory | R44: GPSC CUP2-F | S44: FLEXIBLE4 | T44: Male | U44: 0898912950
A45: 23630496 | B45: นาย | C45: นิพล | D45: วรรณะ | E45: Mr. Niphol Wanna | F45: Technical Director | G45: Technical Director | H45: BFS | M45: สายงานรองกผญ.พัฒนาธุรกิจ | O45: บริษัท ปตท. จำกัด (มหาชน) | P45: GPSC Bangkok | Q45: GPSC RYG : Energy Storage Factory | R45: GPSC HO-F | S45: FLEXIBLE1 | T45: Male | U45: 081-8648738
A46: 23560225 | B46: นาย | C46: ภาณุ | D46: มังกรกาญจน์ | E46: Mr. Parnu Mongkornkarn | F46: Business Development Division Manager | G46: ผู้จัดการส่วนพัฒนาธุรกิจ | H46: BIV | K46: หน่วยพัฒนาธุรกิจต่างประเทศ | M46: สายงานรองกผญ.พัฒนาธุรกิจ | O46: บริษัท ปตท. จำกัด (มหาชน) | P46: GPSC Bangkok | Q46: GPSC BKK : EnCo B - 5th floor | R46: GPSC HO-F | S46: FLEXIBLE4 | T46: Male
A47: 23560226 | B47: นาย | C47: ณพงศ์ | D47: ธนาธรรมธร | E47: Mr. Napong Tanatammatorn | F47: Business Development Division Manager | G47: ผู้จัดการส่วนพัฒนาธุรกิจ | H47: BIV | K47: หน่วยพัฒนาธุรกิจต่างประเทศ | M47: สายงานรองกผญ.พัฒนาธุรกิจ | O47: บริษัท ปตท. จำกัด (มหาชน) | P47: GPSC Bangkok | Q47: GPSC BKK : EnCo B - 5th floor | R47: GPSC HO-F | S47: FLEXIBLE4 | T47: Male | U47: +6689249882
A48: 23580010 | B48: นาย | C48: พหล | D48: เฉลยกิตติ | E48: Mr. Pahol Chaloeykitti | F48: Business Development Officer | G48: พนักงานพัฒนาธุรกิจ | H48: BIV | K48: หน่วยพัฒนาธุรกิจต่างประเทศ | M48: สายงานรองกผญ.พัฒนาธุรกิจ | O48: บริษัท ปตท. จำกัด (มหาชน) | P48: GPSC Bangkok | Q48: GPSC BKK : EnCo B - 5th floor | R48: GPSC HO-F | S48: FLEXIBLE4 | T48: Male
A49: 23580013 | B49: นาย | C49: สืบตระกูล | D49: คอวินิจ | E49: Mr. Suabtragool Khowinij | F49: Business Development Division Manager | G49: ผู้จัดการส่วนพัฒนาธุรกิจ | H49: BIV | K49: หน่วยพัฒนาธุรกิจต่างประเทศ | M49: สายงานรองกผญ.พัฒนาธุรกิจ | O49: บริษัท ปตท. จำกัด (มหาชน) | P49: GPSC Bangkok | Q49: GPSC BKK : EnCo B - 5th floor | R49: GPSC HO-F | S49: FLEXIBLE4 | T49: Male | U49: 0894995498
A50: 23590031 | B50: น.ส. | C50: ณัฐชา | D50: ตู้จินดา | E50: Miss Natchar Tuchinda | F50: Business Development Division Manager | G50: ผู้จัดการส่วนพัฒนาธุรกิจ | H50: BIV | K50: หน่วยพัฒนาธุรกิจต่างประเทศ | M50: สายงานรองกผญ.พัฒนาธุรกิจ | O50: บริษัท ปตท. จำกัด (มหาชน) | P50: GPSC Bangkok | Q50: GPSC BKK : EnCo B - 5th floor | R50: GPSC HO-F | S50: FLEXIBLE4 | T50: Female
A51: 23600024 | B51: นาย | C51: อธิป | D51: ตันติวรวงศ์ | E51: Mr. Athip Tantivorawong | F51: Business Development Division Manager | G51: ผู้จัดการส่วนพัฒนาธุรกิจ | H51: BIV | K51: หน่วยพัฒนาธุรกิจต่างประเทศ | M51: สายงานรองกผญ.พัฒนาธุรกิจ | O51: บริษัท ปตท. จำกัด (มหาชน) | P51: GPSC Bangkok | Q51: GPSC BKK : EnCo B - 5th floor | R51: GPSC HO-F | S51: FLEXIBLE4 | T51: Male
A52: 23600035 | B52: นาย | C52: ประภาสักก์ | D52: เจริญพร | E52: Mr. Praphasak Charoenporn | F52: Business Development Manager | G52: ผู้จัดการพัฒนาธุรกิจ | H52: BIV | K52: หน่วยพัฒนาธุรกิจต่างประเทศ | M52: สายงานรองกผญ.พัฒนาธุรกิจ | O52: บริษัท ปตท. จำกัด (มหาชน) | P52: GPSC Bangkok | Q52: GPSC BKK : EnCo B - 5th floor | R52: GPSC HO-F | S52: FLEXIBLE4 | T52: Male
A53: 23600036 | B53: นาย | C53: จิรัฐ | D53: เจตน์วราพงศ์ | E53: Mr. Jirat Jetwarapong | F53: Business Development Officer | G53: พนักงานพัฒนาธุรกิจ | H53: BIV | K53: หน่วยพัฒนาธุรกิจต่างประเทศ | M53: สายงานรองกผญ.พัฒนาธุรกิจ | O53: บริษัท ปตท. จำกัด (มหาชน) | P53: GPSC Bangkok | Q53: GPSC BKK : EnCo B - 5th floor | R53: GPSC HO-F | S53: FLEXIBLE4 | T53: Male | U53: 0814343717
A54: 23630008 | B54: นาย | C54: พีรพล | D54: อำไพวิทย์ | E54: Mr. Perapol Umpaivit | F54: Business Development Division Manager | G54: ผู้จัดการส่วนพัฒนาธุรกิจ | H54: BIV | K54: หน่วยพัฒนาธุรกิจต่างประเทศ | M54: สายงานรองกผญ.พัฒนาธุรกิจ | O54: บริษัท ปตท. จำกัด (มหาชน) | P54: GPSC Bangkok | Q54: GPSC BKK : EnCo B - 5th floor | R54: GPSC HO-F | S54: FLEXIBLE4 | T54: Male
A55: 23630012 | B55: นาย | C55: กิตตินันท์ | D55: ชุติมาศ | E55: Mr. Kittinan Chutimas | F55: Business Development Officer | G55: พนักงานพัฒนาธุรกิจ | H55: BIV | K55: หน่วยพัฒนาธุรกิจต่างประเทศ | M55: สายงานรองกผญ.พัฒนาธุรกิจ | O55: บริษัท ปตท. จำกัด (มหาชน) | P55: GPSC Bangkok | Q55: GPSC BKK : EnCo B - 5th floor | R55: GPSC HO-F | S55: FLEXIBLE1 | T55: Male
A56: 23630286 | B56: น.ส. | C56: บุษกร | D56: หงษ์สุวรรณ | E56: Miss Busakorn Hongsuwan | F56: Administration Officer | G56: พนักงานบริหารงาน | H56: BIV | K56: หน่วยพัฒนาธุรกิจต่างประเทศ | M56: สายงานรองกผญ.พัฒนาธุรกิจ | O56: บริษัท ปตท. จำกัด (มหาชน) | P56: GPSC Bangkok | Q56: GPSC BKK : EnCo B - 5th floor | R56: GPSC HO-F | S56: FLEXIBLE4 | T56: Female
A57: 23630478 | B57: นาย | C57: วิวัฒน์ | D57: เตชะกิจขจร | E57: MR. Wiwat Techakijkachorn | F57: Business Development Manager | G57: ผู้จัดการพัฒนาธุรกิจ | H57: BIV | K57: หน่วยพัฒนาธุรกิจต่างประเทศ | M57: สายงานรองกผญ.พัฒนาธุรกิจ | O57: บริษัท ปตท. จำกัด (มหาชน) | P57: GPSC Bangkok | Q57: GPSC BKK : EnCo B - 5th floor | R57: GPSC HO-F | S57: FLEXIBLE1 | T57: Male
A58: 23630408 | B58: นาย | C58: นรเศรษฐ์ | D58: ตระการกุลชร | E58: Mr. Norasret Trakarnkulchorn | F58: Business Development Manager | G58: ผู้จัดการพัฒนาธุรกิจ | H58: BNS | M58: สายงานรองกผญ.พัฒนาธุรกิจ | O58: บริษัท ปตท. จำกัด (มหาชน) | P58: GPSC Bangkok | Q58: GPSC BKK : Empire Tower - 38th floor | R58: GPSC HO-F | S58: FLEXIBLE4 | T58: Male | U58: 061-4182200
A59: 23630409 | B59: น.ส. | C59: ปิยวรรณ | D59: อยู่พรม | E59: Miss Piyawan Youprom | F59: Business Development Manager | G59: ผู้จัดการพัฒนาธุรกิจ | H59: BNS | M59: สายงานรองกผญ.พัฒนาธุรกิจ | O59: บริษัท ปตท. จำกัด (มหาชน) | P59: GPSC Bangkok | Q59: GPSC BKK : Empire Tower - 38th floor | R59: GPSC HO-F | S59: FLEXIBLE4 | T59: Female | U59: 098-2821370
A60: 23580012 | B60: นาย | C60: กมลยศ | D60: ชัยรัตน์ | E60: Mr. Kamolyot Chairatana | F60: Business Development Officer | G60: พนักงานพัฒนาธุรกิจ | H60: BNS | M60: สายงานรองกผญ.พัฒนาธุรกิจ | O60: บริษัท ปตท. จำกัด (มหาชน) | P60: GPSC Bangkok | Q60: GPSC BKK : EnCo B - 5th floor | R60: GPSC HO-F | S60: FLEXIBLE4 | T60: Male
A61: 23610001 | B61: นาย | C61: ลักษณะปรีชา | D61: ครุฑขุนทด | E61: Mr. Laksanapreecha Krutkuntode | F61: Senior Vice President New Technology | G61: ผู้จัดการฝ่ายอาวุโสนวัตกรรมและเทคโนโลยีพลังงาน | H61: BNS | M61: สายงานรองกผญ.พัฒนาธุรกิจ | O61: บริษัท ปตท. จำกัด (มหาชน) | P61: GPSC Bangkok | Q61: GPSC BKK : EnCo B - 5th floor | R61: GPSC HO-F | S61: FLEXIBLE4 | T61: Male | U61: 0813713993
A62: 23610015 | B62: นาย | C62: จีรวิชช์ | D62: จิตถวิล | E62: Mr. Jeerawit Chittavil | F62: Engineer | G62: วิศวกร | H62: BNS | M62: สายงานรองกผญ.พัฒนาธุรกิจ | O62: บริษัท ปตท. จำกัด (มหาชน) | P62: GPSC Bangkok | Q62: GPSC BKK : EnCo B - 5th floor | R62: GPSC HO-F | S62: FLEXIBLE4 | T62: Male | U62: 081-174-2998
A63: 23610027 | B63: นาย | C63: สุทธิภูมิ | D63: พุ่มหิรัญ | E63: Mr. Sudhibhumi Pumhiran | F63: Business Development Division Manager | G63: ผู้จัดการส่วนพัฒนาธุรกิจ | H63: BNS | M63: สายงานรองกผญ.พัฒนาธุรกิจ | O63: บริษัท ปตท. จำกัด (มหาชน) | P63: GPSC Bangkok | Q63: GPSC BKK : EnCo B - 5th floor | R63: GPSC HO-F | S63: FLEXIBLE4 | T63: Male
A64: 23630005 | B64: นาย | C64: พงศ์วสุ | D64: ศุขสุเมฆ | E64: Mr. Pongwasu Suksumek | F64: Business Development Officer | G64: พนักงานพัฒนาธุรกิจ | H64: BNS | M64: สายงานรองกผญ.พัฒนาธุรกิจ | O64: บริษัท ปตท. จำกัด (มหาชน) | P64: GPSC Bangkok | Q64: GPSC BKK : EnCo B - 5th floor | R64: GPSC HO-F | S64: FLEXIBLE4 | T64: Male
A65: 23630007 | B65: นาย | C65: ภัทรวิทย์ | D65: แซ่อ๋อง | E65: Mr. Pattarawit Sae-ong | F65: Business Development Division Manager | G65: ผู้จัดการส่วนพัฒนาธุรกิจ | H65: BNS | M65: สายงานรองกผญ.พัฒนาธุรกิจ | O65: บริษัท ปตท. จำกัด (มหาชน) | P65: GPSC Bangkok | Q65: GPSC BKK : EnCo B - 5th floor | R65: GPSC HO-F | S65: FLEXIBLE4 | T65: Male
A66: 23630014 | B66: นาย | C66: สุทธิพล | D66: พฤกษะวัน | E66: Mr. Sutthipol Phrueksawan | F66: Engineer | G66: วิศวกร | H66: BNS | M66: สายงานรองกผญ.พัฒนาธุรกิจ | O66: บริษัท ปตท. จำกัด (มหาชน) | P66: GPSC Bangkok | Q66: GPSC BKK : EnCo B - 5th floor | R66: GPSC HO-F | S66: FLEXIBLE1 | T66: Male
A67: 23630471 | B67: นาย | C67: พัฑฒิ | D67: บุณยสุขานนท์ | E67: Mr. Patti Boonyasukanon | F67: Business Development Division Manager | G67: ผู้จัดการส่วนพัฒนาธุรกิจ | H67: BNS | M67: สายงานรองกผญ.พัฒนาธุรกิจ | O67: บริษัท ปตท. จำกัด (มหาชน) | P67: GPSC Bangkok | Q67: GPSC BKK : EnCo B - 5th floor | R67: GPSC HO-F | S67: FLEXIBLE1 | T67: Male
A68: 23630487 | B68: นาย | C68: พชรวิทย์ | D68: ผู้พัฒน์ | E68: Mr. Phocharavidh Phuphatana | F68: Business Development Officer | G68: พนักงานพัฒนาธุรกิจ | H68: BNS | M68: สายงานรองกผญ.พัฒนาธุรกิจ | O68: บริษัท ปตท. จำกัด (มหาชน) | P68: GPSC Bangkok | Q68: GPSC BKK : EnCo B - 5th floor | R68: GPSC HO-F | S68: FLEXIBLE1 | T68: Male
A69: 23570014 | B69: น.ส. | C69: รพีรัตน์ | D69: ศรีธิ | E69: Miss Rapeerat Srithi | F69: Business Development Officer | G69: พนักงานพัฒนาธุรกิจ | H69: BOS | M69: สายงานรองกผญ.พัฒนาธุรกิจ | O69: บริษัท ปตท. จำกัด (มหาชน) | P69: GPSC Bangkok | Q69: GPSC BKK : EnCo B - 5th floor | R69: GPSC HO-F | S69: FLEXIBLE4 | T69: Female
A70: 23580030 | B70: น.ส. | C70: เพ็ญสินี | D70: จินดานุวัฒน์ | E70: Miss Pensinee Jindanuwat | F70: Business Development Officer | G70: พนักงานพัฒนาธุรกิจ | H70: BOS | M70: สายงานรองกผญ.พัฒนาธุรกิจ | O70: บริษัท ปตท. จำกัด (มหาชน) | P70: GPSC Bangkok | Q70: GPSC BKK : EnCo B - 5th floor | R70: GPSC HO-F | S70: FLEXIBLE4 | T70: Female
A71: 23590023 | B71: น.ส. | C71: พิรนุช | D71: วิทยาโกมล | E71: Miss Piranuj Vithyakomol | F71: Business Development Division Manager | G71: ผู้จัดการส่วนพัฒนาธุรกิจ | H71: BOS | M71: สายงานรองกผญ.พัฒนาธุรกิจ | O71: บริษัท ปตท. จำกัด (มหาชน) | P71: GPSC Bangkok | Q71: GPSC BKK : EnCo B - 5th floor | R71: GPSC HO-F | S71: FLEXIBLE4 | T71: Female
A72: 23630011 | B72: นาย | C72: จาตุรันต์ | D72: ทองบุญส่ง | E72: Mr. Jarturun Thongboonsong | F72: Engineer | G72: วิศวกร | H72: BOS | M72: สายงานรองกผญ.พัฒนาธุรกิจ | O72: บริษัท ปตท. จำกัด (มหาชน) | P72: GPSC Bangkok | Q72: GPSC BKK : EnCo B - 5th floor | R72: GPSC HO-F | S72: FLEXIBLE1 | T72: Male
A73: 23630472 | B73: นาย | C73: วัชรพงศ์ | D73: อินทะเคหะ | E73: Mr. Watcharapong Indageha | F73: Business Development Division Manager | G73: ผู้จัดการส่วนพัฒนาธุรกิจ | H73: BOS | M73: สายงานรองกผญ.พัฒนาธุรกิจ | O73: บริษัท ปตท. จำกัด (มหาชน) | P73: GPSC Bangkok | Q73: GPSC BKK : EnCo B - 5th floor | R73: GPSC HO-F | S73: FLEXIBLE1 | T73: Male
A74: 23560224 | B74: น.ส. | C74: ปัณญนาถ | D74: วิสูตร | E74: Miss Panyanath Visoot | F74: Business Development Division Manager | G74: ผู้จัดการส่วนพัฒนาธุรกิจ | H74: BTS | M74: สายงานรองกผญ.พัฒนาธุรกิจ | O74: บริษัท ปตท. จำกัด (มหาชน) | P74: GPSC Bangkok | Q74: GPSC BKK : CHPP | R74: GPSC HO-F | S74: FLEXIBLE4 | T74: Female | U74: 0924983556
A75: 23630435 | B75: น.ส. | C75: พรเพ็ญ | D75: จิตติวุฒินนท์ | E75: Miss Pornpen Jittiwuttinon | F75: Business Development Manager | G75: ผู้จัดการพัฒนาธุรกิจ | H75: BTS | M75: สายงานรองกผญ.พัฒนาธุรกิจ | O75: บริษัท ปตท. จำกัด (มหาชน) | P75: GPSC Bangkok | Q75: GPSC BKK : Empire Tower - 38th floor | R75: GPSC HO-F | S75: FLEXIBLE1 | T75: Female
A76: 23630030 | B76: น.ส. | C76: นิตยา | D76: เนตรชลายุทธ | E76: Miss Nitaya Natechalayooth | F76: IPP & SPP Contract management Division Manager | G76: ผู้จัดการส่วนบริหารสัญญาลูกค้า IPP & SPP | H76: CCM | J76: ส่วนบริหารสัญญาลูกค้า IPP & SPP | L76: ฝ่ายการพาณิชย์ กลุ่มลูกค้า GPSC บริหารฯ | M76: สายงานรองกผญ.การพาณิชย์ | N76: สายงานประธานเจ้าหน้าที่ปฏิบัติการ | O76: ปธบ.และกรรมการผู้จัดการใหญ่ | P76: GPSC Bangkok | Q76: GPSC BKK : Empire Tower - 38th floor | R76: GPSC HO-F | S76: FLEXIBLE4 | T76: Female | U76: 089-9255886
A77: 23630359 | B77: น.ส. | C77: ภัณฑิรา | D77: อิงคะสุวรรณ์ | E77: Miss Phantira Inkasuwan | F77: IPP & SPP Contract Management Officer | G77: พนักงานบริหารสัญญาลูกค้า IPP & SPP | H77: CCM | J77: ส่วนบริหารสัญญาลูกค้า IPP & SPP | L77: ฝ่ายการพาณิชย์ กลุ่มลูกค้า GPSC บริหารฯ | M77: สายงานรองกผญ.การพาณิชย์ | N77: สายงานประธานเจ้าหน้าที่ปฏิบัติการ | O77: ปธบ.และกรรมการผู้จัดการใหญ่ | P77: GPSC Bangkok | Q77: GPSC BKK : Empire Tower - 38th floor | R77: GPSC HO-F | S77: FLEXIBLE1 | T77: Female
A78: 23580002 | B78: น.ส. | C78: อิสรีย์ | D78: แอกทอง | E78: Miss Issaree Agthong | F78: Manager | G78: ผู้จัดการ | H78: CCM | J78: ส่วนบริหารสัญญาลูกค้า IPP & SPP | L78: ฝ่ายการพาณิชย์ กลุ่มลูกค้า GPSC บริหารฯ | M78: สายงานรองกผญ.การพาณิชย์ | N78: สายงานประธานเจ้าหน้าที่ปฏิบัติการ | O78: ปธบ.และกรรมการผู้จัดการใหญ่ | P78: GPSC Bangkok | Q78: GPSC BKK : EnCo B - 5th floor | R78: GPSC HO-F | S78: FLEXIBLE4 | T78: Female | U78: 0615595365
A79: 23630152 | B79: น.ส. | C79: ปีติพร | D79: วรวรรณ | E79: Miss Peetiporn Voravarn | F79: Commercial Data Manager | G79: ผู้จัดการ Commercial Data | H79: CDT | I79: โครงการวิเคราะห์ข้อมูลการพาณิชย์ | M79: สายงานรองกผญ.การพาณิชย์ | N79: สายงานประธานเจ้าหน้าที่ปฏิบัติการ | O79: ปธบ.และกรรมการผู้จัดการใหญ่ | P79: GPSC Bangkok | Q79: GPSC BKK : Empire Tower - 38th floor | R79: GPSC HO-F | S79: FLEXIBLE4 | T79: Female
A80: 23630506 | B80: น.ส. | C80: ภัคสิรี | D80: หอระตะ | E80: Miss Paksiree Horata | F80: Secretary CEO | G80: เลขานุการ ประธานเจ้าหน้าที่บริหารและกรรมการผู้จัดการใหญ่ | H80: CEO | O80: บริษัท ปตท. จำกัด (มหาชน) | P80: GPSC Bangkok | R80: GPSC HO-F | S80: FLEXIBLE4 | T80: Female
A81: 23640006 | B81: น.ส. | C81: ณัฏฐา | D81: ดนตรี | E81: Miss Nattha Dontree | F81: Division Manager | G81: ผู้จัดการส่วนโครงการบริหารกิจการพิเศษ | H81: CEO | O81: บริษัท ปตท. จำกัด (มหาชน) | P81: GPSC Bangkok | R81: GPSC HO-F | S81: FLEXIBLE1 | T81: Female
A82: 23590001 | B82: นาง | C82: ดวงกมล | D82: เวชสุภาพร | E82: Mrs. Duangkamol Vejsupaporn | F82: Senior Secretary | G82: เลขานุการอาวุโส | H82: CEO | O82: บริษัท ปตท. จำกัด (มหาชน) | P82: GPSC Bangkok | Q82: GPSC BKK : EnCo B - 18th floor | R82: GPSC HO-F | S82: FLEXIBLE4 | T82: Female
A83: 23630501 | B83: นาย | C83: วรวัฒน์ | D83: พิทยศิริ | E83: Mr. Worawat Pitayasiri | F83: President and Chief Executive Officer | G83: ประธานเจ้าหน้าที่บริหารและกรรมการผู้จัดการใหญ่ | H83: CEO | O83: บริษัท ปตท. จำกัด (มหาชน) | P83: GPSC Bangkok | Q83: GPSC BKK : EnCo B - 18th floor | R83: GPSC HO-F | S83: FLEXIBLE4 | T83: Male
A84: 23640001 | B84: นาย | C84: ทิติพงษ์ | D84: จุลพรศิริดี | E84: Mr. Thitipong Jurapornsiridee | F84: Chief Financial Officer | G84: ประธานเจ้าหน้าที่บริหารการเงิน | H84: CFO | O84: บริษัท ปตท. จำกัด (มหาชน) | P84: GPSC Bangkok | R84: GPSC HO-F | S84: FLEXIBLE1 | T84: Male
A85: 23630057 | B85: น.ส. | C85: ฉัฐมณฑน์ | D85: กุลถาวรากร | E85: Miss Chatamon Kulthavarakorn | F85: Manager of Chief Financial Officer | G85: ผู้จัดการ ประจำประธานเจ้าหน้าที่บริหารการเงิน | H85: CFO | O85: บริษัท ปตท. จำกัด (มหาชน) | P85: GPSC Bangkok | Q85: GPSC BKK : Empire Tower - 38th floor | R85: GPSC HO-F | S85: FLEXIBLE4 | T85: Female
A86: 23630136 | B86: น.ส. | C86: ประภารัตน์ | D86: นรานุวัฒน์ | E86: Miss Praparat Naranuwat | F86: Manager of Chief Financial Officer | G86: ผู้จัดการ ประจำประธานเจ้าหน้าที่บริหารการเงิน | H86: CFO | O86: บริษัท ปตท. จำกัด (มหาชน) | P86: GPSC Bangkok | Q86: GPSC BKK : Empire Tower - 38th floor | R86: GPSC HO-F | S86: FLEXIBLE4 | T86: Female | U86: 090-1987180
A87: 23590014 | B87: น.ส. | C87: ร่มบุญ | D87: อุดมสิน | E87: Miss Romboon Udomsin | F87: Secretary | G87: เลขานุการ | H87: CFO | O87: บริษัท ปตท. จำกัด (มหาชน) | P87: GPSC Bangkok | Q87: GPSC BKK : EnCo B - 18th floor | R87: GPSC HO-F | S87: FLEXIBLE4 | T87: Female
A88: 23560122 | B88: น.ส. | C88: สุกิตตี | D88: ไชยรักษ์ | E88: Miss Sukittee Chaiyarak | F88: Senior Vice President of Chief Financial Officer | G88: ผู้จัดการฝ่ายอาวุโส ประจำประธานเจ้าหน้าที่บริหารการเงิน ปฏิบัติงาน Secondment ต จัดการ GPSCTC และกำกับดูแลส่วนบริหารการเงินองค์กร อีกหน้าที | H88: CFO | O88: บริษัท ปตท. จำกัด (มหาชน) | P88: GPSC Bangkok | Q88: GPSC BKK : EnCo B - 5th floor | R88: GPSC HO-F | S88: FLEXIBLE4 | T88: Female
A89: 23620051 | B89: น.ส. | C89: ธัญย์หทัยขวัญ | D89: ธนอนันตกูล | E89: Ms. Tanhataikwan Thana-Anantakul | F89: Finance Officer of Chief Financial Officer | G89: พนักงานการเงิน ประจำประธานเจ้าหน้าที่บริหารการเงิน | H89: CFO | O89: บริษัท ปตท. จำกัด (มหาชน) | P89: GPSC Bangkok | Q89: GPSC BKK : EnCo B - 5th floor | R89: GPSC HO-F | S89: FLEXIBLE4 | T89: Female
A90: 23620057 | B90: น.ส. | C90: ภาวินี | D90: ฉัตรสง่า | E90: Ms. Pawinee Shatsa-Nga | F90: Finance Officer of Chief Financial Officer | G90: พนักงานการเงิน ประจำประธานเจ้าหน้าที่บริหารการเงิน | H90: CFO | O90: บริษัท ปตท. จำกัด (มหาชน) | P90: GPSC Bangkok | Q90: GPSC BKK : EnCo B - 5th floor | R90: GPSC HO-F | S90: FLEXIBLE4 | T90: Female
A91: 23630383 | B91: น.ส. | C91: ศศิณี | D91: จักรานุกุล | E91: Miss Sasinee Jukranukul | F91: Manager of Chief Financial Officer | G91: ผู้จัดการ ประจำประธานเจ้าหน้าที่บริหารการเงิน | H91: CFO | O91: บริษัท ปตท. จำกัด (มหาชน) | P91: GPSC Bangkok | Q91: GPSC BKK : EnCo B - 5th floor | R91: GPSC HO-F | S91: FLEXIBLE4 | T91: Female
A92: 23560227 | B92: นาย | C92: ปวเรศ | D92: รัตนสุวรรณ | E92: Mr. Pavarate Rattanasuwan | F92: Senior Vice President - Commercial GPSC and Government Contract | G92: ผู้จัดการฝ่ายอาวุโสการพาณิชย์ กลุ่มลูกค้า GPSC และบริหารสัญญา | H92: CGS | M92: สายงานรองกผญ.การพาณิชย์ | N92: สายงานประธานเจ้าหน้าที่ปฏิบัติการ | O92: ปธบ.และกรรมการผู้จัดการใหญ่ | P92: GPSC Bangkok | Q92: GPSC BKK : Empire Tower - 38th floor | R92: GPSC HO-F | S92: FLEXIBLE4 | T92: Male
A93: 23570041 | B93: นาย | C93: คมสัน | D93: ศักดิ์ศรีวัฒนา | E93: Mr. Komsun Saksriwattana | F93: Vice President | G93: ผู้จัดการฝ่าย รักษาการผู้จัดการฝ่ายอาวุโส | H93: CHPP | K93: บริษัท ผลิตไฟฟ้าและพลังงานร่วม จำกัด | N93: กลุ่มบริษัทในเครือGPSC | O93: บริษัท ปตท. จำกัด (มหาชน) | P93: GPSC Bangkok | Q93: GPSC BKK : CHPP | R93: GPSC HO-F | S93: FLEXIBLE4 | T93: Male
A94: 23570042 | B94: นาย | C94: เอนก | D94: ไอศวรรย์ศาลี | E94: Mr. Anek Isawansaree | F94: Division Manager | G94: ผู้จัดการส่วน | H94: CHPP | K94: บริษัท ผลิตไฟฟ้าและพลังงานร่วม จำกัด | N94: กลุ่มบริษัทในเครือGPSC | O94: บริษัท ปตท. จำกัด (มหาชน) | P94: GPSC Bangkok | Q94: GPSC BKK : CHPP | R94: GPSC HO-F | S94: FLEXIBLE4 | T94: Male
A95: 23630016 | B95: นาง | C95: ศรีประภา | D95: สำรวจรวมผล | E95: Mrs. Sriprapha Sumruatruamphol | F95: Executive Vice President - Commercial | G95: รองกรรมการผู้จัดการใหญ่การพาณิชย์ | H95: CME | N95: สายงานประธานเจ้าหน้าที่ปฏิบัติการ | O95: บริษัท ปตท. จำกัด (มหาชน) | P95: GPSC Bangkok | Q95: GPSC BKK : Empire Tower - 38th floor | R95: GPSC HO-F | S95: FLEXIBLE4 | T95: Female | U95: 081-8202746
A96: 23630174 | B96: น.ส. | C96: สุภัทรา | D96: วามะสุรีย์ | E96: Miss Supattra Vamasuree | F96: Secretary | G96: เลขานุการ | H96: CME | N96: สายงานประธานเจ้าหน้าที่ปฏิบัติการ | O96: บริษัท ปตท. จำกัด (มหาชน) | P96: GPSC Bangkok | Q96: GPSC BKK : Empire Tower - 38th floor | R96: GPSC HO-F | S96: FLEXIBLE4 | T96: Female
A97: 23630060 | B97: น.ส. | C97: ศิริจันทร์ | D97: โชติชัยสถิตย์ | E97: Miss Sirichan Chotchaisathit | F97: Vice President Industrial Customers Sales, GLOW | G97: ผู้จัดการฝ่ายการพาณิชย์ กลุ่มลูกค้าอุตสาหกรรม GLOW | H97: CMV | K97: หน่วยการพาณิชย์กลุ่มลูกค้าอุตสาหกรรมGLOW | M97: สายงานรองกผญ.การพาณิชย์ | N97: สายงานประธานเจ้าหน้าที่ปฏิบัติการ | O97: ปธบ.และกรรมการผู้จัดการใหญ่ | P97: GPSC Bangkok | Q97: GPSC BKK : Empire Tower - 38th floor | R97: GPSC HO-F | S97: FLEXIBLE4 | T97: Female | U97: 081-8135739
A98: 23630281 | B98: นาง | C98: วิชชุดา | D98: หุวะนันทน์ | E98: Mrs. Witchuda Huvanandana | F98: Manager | G98: ผู้จัดการ | H98: CMV | K98: หน่วยการพาณิชย์กลุ่มลูกค้าอุตสาหกรรมGLOW | M98: สายงานรองกผญ.การพาณิชย์ | N98: สายงานประธานเจ้าหน้าที่ปฏิบัติการ | O98: ปธบ.และกรรมการผู้จัดการใหญ่ | P98: GPSC Bangkok | Q98: GPSC BKK : Empire Tower - 38th floor | R98: GPSC HO-F | S98: FLEXIBLE4 | T98: Female | U98: 081-1715466
A99: 23630407 | B99: น.ส. | C99: อรวรา | D99: จิ๋วพัฒนกุล | E99: Miss Onvara Jewpattanakul | F99: Administration Officer | G99: พนักงานบริหารงาน | H99: CMV | K99: หน่วยการพาณิชย์กลุ่มลูกค้าอุตสาหกรรมGLOW | M99: สายงานรองกผญ.การพาณิชย์ | N99: สายงานประธานเจ้าหน้าที่ปฏิบัติการ | O99: ปธบ.และกรรมการผู้จัดการใหญ่ | P99: GPSC Bangkok | Q99: GPSC BKK : Empire Tower - 38th floor | R99: GPSC HO-F | S99: FLEXIBLE4 | T99: Female
A100: 23630440 | B100: น.ส. | C100: ชมภูนุช | D100: สมบูรณ์พร | E100: Miss Chompoonuch Somboonporn | F100: Manager | G100: ผู้จัดการ | H100: CMV | K100: หน่วยการพาณิชย์กลุ่มลูกค้าอุตสาหกรรมGLOW | M100: สายงานรองกผญ.การพาณิชย์ | N100: สายงานประธานเจ้าหน้าที่ปฏิบัติการ | O100: ปธบ.และกรรมการผู้จัดการใหญ่ | P100: GPSC Bangkok | Q100: GPSC BKK : Empire Tower - 38th floor | R100: GPSC HO-F | S100: FLEXIBLE4 | T100: Female | U100: 089-8100872
...

Sheet Risk Criteria (TH)
B1: GPSC Risk Criteria
G2: (Version as of 7 Aug 2019)
B3: เกณฑ์การประเมินโอกาสเกิด (Likelihood) | D3: ระดับ
D4: ต่ำ 1 | E4: ปานกลาง 2 | F4: สูง 3 | G4: รุนแรง 4
B6: โอกาสเกิด | D6: < 10% | E6: >10% ถึง < 20% | F6: >20% ถึง < 50% | G6: > 50%
D7: ไม่เคย/เคยเกิดขึ้น 1 ครั้งใน 5 ปี | E7: เคยเกิดขึ้น 1 ครั้ง ใน 3 ปี | F7: เคยเกิดขึ้น 1 ครั้ง ใน 1 ปี | G7: เคยเกิดขึ้น > 1 ครั้ง ใน 1 ปี
B9: เกณฑ์การประเมินผลกระทบ (Impact) | D9: ระดับ
D10: ต่ำ 1 | E10: ปานกลาง 2 | F10: สูง 3 | G10: รุนแรง 4
B11: ด้านการเงิน (Financial) | C11: กำไรสุทธิต่ำกว่าเป้าหมาย (Net Profit) | D11: < 1.25% | E11: > 1.25% ถึง < 2.5% | F11: > 2.5% ถึง < 5% | G11: > 5%
C12: กำไรขั้นต้นต่ำกว่าเป้าหมาย (EBITDA) | D12: < 1.25% | E12: > 1.25% ถึง < 2.5% | F12: > 2.5% ถึง < 5% | G12: > 5%
C13: รายได้ต่ำกว่าเป้าหมาย (Revenue) | D13: < 1.25% | E13: > 1.25% ถึง < 2.5% | F13: > 2.5% ถึง < 5% | G13: > 5%
C14: ค่าใช้จ่ายสูงกว่าเป้าหมาย (Expense) | D14: < 1.25% | E14: > 1.25% ถึง < 2.5% | F14: > 2.5% ถึง < 5% | G14: > 5%
C15: ผลตอบแทนการลงทุนต่ำกว่าเป้าหมาย (Project Return: Equity IRR) | D15: < 5 % จาก base case | E15: > 5 % ถึง < 10 % จาก base case | F15: > 10% ถึง < 15% จาก base case | G15: >15 % จาก base case
C16: งบประมาณลงทุนสูงกว่าที่ได้รับอนุมัติ (Project Cost Overrun) | D16: < 1.25%จาก base case | E16: > 1.25% ถึง < 2.5% จาก base case | F16: > 2.5% ถึง < 5% จาก base case | G16: > 5% จาก base case
B17: ด้านกระบวนการธุรกิจ และการปฏิบัติการ (Business Process and Operation ) | C17: ประสิทธิผลของกระบวนการ | D17: มีผลกระทบต่อกระบวนการผลิต/กระบวนการดำเนินงานเล็กน้อยโดยอยู่ในระดับที่สามารถควบคุมและแก้ไขได้ด้วยตนเอง | E17: มีผลกระทบต่อกระบวนการผลิต/กระบวนการดำเนินงาน โดยอยู่ในระดับที่สามารถควบคุมและแก้ไขได้โดยหน่วยงานที่เกี่ยวข้อง | F17: มีผลกระทบต่อกระบวนการผลิต/กระบวนการดำเนินงาน โดยจำเป็นต้องหยุด/ชะลอการดำเนินงานหลักบางส่วนลง | G17: มีผลกระทบต่อกระบวนการผลิต/กระบวนการดำเนินงานอย่างรุนแรง โดยส่งผลกระทบต่อการส่งมอบผลิตภัณฑ์แก่ลูกค้า/การดำเนินงานและเป้าหมายตามแผนงาน
C18: ผลิตภัณฑ์หรือบริการ | D18: เกิดความล่าช้าในการส่งมอบผลิตภัณฑ์/บริการ | E18: เกิดความล่าช้าในการส่งมอบผลิตภัณฑ์/บริการ และไม่ได้คุณภาพตรงตามข้อกำหนด | F18: ไม่สามารถผลิต/ส่งมอบผลิตภัณฑ์หรือบริการได้ | G18: ไม่สามารถผลิต/ส่งมอบผลิตภัณฑ์หรือบริการและบริษัทมีค่าใช้จ่ายส่วนเพิ่มหรือถูกเรียกร้องค่าเสียหาย
C19: การปฏิบัติตามกฎหมาย / กฎระเบียบ / ข้อบังคับ | D19: ขัดต่อกฎระเบียบ/ข้อบังคับ/ข้อกำหนดตามมาตรฐานต่างๆ ของบริษัท | E19: ขัดต่อกฎหมาย กฏระเบียบของหน่วยงานภายนอกที่กำกับดูแล ซึ่งกระทบต่อการดำเนินงานของบริษัท แต่สามารถดำเนินการแก้ไขได้ในทันที | F19: ขัดต่อกฎหมาย/ข้อบังคับ กฏระเบียบของหน่วยงานภายนอกที่กำกับดูแล โดยได้รับบทลงโทษตามกฎหมาย หรือต้องแก้ไขตามคำสั่งของหน่วยงานภายนอกที่กำกับดูแล | G19: ขัดต่อกฎหมาย กฏระเบียบของหน่วยงานภายนอกที่กำกับดูแล โดยถูกเพิกถอนใบอนุญาต หรือถูกปิดกิจการ
C20: ระยะเวลาการดำเนินโครงการล่าช้า (ตั้งแต่ BOD Approval ถึง COD) | D20: < 3% จากแผนงาน หรือ < 1 เดือน | E20: 3% < X < 5% จากแผนงาน หรือ < 2 เดือน | F20: 5% < X < 10% จากแผนงาน หรือ < 3 เดือน | G20: ล่าช้าจากแผนงาน > 10% หรือ > 3 เดือน
C21: การกำกับดูแลบริษัทในเครือ | D21: การดำเนินงานเป็นไปตามนโยบาย/แนวทางของ GPSC และสามารถควบคุมได้ | E21: การดำเนินงานเป็นไปตามนโยบาย/แนวทางของ GPSC โดยไม่สามารถควบคุมได้ | F21: ไม่ดำเนินงานตามนโยบาย/แนวทางของ GPSC | G21: ไม่ดำเนินงานตามนโยบาย/แนวทางของ GPSC และส่งผลเสียหายต่อ GPSC
B22: ชื่อเสียงองค์กร (Image and Reputation) | C22: ภาพลักษณ์ GPSC ต่อสาธารณะ/สื่อ | D22: - | E22: ทำให้เกิดความไม่พอใจจากสาธารณะ เช่น การเขียนบทความวิจารณ์ | F22: ทำให้เกิดความไม่พอใจอย่างมากจากสาธารณะ เช่น การแสดงความเห็นคัดค้านผ่านสื่อต่างๆ | G22: ทำให้เกิดการต่อต้านอย่างรุนแรงจากสาธารณะ เช่น การประท้วงจากชุมชน
C23: ภาพลักษณ์ GPSC ต่อชุมชน | D23: มีผลกระทบต่อชุมชนรอบสถานประกอบการ/โรงงานเล็กน้อย โดยได้รับคำติเตียนข้อครหาอย่างไม่เป็นทางการผ่านช่องทางต่างๆ ของบริษัท | E23: มีผลกระทบต่อชุมชนรอบสถานประกอบการ/โรงงาน โดยได้รับข้อร้องเรียนอย่างเป็นลายลักษณ์อักษร และดำเนินแก้ไขได้ภายใน 1 สัปดาห์ | F23: มีผลกระทบต่อชุมชนรอบสถานประกอบการ/โรงงานโดย ได้รับข้อร้องเรียนอย่างเป็นลายลักษณ์อักษร และถูกดำเนินการตรวจสอบจากหน่วยงานกำกับดูแลจากภายนอก | G23: มีผลกระทบรุนแรงต่อชุมชนเป็นบริเวณกว้าง โดยได้รับคำสั่งหยุดการดำเนินการ หรือถูกประท้วงจากมวลชนจนไม่สามารถดำเนินธุรกิจได้
C24: สิ่งแวดล้อม | D24: เกิดผลกระทบต่อสิ่งแวดล้อมในบริเวณข้างเคียงเล็กน้อย โดยไม่ต้องมีมาตรการดำเนินการแก้ไข | E24: เกิดผลกระทบต่อสิ่งแวดล้อมโดยสามารถดำเนินการแก้ไขได้ภายใน 1 วัน หรือใช้ระยะเวลาในการบรรเทา/ฟื้นฟูให้กลับคืนสภาพได้ภายในระยะเวลา < 1 ปี | F24: เกิดผลกระทบต่อสิ่งแวดล้อมระดับรุนแรงโดยสามารถดำเนินการแก้ไขได้ในระยะเวลามากกว่า 1 วัน แต่ไม่เกิน 1 เดือน หรือสามารถใช้ระยะเวลาในการบรรเทา/ฟื้นฟูให้กลับคืนสภาพได้ภายในระยะเวลาตั้งแต่ 1-5 ปี | G24: เกิดผลกระทบต่อสิ่งแวดล้อมระดับรุนแรงมาก โดยสามารถดำเนินการแก้ไขได้ในระยะเวลามากกว่า 1 เดือน หรือต้องอาศัยระยะเวลามากกว่า 5 ปีขึ้นไปในการบรรเทา/ฟื้นฟู หรือเสียหายจนยากต่อการฟื้นฟู
B25: ด้านลูกค้า (Customers) | C25: ปริมาณขายผลิตภัณฑ์/บริการของ GPSC | D25: ลูกค้าที่ไม่ใช่ลูกค้าหลักลดการซื้อผลิตภัณฑ์/บริการ | E25: ลูกค้าที่ไม่ใช่ลูกค้าหลักเลิกซื้อผลิตภัณฑ์/บริการ | F25: ลูกค้าหลักลดการซื้อผลิตภัณฑ์/บริการ | G25: ลูกค้าหลักเลิกซื้อผลิตภัณฑ์/บริการ
C26: ความพึงพอใจของลูกค้า/คู่ค้า | D26: - | E26: ลูกค้า/คู่ค้าแสดงความไม่พอใจร้องเรียนกลับมาที่บริษัท | F26: ลูกค้า/คู่ค้าแสดงความไม่พอใจผ่านสื่อต่างๆ | G26: ลูกค้า/คู่ค้าฟ้องร้องบริษัท
B27: ด้านบุคคล (People) | C27: ความปลอดภัยและสุขภาพ | D27: พนักงาน ลูกค้า คู่ค้า หรือผู้มีส่วนได้ส่วนเสียได้รับบาดเจ็บจนต้องได้รับการปฐมพยาบาลทางการแพทย์ | E27: พนักงาน ลูกค้า คู่ค้า หรือผู้มีส่วนได้ส่วนเสีย ได้รับบาดเจ็บหรือเจ็บป่วยจนต้องได้รับการรักษาจากแพทย์ (OPD) แต่ไม่ต้องเข้าพักรักษาในโรงพยาบาล | F27: พนักงาน ลูกค้า คู่ค้า หรือผู้มีส่วนได้ส่วนเสีย ได้รับบาดเจ็บหนักหรือเจ็บป่วยจนต้องเข้าพักรักษาในโรงพยาบาล (IPD) | G27: พนักงาน ลูกค้า คู่ค้า หรือผู้มีส่วนได้ส่วนเสีย ทุพพลภาพ/เสียชีวิต
C28: ความพึงพอใจของพนักงาน | D28: พนักงานเกิดความไม่พอใจ และสามารถบริหารจัดการแก้ไขได้ภายในหน่วยงาน | E28: พนักงานเกิดความไม่พึงพอใจ และมีความจำเป็นต้องอาศัยหน่วยงานกลาง (HR) ในการดำเนินการแก้ไข | F28: พนักงานเกิดความไม่พึงพอใจสูง และมีการร้องเรียนผ่านช่องทางภายในบริษัท | G28: พนักงานเกิดความไม่พึงพอใจรุนแรง เช่น นัดหยุดงานหรือลาออก และส่งผลให้การดำเนินธุรกิจหยุดชะงัก หรือเกิดข้อพิพาทที่ต้องเข้าสู่กระบวนการทางกฎหมาย

Sheet Risk Criteria (ENG)
B1: GPSC Risk Criteria
G2: (Version as of 7 Aug 2019)
B3: Likelihood | D3: Level
D4: Low 1 | E4: Medium 2 | F4: High 3 | G4: Extreme 4
B6: Likelihood | D6: < 10% | E6: >10% to < 20% | F6: >20% to < 50% | G6: > 50%
D7: Never or occure 1 time in 5 years | E7: Occure 1 time in 3 years | F7: Occure 1 time in a year | G7: Occure more than 1 time in a year
B9: Impact | D9: Level
D10: Low 1 | E10: Medium 2 | F10: High 3 | G10: Extreme 4
B12: Financial | C12: Net Profit: Lower than Target | D12: < 1.25% | E12: > 1.25% to < 2.5% | F12: > 2.5% to < 5% | G12: > 5%
C13: EBITDA: Lower than Target | D13: < 1.25% | E13: > 1.25% to < 2.5% | F13: > 2.5% to < 5% | G13: > 5%
C14: Revenue: Lower than Target | D14: < 1.25% | E14: > 1.25% to < 2.5% | F14: > 2.5% to < 5% | G14: > 5%
C15: Expense: Higher than Target | D15: < 1.25% | E15: > 1.25% to < 2.5% | F15: > 2.5% to < 5% | G15: > 5%
C16: Project Return: Equity IRR Lower than Target | D16: < 5 % from base case | E16: > 5 % to < 10 % from base case | F16: > 10% to < 15% from base case | G16: >15 % to base case
C17: Project Cost Overrun | D17: < 1.25% from base case | E17: > 1.25% to < 2.5% from base case | F17: > 2.5% to < 5% from base case | G17: > 5% from base case
B18: Business Process and Operation | C18: Process Effectiveness | D18: Slight/Minor impact on operating/core process, and can be controlled and recovered by owner | E18: Moderate impact on operating/core process, and need support from related party to control and recover | F18: High impact on operating/core process, and need to stop/slow down some part of the core process | G18: Extreme impact on operating/core process, and also affect to customers' product or business target
C19: Product/Service | D19: Delay in delivery of the product/service | E19: Delay in delivery and unable to meet quality standard of the product/service | F19: Delivery of the product/service cannot be done | G19: Delivery of the product/service cannot be done, and company is charged with additional costs or damage claim
C20: Regulatory Compliance | D20: Not comply with the regulations, policies, procedures and standards of the company | E20: Not comply with the laws and regulations from external regulator, but can be resolved immediately | F20: Not comply with the laws and regulations from external regulator, and be punished according to law or required to remedy according to external regulator's order | G20: Not comply with the laws and regulations from external regulator, and cause revokation of license or dissolution
C21: Project Delay (from BOD Approval Plan) | D21: < 3% from plan or < 1 month | E21: 3% < X < 5% from plan or < 2 months | F21: 5% < X < 10% from plan or < 3 months | G21: Delay from plan > 10% or > 3 months
C22: Subsidiary Management | D22: Managing subsidiary aligns with GPSC's policy or GPSC way of conduct, and can be controlled | E22: Managing subsidiary aligns with GPSC's policy or GPSC way of conduct, and cannot be controlled | F22: Managing subsidiary does not align with GPSC's policy or GPSC way of conduct | G22: Managing subsidiary does not align with GPSC's policy or GPSC way of conduct, and caues impact to GPSC business
B23: Image and Reputation | C23: GPSC Image to Public/Media | D23: - | E23: Moderate adveres impact from the public i.e. negative criticism in publication | F23: High adveres impact from the public i.e. negative feedback in media coverage | G23: Extreme adveres impact from the public i.e. local community protest
C24: GPSC Image to Community | D24: Minor impact on local community with informal feedback from various internal company channels | E24: Impact on local community with formal letter, but can be recovered within 1 week | F24: Impact on local community with formal letter, and be investigated from external regulator | G24: Extreme impact on community in wide area, and be ordered to stop operation or unable to operate due to the protest
C25: Environment | D25: Minor impact on the environment in surrounding areas without required additional action | E25: Impact on the environment which can be resolved within 1 day or need less than 1 week for restoration/rehabilitation | F25: High impact on the environment which can be resolved withinh 1 month or need 1-5 years for restoration/rehabilitation | G25: Extreme impact on the environment which can be resolved more than 1 month or need more than 5 years for restoration/rehabilitation
B26: Customers | C26: Volume of Product/Service | D26: General customer reduces purchasing of products/services. | E26: General customer stops purchasing of products/services. | F26: Main customer reduces purchasing of products/services. | G26: Main customer stops purchasing of products/services.
C27: Customer/Partner Satisfaction | D27: - | E27: Complaint of dissatisfacton from customer/partner is reported to the company | F27: Dissatisfaction from customer/partner is published in media channels | G27: Customer/partner sues the company
B28: People | C28: Health and Safety | D28: Employee, customer, partner, or stakeholder is injured and required medical first aid | E28: Employee, customer, partner, or stakeholder is injured and required medical treatment (OPD) | F28: Employee, customer, partner, or stakeholder is severely injured and required hospitalization (IPD). | G28: Employee, customer, partner, or stakeholder is permanent incapacity/dealth
C29: Employee Engagement | D29: Employees are dissatisfied, and the issues can be managed within the department | E29: Employees are dissatisfied, and need HR department to resolve the issues | F29: Employees are severely dissatisfied, and complaints are addressed through company channels | G29: Employees are extremely dissatisfied and expressed by resigning or protesting, which result in business interruption or legal dispute

Sheet Data1
A2: พื้นที่
A3: GPSC BKK : EnCo B - 5th floor
A4: GPSC BKK : EnCo B - 18th floor
A5: GPSC BKK : Empire Tower
A6: GPSC CBI : GIPP
A7: GPSC CBI : IPP1
A8: GPSC RYG : Central Warehouse
A9: GPSC RYG : CUP-1
A10: GPSC RYG : CUP-2
A11: GPSC RYG : CUP-3
A12: GPSC RYG : CUP-4
A13: GPSC RYG : Energy Storage Factory
... A18: GPSC RYG : SPP2/3
A21: BFS | B21: โครงการแฟลซ
A22: ESS | B22: ฝ่ายกลยุทธ์ซ่อมบำรุงโรงไฟฟ้า
A23: SCS | B23: ฝ่ายกลยุทธ์องค์กรและบริหารความเสี่ยง
A24: FFS | B24: ฝ่ายการเงินองค์กร
A25: CGS | B25: ฝ่ายการพาณิชย์ กลุ่มลูกค้า GPSCและบริหารสัญญา
A26: HES | B26: ฝ่ายความมั่นคงปลอดภัย อาชีวอนามัและสิ่งแวดล้อม
A27: PSS | B27: ฝ่ายจัดซื้อ
A28: EMS | B28: ฝ่ายซ่อมบำรุงโรงไฟฟ้า
A29: IAS | B29: ฝ่ายตรวจสอบภายในองค์กร
A30: BNS | B30: ฝ่ายนวัฒกรรมและเทคโนโลยีพลังงาน
A31: STS | B31: ฝ่ายบริหารการเปลี่ยนแปลงและความยั่งยืนองค์กร
A32: JCS | B32: ฝ่ายบริหารโครงการก่อสร้าง
... A63: CRV | B63: หน่วยลูกค้าสัมพันธ์ Glow
B66: 1 | C66: Financial
B67: 2 | C67: Strategy and Business Growth
B68: 3 | C68: Subsidiary Management
B69: 4 | C69: Operational Management
B70: 5 | C70: Quality, Safety, Health, and Environment
B71: 6 | C71: Human Resource and Organization Capability
B72: 7 | C72: Project Execution
B73: 8 | C73: Legal, Regulation and Compliance
A76: A. สูญเสียรายได้โดยตรง | C76: F - กำไรสุทธิต่ำกว่าเป้าหมาย
A77: B.ผลกระทบต่อลูกค้า | C77: F - กำไรขั้นต้นต่ำกว่าเป้าหมาย | E77: Likelyhood Level | F77: Impact Level
A78: C.ผลกระทบต่อชีวิตและความปลอดภัย | C78: F - รายได้ต่ำกว่าเป้าหมาย | E78: - | F78: -
A79: D.การหยุดชะงักของการปฏิบัติงาน/หน้าที่และงานประจำวัน | C79: F - ค่าใช้จ่ายสูงกว่าเป้าหมาย | E79: 1 | F79: 1
A80: E.ผลกระทบต่อชื่อเสียง | C80: F - ผลตอบแทนการลงทุนต่ำกว่าเป้าหมาย | E80: 2 | F80: 2
A81: F.ผลกระทบต่อสัญญา/ข้อตกลงระดับของการให้บริการ | C81: F - ประมาณลงทุนสูงกว่าที่ได้รับอนุมัติ | E81: 3 | F81: 3
A82: G.ไม่สอดคล้องตามกฎหมายกำหนด | C82: B - ประสิทธิผลของกระบวนการ | E82: 4 | F82: 4
C83: B - ผลิตภัณฑ์หรือบริการ
C84: B - การปฏิบัติตามกฎหมาย/กฎระเบียบ/ข้อบังคับ
C85: B - ระยะเวลาดำเนินโครงการล่าช้า
C86: B - การกำกับดูแลบริษัทในเครือ
C87: I - ภาพลักษณ์ต่อสาธารณะ/สื่อ
C88: I - ภาพลักษณ์ GPSC ต่อชุมชน
C89: I - สิ่งแวดล้อม
C90: C - ปริมาณขายผลิตภัณฑ์/บริการของ GPSC
C91: C - ความพึงพอใจของลูกค้า/คู่ค้า
C92: P - ความปลอดภัยและสุขภาพ
C93: P - ความพึงพอใจของพนักงาน

Sheet 2. BIA Process
A1: Process กระบวนการผลิต | B1: Impact Category ประเภทของผลกระทบที่เกิดขึ้น | C1: 1 Hour | D1: 4 Hour | E1: 8 Hour | F1: 12 Hour | G1: 24 Hour | H1: 3 Days | I1: 14 Days | J1: 30 Days | K1: Severity overtime scores | L1: Maximum Tolerable Period of Disruption (MTPD) | M1: Recovery Time Objective (RTO) | N1: Minimum Business Continuity Objective (MBCO) | O1: Posible Risk ความเสี่ยงที่เป็นไปได้ | P1: Existing Control มาตรการควบคุมที่มีอยู่ | Q1: Mitigation Plan (new countermeasure to reduce threats) | R1: Possible Risk Scores | S1: Existing Control Scores | T1: Mitigation Scores | U1: Prevention scores
A2: การรับวัตถุดิบ (น้ำDemin) | B2: การเงิน | C2: 1 | D2: 1 | E2: 1 | F2: 1 | G2: 2 | H2: 2 | I2: 3 | J2: 4 | K2: =SUM(C2*8)+(D2*7)+(E2*6)+(F2*5)+(G2*4)+(H2*3)+(I2*2)+(J2*1) -> 50 | L2: 24 Hours | M2: 1 Hours | N2: 1 | O2: 1.ถังกักเก็บน้ำชำรุดรั่วไหล 2.ท่อส่งเข้าระบบเสียหาย 3.อุปกรณ์ควบคุมใช้งานไม่ได้ | P2: 1.1จัดหาแหล่งน้ำสำรองจากแหล่งอื่นๆ เช่น WHA 1.2 จัดหาแหล่งน้ำสำรองจากแหล่งอื่นๆ เช่นเชื่อมระบบกับ Glow & CUP3 2.1มีการตรวจสอบ รายวัน 2.2มีทีมซ่อมบำรุง on call 24 hr 3.1มีการกำหนดแผนซ่อมบำรุงตามระยะเวลากำหนด 3.2มีสัญญาเข้าซ่อมบำรุงระบบ | R2: 6 | S2: 3 | T2: 0 | U2: =(S2+T2)/(R2*100) -> 0.005
A3: 2.การรับวัตถุดิบ (น้ำ Clearify water) | B3: การเงิน | C3: 1 | D3: 1 | E3: 1 | F3: 1 | G3: 2 | H3: 2 | I3: 2 | J3: 2 | K3: =SUM(C3*8)+(D3*7)+(E3*6)+(F3*5)+(G3*4)+(H3*3)+(I3*2)+(J3*1) -> 46 | L3: 24 Hours | M3: 1 Hours | N3: 1 | O3: 1.ถังกักเก็บน้ำชำรุดรั่วไหล 2.ท่อส่งเข้าระบบเสียหาย 3.อุปกรณ์ควบคุมใช้งานไม่ได้ | P3: 1.1จัดหาแหล่งน้ำxxx 2.1มีการตรวจสอบ รายวัน 2.2มีทีมซ่อมบำรุง on call 24 hr 3.1มีการกำหนดแผนซ่อมบำรุงตามระยะเวลากำหนด 3.2มีสัญญาเข้าซ่อมบำรุงระบบ | Q3: 1.ปรับลดปริมาณการใช้น้ำในกระบวนการผลิต 2.พิจารณาหาแหล่งน้ำสำรอง เช่น รถขนส่งน้ำจากภายนอก 3.หาแหล่งน้ำดิบเพิ่มอีกแหล่ง เช่น จากบริษัท EAST WATER | R3: 3 | S3: 5 | T3: 3 | U3: =(S3+T3)/(R3*100) -> 0.026666667
A4: 3.การรับวัตถุดิบ (สารเคมี) | B4: การเงิน | C4: 1 | D4: 1 | E4: 1 | F4: 1 | G4: 2 | H4: 2 | I4: 3 | J4: 4 | K4: =SUM(C4*8)+(D4*7)+(E4*6)+(F4*5)+(G4*4)+(H4*3)+(I4*2)+(J4*1) -> 50 | L4: 24 Hours | M4: 1 Hours | N4: 1 | O4: 1.ปริมาณสารเคมีไม่พอใช้งาน 2.ถังกักเก็บสารเคมีชำรุดรั่วไหล | P4: 1.1มี On call ผู้จำหน่ายสารเคมี (12 ชม.) 1.2มีการควบคุมปริมาณขั้นต่ำ (Max-Min) สารเคมี 2.1มีกำหนดการตรวจสอบและซ่อมบำรุงถังxxxxx | Q4: 1.จัดหาให้มีระบบถังสารเคมีสำรองเพิ่มอีก 1 ถัง ในการใช้งาน | R4: 2 | S4: 3 | T4: 1 | U4: =(S4+T4)/(R4*100) -> 0.02
A5: 4.การรับวัตถุดิบ (ก๊าซเชื้อเพลิง) | B5: การเงิน | C5: 1 | D5: 1 | E5: 1 | F5: 1 | G5: 2 | H5: 3 | I5: 4 | J5: 4 | K5: =SUM(C5*8)+(D5*7)+(E5*6)+(F5*5)+(G5*4)+(H5*3)+(I5*2)+(J5*1) -> 55 | L5: 48 Hours | M5: 1 Hours | N5: 1 | O5: 1.ไม่มีก๊าซหรือก๊าซไม่เพียงพอ 2.ท่อส่งเข้าระบบเสียหาย, อุปกรณ์ควบคุมใช้งานไม่ได้ 3.ไฟไหม้ | P5: 1.1มีการตรวจสอบ รายวัน 1.2มีทีมซ่อมบำรุง on call 24 hr 2.1มีการกำหนดแผนซ่อมบำรุงตามระยะเวลากำหนด 2.2มีสัญญาเข้าซ่อมบำรุงระบบ 3.1มีระบบดับเพลิงเครื่องจักร 2 ตัวเพื่อช่วยในการดับเพลิง | Q5: 1.ทำระบบไฟฟ้าส่งจ่ายจาก GLOW,PEA มาจ่ายให้กับลูกค้าแทน 2.ทำระบบท่อไอน้ำจาก GLOW มาจ่ายให้กับลูกค้า | R5: 3 | S5: 5 | T5: 2 | U5: =(S5+T5)/(R5*100) -> 0.023333333
A6: 5.การรับวัตถุดิบ (น้ำมันเชื้อเพลิงสำหรับระบบดับเพลิง) | B6: การเงิน | C6: 1 | D6: 1 | E6: 1 | F6: 1 | G6: 1 | H6: 1 | I6: 1 | J6: 1 | K6: =SUM(C6*8)+(D6*7)+(E6*6)+(F6*5)+(G6*4)+(H6*3)+(I6*2)+(J6*1) -> 36 | L6: 48 Hours | M6: 1 Hours | N6: 1 | O6: 1.ปริมาณน้ำมันเชื้อเพลิงไม่พอใช้งาน | P6: 1.มีระบบดับเพลิงเครื่องจักร 2 ตัวเพื่อช่วยในการดับเพลิง 2.มีการซ้อมแผนฉุกเฉินเป็นประจำทุกๆปี 3.มีการตรวจสอบอุปกรณ์เครื่องจักรตามแผนงานซ่อมบำรุงประจำปี | Q6: 1.จัดหาให้มีระบบน้ำมันเชื้อเพลิงสำรองเพิ่ม ในการใช้งาน 2.ติดต่อหน่วยงานที่เกี่ยวข้องเพื่อจัดเตรียมรถดับเพลิงในกรณีฉุกเฉิน (NPCS&E) | R6: 1 | S6: 3 | T6: 2 | U6: =(S6+T6)/(R6*100) -> 0.05
A7: 6.การรับวัตถุดิบ (ไฟฟ้าสำหรับ Start up process) | B7: การเงิน | C7: 1 | D7: 1 | E7: 1 | F7: 1 | G7: 2 | H7: 2 | I7: 3 | J7: 3 | K7: =SUM(C7*8)+(D7*7)+(E7*6)+(F7*5)+(G7*4)+(H7*3)+(I7*2)+(J7*1) -> 49 | L7: 24 Hours | M7: 1 Hours | N7: 1 | O7: 1.การผลิตหยุดชะงักเนื่องจากไม่มีกระแสไฟฟ้า 2.ไม่สามารถ Start กระบวนการผลิตได้กรณีที่สายส่ง EGAT/ PEA ชำรุดส่งผลให้ Plant Blackout | P7: 1.1มีสัญญาการรับไฟฟ้าจากการไฟฟ้า 2.1จัดทำแผนซ่อมบำรุง อุปกรณ์ตามระยะเวลาที่กำหนด 2.2มีทีม on call ซ่อมบำรุง 24 ชม. | Q7: 1.ศึกษาการจัดหาแหล่งไฟฟ้าสำรองในการ Start plant จากแหล่งอื่น เช่น Diesel GEN. 2.ศึกษาการเชื่อมต่อระบบกับ Glow ในการ Charge Back | R7: 2 | S7: 3 | T7: 2 | U7: =(S7+T7)/(R7*100) -> 0.025
A8: 7.เดินเครื่องระบบ BOP (Cooling, Air Compressor ) | B8: การเงิน | C8: 1 | D8: 1 | E8: 1 | F8: 1 | G8: 2 | H8: 2 | I8: 3 | J8: 3 | K8: =SUM(C8*8)+(D8*7)+(E8*6)+(F8*5)+(G8*4)+(H8*3)+(I8*2)+(J8*1) -> 49 | L8: 7 Days | M8: 7 Days | N8: 1 | O8: 1. การผลิตหยุดเนื่องจากไม่มีกระแสไฟฟ้า 2.การผลิตหยุดเนื่องจากไม่มีน้ำ | P8: 1.1มีระบบ อัตโนมัติควบคุม 2 ตัวขึ้นไปในการใช้งานกระบวนการผลิต 1.2มีระบบ by pass 1.3มีระบบควบคุมอัตโนมัติ (Emergency) และระบบป้องกันอุปกรณ์(Protection)) เพื่อป้องกันเครื่องจักรเสียหาย 1.4มีการติดตั้งอุปกรณ์สำรอง 1.5มีแผนซ่อมบำรุงรักษาประจำปี/ ประจำเดือน 2.1มีการจด log sheet เพื่อประเมินค่าของอุปกรณ์ว่าผิดปกติหรือไม่และ Visual check ขณะทำการจด log sheet | Q8: 1.สำรองติดตั้ง Mobile Air compressor ชั่วคราวโดยทำสัญญากับ Supplier | R8: 2 | S8: 6 | T8: 1 | U8: =(S8+T8)/(R8*100) -> 0.035
A9: 8.เดินเครื่องระบบ Fuel Gas | B9: การเงิน | C9: 1 | D9: 1 | E9: 1 | F9: 1 | G9: 2 | H9: 2 | I9: 3 | J9: 3 | K9: =SUM(C9*8)+(D9*7)+(E9*6)+(F9*5)+(G9*4)+(H9*3)+(I9*2)+(J9*1) -> 49 | L9: 7 Days | M9: 7 Days | N9: 1 | O9: 1.ไม่สามารถเดินเครื่องได้เนื่องจากไม่มีก๊าซทำให้ระบบเครื่องจักรการผลิตหยุดชะงัก | P9: 1.1 มีแผนซ่อมบำรุงรักษาประจำปี/ ประจำเดือน 1.2 มีการติดตั้งอุปกรณ์สำรอง 1.3 มีการจด log sheet เพื่อประเมินค่าของอุปกรณ์ว่าผิดปกติหรือไม่และ Visual check ขณะทำการจด log sheet | Q9: 1.ให้มีทีมซ่อมบำรุง และชิ้นส่วนอะไหล่ ตลอด24 ชม. เพื่อไม่ต้องเสียเวลาในการรอคอย ในขณะที่ตาม oncall | R9: 1 | S9: 3 | T9: 1 | U9: =(S9+T9)/(R9*100) -> 0.04
A10: 9.เดินเครื่องระบบ Demin, Condensate และ Neutralization. | B10: การเงิน | C10: 1 | D10: 1 | E10: 1 | F10: 1 | G10: 2 | H10: 2 | I10: 3 | J10: 3 | K10: =SUM(C10*8)+(D10*7)+(E10*6)+(F10*5)+(G10*4)+(H10*3)+(I10*2)+(J10*1) -> 49 | L10: 7 Days | M10: 7 Days | N10: 1 | O10: 1.ไม่สามารถผลิตน้ำ Demin ได้เนื่องจากไม่มีกระแสไฟฟ้า 2.ปริมาณน้ำ Demin ไม่เพียงพอต่อการใช้งานในการบวนการผลิตและส่งให้ลูกค้าได้ | P10: 1.1มีการติดตั้งระบบสำรองในการผลิตนำ Demin 4 units, Condensate 2 units. 1.2ระบบ Pump Neutralization มี 2 unit สามารถได้สลับกันได้กรณีอีกตัวเสีย 2.1มีระบบนำ RO เพิ่มอีก 2 units ในกระบวนการผลิตเพื่อช่วยผลิตน้ำได้ 2.2รับน้ำ Demin จาก WHA | Q10: 1.พิจารณาหาแหล่งน้ำสำรอง เช่น รถขนส่ง 2.จัดหาแหล่งน้ำสำรองจากแหล่งอื่นๆ เช่น เชื่อมระบบกับ Glow & CUP3 | R10: 2 | S10: 4 | T10: 2 | U10: =(S10+T10)/(R10*100) -> 0.03
A11: 10.เดินเครื่องระบบ BFW และ Deaerator | B11: การเงิน | C11: 1 | D11: 1 | E11: 1 | F11: 1 | G11: 2 | H11: 2 | I11: 3 | J11: 3 | K11: =SUM(C11*8)+(D11*7)+(E11*6)+(F11*5)+(G11*4)+(H11*3)+(I11*2)+(J11*1) -> 49 | L11: 7 Days | M11: 7 Days | N11: 1 | O11: 1. ไม่สามารถเดินระบบได้เนื่องจากไม่มีกระแสไฟฟ้า 2.การผลิตหยุดเนื่องจากไม่มีน้ำ | P11: 1.1xxxxx 2.1xxxxx | Q11: 1.ให้มีทีมซ่อมบำรุง และชิ้นส่วนอะไหล่ ตลอด24 ชม. เพื่อไม่ต้องเสียเวลาในการรอคอย ในขณะที่ตาม oncall 2.หาแหล่งน้ำอื่นๆเช่น BFW จาก CUP3 ส่งให้ลูกค้าแทนได้ | R11: 2 | S11: 2 | T11: 2 | U11: =(S11+T11)/(R11*100) -> 0.02
A12: 11.เดินเครื่อง Aux Boiler , HRSG และ Emission Control. | B12: การเงิน | C12: 1 | D12: 1 | E12: 1 | F12: 1 | G12: 2 | H12: 2 | I12: 3 | J12: 3 | K12: =SUM(C12*8)+(D12*7)+(E12*6)+(F12*5)+(G12*4)+(H12*3)+(I12*2)+(J12*1) -> 49 | L12: 7 Days | M12: 7 Days | N12: 1 | O12: 1. การผลิตไอน้ำหยุดเนื่องจากไม่มีกระแสไฟฟ้า 2.การผลิตไอน้ำหยุดเนื่องจากไม่มีน้ำ 3.การผลิตไอน้ำหยุดเนื่องจากไม่มีเชื้อเพลิง 4.การผลิตไอน้ำหยุดเนื่องจากปริมาณสารเคมีไม่พอใช้งาน 5.ไม่สอดคล้องตามกฏหมาย ค่า Emission เกินมาตราฐาน เนื่องจากไม่มีสารเคมีใช้ในกระบวนการผลิต (No chemical) | P12: 1.1มีสัญญาการรับไฟฟ้าจากการไฟฟ้า 2.1xxxx 3.1xxxxx 4.1มี On call ผู้จำหน่ายสารเคมี (12 ชม.) 4.2มีการควบคุมปริมาณขั้นต่ำ (Max-Min) สารเคมี 5.1 มีระบบควบคุม Emission และระบบเตือนเมื่อค่าเกิดค่าที่ควบคุม | Q12: 1.ให้มีทีมซ่อมบำรุง และชิ้นส่วนอะไหล่ ตลอด24 ชม. เพื่อไม่ต้องเสียเวลาในการรอคอย ในขณะที่ตาม oncall 2.หาแหล่งไอน้ำอื่นๆ เช่น รับจาก CUP3,CUP4&GLOW ส่งให้ลูกค้าแทนได้ | R12: 5 | S12: 5 | T12: 2 | U12: =(S12+T12)/(R12*100) -> 0.014
A13: 12.เดินเครื่องระบบ GTG | B13: การเงิน | C13: 1 | D13: 1 | E13: 1 | F13: 1 | G13: 2 | H13: 2 | I13: 3 | J13: 3 | K13: =SUM(C13*8)+(D13*7)+(E13*6)+(F13*5)+(G13*4)+(H13*3)+(I13*2)+(J13*1) -> 49 | L13: 140 Days | M13: 140 Days | N13: 1 | O13: 1. การผลิตไฟฟ้าหยุดเนื่องจากไม่มีกระแสไฟฟ้า 2.การผลิตไฟฟ้าหยุดเนื่องจากไม่มีก๊าซ หรือก๊าซไม่เพียงพอ 3.ไฟไหม้ | P13: 1.1xxx 2.1xxx 3.1มีระบบควบคุมอัตโนมัติ (Emergency) และระบบป้องกันอุปกรณ์(Protection)) เพื่อป้องกันเครื่องจักรเสียหาย 3.2มีการจัดทำแผนตอบโต้ฉุกเฉิน ตาม Mitigation plan ภายในการเดินเครื่อง 3.3มีแผนซ่อมบำรุงรักษาประจำปี/ ประจำเดือน 3.4มีแผนการตรวจสอบระบบเครื่องจักร ตามระยะเวลาที่กำหนด | Q13: 1.ให้มีทีมซ่อมบำรุง และชิ้นส่วนอะไหล่ ตลอด24 ชม. เพื่อไม่ต้องเสียเวลาในการรอคอย ในขณะที่ตาม oncall 2.หาแหล่งไฟฟ้าอื่นๆ เช่น รับจาก PEA,CUP4&GLOW ส่งให้ลูกค้าแทนได้ | R13: 3 | S13: 4 | T13: 2 | U13: =(S13+T13)/(R13*100) -> 0.02
A14: 13.เดินเครื่องระบบส่งผ่านผลิตภัณฑ์ (สายไฟฟ้า) | B14: การเงิน | C14: 1 | D14: 1 | E14: 1 | F14: 1 | G14: 2 | H14: 2 | I14: 3 | J14: 3 | K14: =SUM(C14*8)+(D14*7)+(E14*6)+(F14*5)+(G14*4)+(H14*3)+(I14*2)+(J14*1) -> 49 | L14: 7 Days | M14: 7 Days | N14: 1 | O14: 1.ไม่มีกระแสไฟฟ้า 2.สายส่งไฟฟ้าชำรุดจึงไม่สามารถส่งกระแสไฟฟ้าให้กับลูกค้าได้ | P14: 1.1xxx 2.1มีการตรวจสอบอุปกรณ์ป้องกัน โดยพนักงานเดินเครื่อง และสายส่งโดยทีมงานซ่อมบำรุง อย่างประจำ 2.2มีแผนการซ่อมบำรุงรักษาระบบส่งจ่ายไฟฟ้ารายปี มีแผนการตรวจสอบระบบส่งจ่ายไฟฟ้าตามระยะเวลาที่กำหนด 2.3มีทีมปฏิบัติการในกรณีฉุกเฉิน (on-call) ตลอด 24 ชม. สำหรับงานซ่อมเร่งด่วน 2.4จัดเตรียมสายไฟฟ้าสำรองไว้เปลี่ยนในกรณีเกิดเหตุฉุกเฉิน 2.5 มีระบบควบคุมอัตโนมัติ (Emergency) และระบบป้องกันอุปกรณ์(Protection) เพื่อป้องกันเครื่องจักรเสียหาย | Q14: 1.เพิ่มระบบสายส่งเป็น 2 Feeder ใช้งาน 1 Feeder Standby เตรียมพร้อมอีก 1 Feeder (EGAT) 2.สลับแหล่งจ่ายไฟลูกค้า GPSC ไปรับยัง บริษัท Glow | R14: 2 | S14: 6 | T14: 2 | U14: =(S14+T14)/(R14*100) -> 0.04
... A20: 19.ระบบควบคุมการผลิต ( UPS ,DCS) | B20: การเงิน | C20: 1 | D20: 1 | E20: 1 | F20: 1 | G20: 2 | H20: 2 | I20: 3 | J20: 3 | K20: =SUM(C20*8)+(D20*7)+(E20*6)+(F20*5)+(G20*4)+(H20*3)+(I20*2)+(J20*1) -> 49 | L20: 60 Days | M20: 60 Days | N20: 1 | O20: 1.ไม่มีกระแสไฟฟ้าจ่ายเข้าระบบ 2.ระบบ UPS failedและ หรือ ระบบ DCS failed | P20: 1.1มีระบบควบคุมเป็นแบบ ขนาน 2 ระบบ 2.1มีการตรวจสอบ PM ระบบ 2.2ในกรณีที่ระบบ failed จะมีการแจ้งเตือนและระบบ สำรองจะเข้ามาควบคุมแทน 2.3มี manual valve ที่หน้างาน 2.4มีby pass control valve ที่หน้างาน 2.5มีชำนาญการระบบ DCS vender oncall 24ชม. | Q20: 1.ให้มีทีมซ่อมบำรุงชำนาญเฉพาะทาง ประสานงานกับทาง Vender และมีการเตรียมชิ้นส่วนอะไหล่ ตลอด24 ชม. เพื่อใช้งานและไม่ต้องเสียเวลาในการรอคอย ในขณะที่ตาม oncall 2.ให้มีทีมซ่อมสายส่งของ Vender (Contactor)ตลอด24ชม. | R20: 2 | S20: 6 | T20: 2 | U20: =(S20+T20)/(R20*100) -> 0.04

Sheet 3.RA Process
A1: No. | B1: Product & Service ผลิตภัณฑ์และบริการ | C1: Process กระบวนการผลิต | D1: Risk Category ประเภทความเสี่ยง | E1: Impact Type ประเภทผลกระทบ | F1: Sub-Dimension | G1: Posible Risk ความเสี่ยงที่เป็นไปได้ | H1: Existing Control มาตรการควบคุมที่มีอยู่ | I1: Risk Assessment | P1: Mitigation Plan (new countermeasure to reduce threats) | Q1: Time Frame | S1: Responsible Person | T1: Target
I2: I | J2: L | K2: R | L2: R | M2: MTPD | N2: RTO | O2: MBCO | Q2: From | R2: To | T2: I | U2: L | V2: R | W2: R
A3: 1 | B3: 1.การผลิตไฟฟ้า | C3: การรับวัตถุดิบ (น้ำDemin) | D3: Operational Management | E3: 6.กระบวนการทางธุรกิจและการปฏิบัติการ | F3: ประสิทธิผลของกระบวนการ | G3: 1.ถังกักเก็บน้ำชำรุดรั่วไหล | H3: 1.1จัดหาแหล่งน้ำสำรองจากแหล่งอื่นๆ เช่น WHA 1.2 จัดหาแหล่งน้ำสำรองจากแหล่งอื่นๆ เช่นเชื่อมระบบกับ Glow & CUP3 | I3: 4 | J3: 1 | K3: =L3 -> E4 | L3: =IF(AND(J3=1,I3=1),"L16",IF(AND(J3=1,I3=2),"L14",IF(AND(J3=1,I3=3),"M11",IF(AND(J3=1,I3=4),"E4",IF(AND(J3=2,I3=1),"L15",IF(AND(J3=2,I3=2),"M12",IF(AND(J3=2,I3=3),"H7",IF(AND(J3=2,I3=4),"E3",IF(AND(J3=3,I3=1),"M13",IF(AND(J3=3,I3=2),"H9",IF(AND(J3=3,I3=3),"E6",IF(AND(J3=4,I3=4),"E2",IF(AND(J3=4,I3=1),"H10",IF(AND(I3=2,J3=4),"H8",IF(AND(J3=4,I3=3),"E5",IF(AND(J3=4,I3=4),"E1",FALSE)))))))))))))))) -> E4 | M3: ='2.2 BIA Process'!N8 -> 24 ชม | N3: ='2.2 BIA Process'!O8 -> 1 ชม | O3: ='2.2 BIA Process'!P8 -> 1 | P3: - | Q3: - | R3: - | S3: - | T3: 4 | U3: 1 | V3: =W3 -> E4 | W3: =IF(AND(U3=1,T3=1),"L16",IF(AND(U3=1,T3=2),"L14",IF(AND(U3=1,T3=3),"M11",IF(AND(U3=1,T3=4),"E4",IF(AND(U3=2,T3=1),"L15",IF(AND(U3=2,T3=2),"M12",IF(AND(U3=2,T3=3),"H7",IF(AND(U3=2,T3=4),"E3",IF(AND(U3=3,T3=1),"M13",IF(AND(U3=3,T3=2),"H9",IF(AND(U3=3,T3=3),"E6",IF(AND(U3=4,T3=4),"E2",IF(AND(U3=4,T3=1),"H10",IF(AND(U3=2,T3=4),"H8",IF(AND(U3=4,T3=3),"E5",IF(AND(U3=4,T3=4),"E1",FALSE)))))))))))))))) -> E4
F4: ประสิทธิผลของกระบวนการ | G4: 2.ท่อส่งเข้าระบบเสียหาย | H4: 2.1 มีการตรวจสอบ รายวัน 2.2มีทีมซ่อมบำรุง on call 24 hr | I4: 4 | J4: 1 | K4: =L3 -> E4
F5: ผลิตภัณฑ์หรือ บริการ | G5: 3.อุปกรณ์ควบคุมใช้งานไม่ได้ | H5: 3.1มีการกำหนดแผนซ่อมบำรุงตามระยะเวลากำหนด 3.2มีสัญญาเข้าซ่อมบำรุงระบบ | I5: 3 | J5: 1 | K5: =L7 -> M11
A6: 2 | B6: 1.การผลิตไฟฟ้า | C6: การรับวัตถุดิบ (น้ำ Clearify water) | D6: Operational Management | E6: 6.กระบวนการทางธุรกิจและการปฏิบัติการ | G6: 1.ถังกักเก็บน้ำชำรุดรั่วไหล 2.ท่อส่งเข้าระบบเสียหาย 3.อุปกรณ์ควบคุมใช้งานไม่ได้ | H6: 1.1จัดหาแหล่งน้ำxxx 2.1มีการตรวจสอบ รายวัน 2.2มีทีมซ่อมบำรุง on call 24 hr 3.1มีการกำหนดแผนซ่อมบำรุงตามระยะเวลากำหนด 3.2มีสัญญาเข้าซ่อมบำรุงระบบ | I6: 4 | J6: 1 | K6: =L6 -> E4 | L6: =IF(AND(J6=1,I6=1),"L16",IF(AND(J6=1,I6=2),"L14",IF(AND(J6=1,I6=3),"M11",IF(AND(J6=1,I6=4),"E4",IF(AND(J6=2,I6=1),"L15",IF(AND(J6=2,I6=2),"M12",IF(AND(J6=2,I6=3),"H7",IF(AND(J6=2,I6=4),"E3",IF(AND(J6=3,I6=1),"M13",IF(AND(J6=3,I6=2),"H9",IF(AND(J6=3,I6=3),"E6",IF(AND(J6=4,I6=4),"E2",IF(AND(J6=4,I6=1),"H10",IF(AND(I6=2,J6=4),"H8",IF(AND(J6=4,I6=3),"E5",IF(AND(J6=4,I6=4),"E1",FALSE)))))))))))))))) -> E4 | M6: ='2.2 BIA Process'!N9 -> 24 ชม | N6: ='2.2 BIA Process'!O9 -> 1 ชม | O6: ='2.2 BIA Process'!P9 -> 1 | P6: 1.ปรับลดปริมาณการใช้น้ำในกระบวนการผลิต 2.พิจารณาหาแหล่งน้ำสำรอง เช่น รถขนส่งน้ำจากภายนอก 3.หาแหล่งน้ำดิบเพิ่มอีกแหล่ง เช่น จากบริษัท EAST WATER | Q6: Jan | R6: Dec | S6: Operation | T6: 3 | U6: 1 | V6: =W6 -> M11 | W6: =IF(AND(U6=1,T6=1),"L16",IF(AND(U6=1,T6=2),"L14",IF(AND(U6=1,T6=3),"M11",IF(AND(U6=1,T6=4),"E4",IF(AND(U6=2,T6=1),"L15",IF(AND(U6=2,T6=2),"M12",IF(AND(U6=2,T6=3),"H7",IF(AND(U6=2,T6=4),"E3",IF(AND(U6=3,T6=1),"M13",IF(AND(U6=3,T6=2),"H9",IF(AND(U6=3,T6=3),"E6",IF(AND(U6=4,T6=4),"E2",IF(AND(U6=4,T6=1),"H10",IF(AND(U6=2,T6=4),"H8",IF(AND(U6=4,T6=3),"E5",IF(AND(U6=4,T6=4),"E1",FALSE)))))))))))))))) -> M11
A7: 3 | B7: 1.การผลิตไฟฟ้า | C7: การรับวัตถุดิบ (สารเคมี) | D7: Operational Management | E7: 6.กระบวนการทางธุรกิจและการปฏิบัติการ | G7: 1.ปริมาณสารเคมีไม่พอใช้งาน 2.ถังกักเก็บสารเคมีชำรุดรั่วไหล | H7: 1.1มี On call ผู้จำหน่ายสารเคมี (12 ชม.) 1.2มีการควบคุมปริมาณขั้นต่ำ (Max-Min) สารเคมี 2.1มีกำหนดการตรวจสอบและซ่อมบำรุงถังxxxxx | I7: 3 | J7: 1 | K7: =L7 -> M11 | L7: =IF(AND(J7=1,I7=1),"L16",IF(AND(J7=1,I7=2),"L14",IF(AND(J7=1,I7=3),"M11",IF(AND(J7=1,I7=4),"E4",IF(AND(J7=2,I7=1),"L15",IF(AND(J7=2,I7=2),"M12",IF(AND(J7=2,I7=3),"H7",IF(AND(J7=2,I7=4),"E3",IF(AND(J7=3,I7=1),"M13",IF(AND(J7=3,I7=2),"H9",IF(AND(J7=3,I7=3),"E6",IF(AND(J7=4,I7=4),"E2",IF(AND(J7=4,I7=1),"H10",IF(AND(I7=2,J7=4),"H8",IF(AND(J7=4,I7=3),"E5",IF(AND(J7=4,I7=4),"E1",FALSE)))))))))))))))) -> M11 | M7: ='2.2 BIA Process'!N10 -> 24 ชม | N7: ='2.2 BIA Process'!O10 -> 1 ชม | O7: ='2.2 BIA Process'!P10 -> 1 | P7: 1.จัดหาให้มีระบบถังสารเคมีสำรองเพิ่มอีก 1 ถัง ในการใช้งาน | Q7: Jan | R7: Dec | S7: Operation | T7: 3 | U7: 1 | V7: =W7 -> M11 | W7: =IF(AND(U7=1,T7=1),"L16",IF(AND(U7=1,T7=2),"L14",IF(AND(U7=1,T7=3),"M11",IF(AND(U7=1,T7=4),"E4",IF(AND(U7=2,T7=1),"L15",IF(AND(U7=2,T7=2),"M12",IF(AND(U7=2,T7=3),"H7",IF(AND(U7=2,T7=4),"E3",IF(AND(U7=3,T7=1),"M13",IF(AND(U7=3,T7=2),"H9",IF(AND(U7=3,T7=3),"E6",IF(AND(U7=4,T7=4),"E2",IF(AND(U7=4,T7=1),"H10",IF(AND(U7=2,T7=4),"H8",IF(AND(U7=4,T7=3),"E5",IF(AND(U7=4,T7=4),"E1",FALSE)))))))))))))))) -> M11
A8: 4 | B8: 1.การผลิตไฟฟ้า | C8: การรับวัตถุดิบ (ก๊าซเชื้อเพลิง) | D8: Operational Management | E8: 6.กระบวนการทางธุรกิจและการปฏิบัติการ | G8: 1.ไม่มีก๊าซหรือก๊าซไม่เพียงพอ 2.ท่อส่งเข้าระบบเสียหาย, อุปกรณ์ควบคุมใช้งานไม่ได้ 3.ไฟไหม้ | H8: 1.1มีการตรวจสอบ รายวัน 1.2มีทีมซ่อมบำรุง on call 24 hr 2.1มีการกำหนดแผนซ่อมบำรุงตามระยะเวลากำหนด 2.2มีสัญญาเข้าซ่อมบำรุงระบบ 3.1มีระบบดับเพลิงเครื่องจักร 2 ตัวเพื่อช่วยในการดับเพลิง | I8: 4 | J8: 1 | K8: =L8 -> E4 | L8: =IF(AND(J8=1,I8=1),"L16",IF(AND(J8=1,I8=2),"L14",IF(AND(J8=1,I8=3),"M11",IF(AND(J8=1,I8=4),"E4",IF(AND(J8=2,I8=1),"L15",IF(AND(J8=2,I8=2),"M12",IF(AND(J8=2,I8=3),"H7",IF(AND(J8=2,I8=4),"E3",IF(AND(J8=3,I8=1),"M13",IF(AND(J8=3,I8=2),"H9",IF(AND(J8=3,I8=3),"E6",IF(AND(J8=4,I8=4),"E2",IF(AND(J8=4,I8=1),"H10",IF(AND(I8=2,J8=4),"H8",IF(AND(J8=4,I8=3),"E5",IF(AND(J8=4,I8=4),"E1",FALSE)))))))))))))))) -> E4 | M8: ='2.2 BIA Process'!N11 -> 48 ชม | N8: ='2.2 BIA Process'!O11 -> 1 ชม | O8: ='2.2 BIA Process'!P11 -> 1 | P8: 1.ทำระบบไฟฟ้าส่งจ่ายจาก GLOW,PEA มาจ่ายให้กับลูกค้าแทน 2.ทำระบบท่อไอน้ำจาก GLOW มาจ่ายให้กับลูกค้า | Q8: Jan | R8: Dec | S8: Operation | T8: 3 | U8: 1 | V8: =W8 -> M11 | W8: =IF(AND(U8=1,T8=1),"L16",IF(AND(U8=1,T8=2),"L14",IF(AND(U8=1,T8=3),"M11",IF(AND(U8=1,T8=4),"E4",IF(AND(U8=2,T8=1),"L15",IF(AND(U8=2,T8=2),"M12",IF(AND(U8=2,T8=3),"H7",IF(AND(U8=2,T8=4),"E3",IF(AND(U8=3,T8=1),"M13",IF(AND(U8=3,T8=2),"H9",IF(AND(U8=3,T8=3),"E6",IF(AND(U8=4,T8=4),"E2",IF(AND(U8=4,T8=1),"H10",IF(AND(U8=2,T8=4),"H8",IF(AND(U8=4,T8=3),"E5",IF(AND(U8=4,T8=4),"E1",FALSE)))))))))))))))) -> M11
A9: 5 | B9: 1.การผลิตไฟฟ้า | C9: การรับวัตถุดิบ (น้ำมันเชื้อเพลิงสำหรับระบบดับเพลิง) | D9: Operational Management | E9: 6.กระบวนการทางธุรกิจและการปฏิบัติการ | G9: 1.ปริมาณน้ำมันเชื้อเพลิงไม่พอใช้งาน | H9: 1.มีระบบดับเพลิงเครื่องจักร 2 ตัวเพื่อช่วยในการดับเพลิง 2.มีการซ้อมแผนฉุกเฉินเป็นประจำทุกๆปี 3.มีการตรวจสอบอุปกรณ์เครื่องจักรตามแผนงานซ่อมบำรุงประจำปี | I9: 2 | J9: 2 | K9: =L9 -> M12 | L9: =IF(AND(J9=1,I9=1),"L16",IF(AND(J9=1,I9=2),"L14",IF(AND(J9=1,I9=3),"M11",IF(AND(J9=1,I9=4),"E4",IF(AND(J9=2,I9=1),"L15",IF(AND(J9=2,I9=2),"M12",IF(AND(J9=2,I9=3),"H7",IF(AND(J9=2,I9=4),"E3",IF(AND(J9=3,I9=1),"M13",IF(AND(J9=3,I9=2),"H9",IF(AND(J9=3,I9=3),"E6",IF(AND(J9=4,I9=4),"E2",IF(AND(J9=4,I9=1),"H10",IF(AND(I9=2,J9=4),"H8",IF(AND(J9=4,I9=3),"E5",IF(AND(J9=4,I9=4),"E1",FALSE)))))))))))))))) -> M12 | M9: ='2.2 BIA Process'!N12 -> 48 ชม | N9: ='2.2 BIA Process'!O12 -> 1 ชม | O9: ='2.2 BIA Process'!P12 -> 1 | P9: 1.จัดหาให้มีระบบน้ำมันเชื้อเพลิงสำรองเพิ่ม ในการใช้งาน 2.ติดต่อหน่วยงานที่เกี่ยวข้องเพื่อจัดเตรียมรถดับเพลิงในกรณีฉุกเฉิน (NPCS&E) | Q9: Jan | R9: Dec | S9: SSHE | T9: 1 | U9: 2 | V9: =W9 -> L15 | W9: =IF(AND(U9=1,T9=1),"L16",IF(AND(U9=1,T9=2),"L14",IF(AND(U9=1,T9=3),"M11",IF(AND(U9=1,T9=4),"E4",IF(AND(U9=2,T9=1),"L15",IF(AND(U9=2,T9=2),"M12",IF(AND(U9=2,T9=3),"H7",IF(AND(U9=2,T9=4),"E3",IF(AND(U9=3,T9=1),"M13",IF(AND(U9=3,T9=2),"H9",IF(AND(U9=3,T9=3),"E6",IF(AND(U9=4,T9=4),"E2",IF(AND(U9=4,T9=1),"H10",IF(AND(U9=2,T9=4),"H8",IF(AND(U9=4,T9=3),"E5",IF(AND(U9=4,T9=4),"E1",FALSE)))))))))))))))) -> L15
A10: 6 | B10: 1.การผลิตไฟฟ้า | C10: การรับวัตถุดิบ (ไฟฟ้าสำหรับ Start up process) | D10: Operational Management | E10: 6.กระบวนการทางธุรกิจและการปฏิบัติการ | G10: 1.การผลิตหยุดชะงักเนื่องจากไม่มีกระแสไฟฟ้า 2.ไม่สามารถ Start กระบวนการผลิตได้กรณีที่สายส่ง EGAT/ PEA ชำรุดส่งผลให้ Plant Blackout | H10: 1.1มีสัญญาการรับไฟฟ้าจากการไฟฟ้า 2.1จัดทำแผนซ่อมบำรุง อุปกรณ์ตามระยะเวลาที่กำหนด 2.2มีทีม on call ซ่อมบำรุง 24 ชม. | I10: 3 | J10: 1 | K10: =L10 -> M11 | L10: =IF(AND(J10=1,I10=1),"L16",IF(AND(J10=1,I10=2),"L14",IF(AND(J10=1,I10=3),"M11",IF(AND(J10=1,I10=4),"E4",IF(AND(J10=2,I10=1),"L15",IF(AND(J10=2,I10=2),"M12",IF(AND(J10=2,I10=3),"H7",IF(AND(J10=2,I10=4),"E3",IF(AND(J10=3,I10=1),"M13",IF(AND(J10=3,I10=2),"H9",IF(AND(J10=3,I10=3),"E6",IF(AND(J10=4,I10=4),"E2",IF(AND(J10=4,I10=1),"H10",IF(AND(I10=2,J10=4),"H8",IF(AND(J10=4,I10=3),"E5",IF(AND(J10=4,I10=4),"E1",FALSE)))))))))))))))) -> M11 | M10: ='2.2 BIA Process'!N13 -> 24 ชม | N10: ='2.2 BIA Process'!O13 -> 1 ชม | O10: ='2.2 BIA Process'!P13 -> 1 | P10: 1.ศึกษาการจัดหาแหล่งไฟฟ้าสำรองในการ Start plant จากแหล่งอื่น เช่น Diesel GEN. 2.ศึกษาการเชื่อมต่อระบบกับ Glow ในการ Charge Back | Q10: Jan | R10: Dec | S10: Engineering | T10: 2 | U10: 1 | V10: =W10 -> L14 | W10: =IF(AND(U10=1,T10=1),"L16",IF(AND(U10=1,T10=2),"L14",IF(AND(U10=1,T10=3),"M11",IF(AND(U10=1,T10=4),"E4",IF(AND(U10=2,T10=1),"L15",IF(AND(U10=2,T10=2),"M12",IF(AND(U10=2,T10=3),"H7",IF(AND(U10=2,T10=4),"E3",IF(AND(U10=3,T10=1),"M13",IF(AND(U10=3,T10=2),"H9",IF(AND(U10=3,T10=3),"E6",IF(AND(U10=4,T10=4),"E2",IF(AND(U10=4,T10=1),"H10",IF(AND(U10=2,T10=4),"H8",IF(AND(U10=4,T10=3),"E5",IF(AND(U10=4,T10=4),"E1",FALSE)))))))))))))))) -> L14
A11: 7 | B11: 1.การผลิตไฟฟ้า | C11: เดินเครื่องระบบ BOP (Cooling, Air Compressor ) | D11: Operational Management | E11: 6.กระบวนการทางธุรกิจและการปฏิบัติการ | G11: 1. การผลิตหยุดเนื่องจากไม่มีกระแสไฟฟ้า 2.การผลิตหยุดเนื่องจากไม่มีน้ำ | H11: 1.1มีระบบ อัตโนมัติควบคุม 2 ตัวขึ้นไปในการใช้งานกระบวนการผลิต 1.2มีระบบ by pass 1.3มีระบบควบคุมอัตโนมัติ (Emergency) และระบบป้องกันอุปกรณ์(Protection)) เพื่อป้องกันเครื่องจักรเสียหาย 1.4มีการติดตั้งอุปกรณ์สำรอง 1.5มีแผนซ่อมบำรุงรักษาประจำปี/ ประจำเดือน 2.1มีการจด log sheet เพื่อประเมินค่าของอุปกรณ์ว่าผิดปกติหรือไม่และ Visual check ขณะทำการจด log sheet | I11: 3 | J11: 1 | K11: =L11 -> M11 | L11: =IF(AND(J11=1,I11=1),"L16",IF(AND(J11=1,I11=2),"L14",IF(AND(J11=1,I11=3),"M11",IF(AND(J11=1,I11=4),"E4",IF(AND(J11=2,I11=1),"L15",IF(AND(J11=2,I11=2),"M12",IF(AND(J11=2,I11=3),"H7",IF(AND(J11=2,I11=4),"E3",IF(AND(J11=3,I11=1),"M13",IF(AND(J11=3,I11=2),"H9",IF(AND(J11=3,I11=3),"E6",IF(AND(J11=4,I11=4),"E2",IF(AND(J11=4,I11=1),"H10",IF(AND(I11=2,J11=4),"H8",IF(AND(J11=4,I11=3),"E5",IF(AND(J11=4,I11=4),"E1",FALSE)))))))))))))))) -> M11 | M11: ='2.2 BIA Process'!N14 -> 7 วัน | N11: ='2.2 BIA Process'!O14 -> 7 วัน | O11: ='2.2 BIA Process'!P14 -> 1 | P11: 1.สำรองติดตั้ง Mobile Air compressor ชั่วคราวโดยทำสัญญากับ Supplier | Q11: Jan | R11: Dec | S11: Maintenance | T11: 1 | U11: 1 | V11: =W11 -> L16 | W11: =IF(AND(U11=1,T11=1),"L16",IF(AND(U11=1,T11=2),"L14",IF(AND(U11=1,T11=3),"M11",IF(AND(U11=1,T11=4),"E4",IF(AND(U11=2,T11=1),"L15",IF(AND(U11=2,T11=2),"M12",IF(AND(U11=2,T11=3),"H7",IF(AND(U11=2,T11=4),"E3",IF(AND(U11=3,T11=1),"M13",IF(AND(U11=3,T11=2),"H9",IF(AND(U11=3,T11=3),"E6",IF(AND(U11=4,T11=4),"E2",IF(AND(U11=4,T11=1),"H10",IF(AND(U11=2,T11=4),"H8",IF(AND(U11=4,T11=3),"E5",IF(AND(U11=4,T11=4),"E1",FALSE)))))))))))))))) -> L16
A12: 8 | B12: 1.การผลิตไฟฟ้า | C12: เดินเครื่องระบบ Fuel Gas | D12: Operational Management | E12: 6.กระบวนการทางธุรกิจและการปฏิบัติการ | G12: 1.ไม่สามารถเดินเครื่องได้เนื่องจากไม่มีก๊าซทำให้ระบบเครื่องจักรการผลิตหยุดชะงัก | H12: 1.1 มีแผนซ่อมบำรุงรักษาประจำปี/ ประจำเดือน 1.2 มีการติดตั้งอุปกรณ์สำรอง 1.3 มีการจด log sheet เพื่อประเมินค่าของอุปกรณ์ว่าผิดปกติหรือไม่และ Visual check ขณะทำการจด log sheet | I12: 4 | J12: 2 | K12: =L12 -> E3 | L12: =IF(AND(J12=1,I12=1),"L16",IF(AND(J12=1,I12=2),"L14",IF(AND(J12=1,I12=3),"M11",IF(AND(J12=1,I12=4),"E4",IF(AND(J12=2,I12=1),"L15",IF(AND(J12=2,I12=2),"M12",IF(AND(J12=2,I12=3),"H7",IF(AND(J12=2,I12=4),"E3",IF(AND(J12=3,I12=1),"M13",IF(AND(J12=3,I12=2),"H9",IF(AND(J12=3,I12=3),"E6",IF(AND(J12=4,I12=4),"E2",IF(AND(J12=4,I12=1),"H10",IF(AND(I12=2,J12=4),"H8",IF(AND(J12=4,I12=3),"E5",IF(AND(J12=4,I12=4),"E1",FALSE)))))))))))))))) -> E3 | M12: ='2.2 BIA Process'!N15 -> 7 วัน | N12: ='2.2 BIA Process'!O15 -> 7 วัน | O12: ='2.2 BIA Process'!P15 -> 1 | P12: 1.ให้มีทีมซ่อมบำรุง และชิ้นส่วนอะไหล่ ตลอด24 ชม. เพื่อไม่ต้องเสียเวลาในการรอคอย ในขณะที่ตาม oncall | Q12: Jan | R12: Dec | S12: Maintenance | T12: 3 | U12: 2 | V12: =W12 -> H7 | W12: =IF(AND(U12=1,T12=1),"L16",IF(AND(U12=1,T12=2),"L14",IF(AND(U12=1,T12=3),"M11",IF(AND(U12=1,T12=4),"E4",IF(AND(U12=2,T12=1),"L15",IF(AND(U12=2,T12=2),"M12",IF(AND(U12=2,T12=3),"H7",IF(AND(U12=2,T12=4),"E3",IF(AND(U12=3,T12=1),"M13",IF(AND(U12=3,T12=2),"H9",IF(AND(U12=3,T12=3),"E6",IF(AND(U12=4,T12=4),"E2",IF(AND(U12=4,T12=1),"H10",IF(AND(U12=2,T12=4),"H8",IF(AND(U12=4,T12=3),"E5",IF(AND(U12=4,T12=4),"E1",FALSE)))))))))))))))) -> H7
A13: 9 | B13: 1.การผลิตไฟฟ้า | C13: เดินเครื่องระบบ Demin, Condensate และ Neutralization. | D13: Operational Management | E13: 6.กระบวนการทางธุรกิจและการปฏิบัติการ | G13: 1.ไม่สามารถผลิตน้ำ Demin ได้เนื่องจากไม่มีกระแสไฟฟ้า 2.ปริมาณน้ำ Demin ไม่เพียงพอต่อการใช้งานในการบวนการผลิตและส่งให้ลูกค้าได้ | H13: 1.1มีการติดตั้งระบบสำรองในการผลิตนำ Demin 4 units, Condensate 2 units. 1.2ระบบ Pump Neutralization มี 2 unit สามารถได้สลับกันได้กรณีอีกตัวเสีย 2.1มีระบบนำ RO เพิ่มอีก 2 units ในกระบวนการผลิตเพื่อช่วยผลิตน้ำได้ 2.2รับน้ำ Demin จาก WHA | I13: 3 | J13: 1 | K13: =L13 -> M11 | L13: =IF(AND(J13=1,I13=1),"L16",IF(AND(J13=1,I13=2),"L14",IF(AND(J13=1,I13=3),"M11",IF(AND(J13=1,I13=4),"E4",IF(AND(J13=2,I13=1),"L15",IF(AND(J13=2,I13=2),"M12",IF(AND(J13=2,I13=3),"H7",IF(AND(J13=2,I13=4),"E3",IF(AND(J13=3,I13=1),"M13",IF(AND(J13=3,I13=2),"H9",IF(AND(J13=3,I13=3),"E6",IF(AND(J13=4,I13=4),"E2",IF(AND(J13=4,I13=1),"H10",IF(AND(I13=2,J13=4),"H8",IF(AND(J13=4,I13=3),"E5",IF(AND(J13=4,I13=4),"E1",FALSE)))))))))))))))) -> M11 | M13: ='2.2 BIA Process'!N16 -> 7 วัน | N13: ='2.2 BIA Process'!O16 -> 7 วัน | O13: ='2.2 BIA Process'!P16 -> 1 | P13: 1.พิจารณาหาแหล่งน้ำสำรอง เช่น รถขนส่ง 2.จัดหาแหล่งน้ำสำรองจากแหล่งอื่นๆ เช่น เชื่อมระบบกับ Glow & CUP3 | Q13: Jan | R13: Dec | S13: Operation | T13: 2 | U13: 1 | V13: =W13 -> L14 | W13: =IF(AND(U13=1,T13=1),"L16",IF(AND(U13=1,T13=2),"L14",IF(AND(U13=1,T13=3),"M11",IF(AND(U13=1,T13=4),"E4",IF(AND(U13=2,T13=1),"L15",IF(AND(U13=2,T13=2),"M12",IF(AND(U13=2,T13=3),"H7",IF(AND(U13=2,T13=4),"E3",IF(AND(U13=3,T13=1),"M13",IF(AND(U13=3,T13=2),"H9",IF(AND(U13=3,T13=3),"E6",IF(AND(U13=4,T13=4),"E2",IF(AND(U13=4,T13=1),"H10",IF(AND(U13=2,T13=4),"H8",IF(AND(U13=4,T13=3),"E5",IF(AND(U13=4,T13=4),"E1",FALSE)))))))))))))))) -> L14
A14: 10 | B14: 1.การผลิตไฟฟ้า | C14: เดินเครื่องระบบ BFW และ Deaerator | D14: Operational Management | E14: 6.กระบวนการทางธุรกิจและการปฏิบัติการ | G14: 1. ไม่สามารถเดินระบบได้เนื่องจากไม่มีกระแสไฟฟ้า 2.การผลิตหยุดเนื่องจากไม่มีน้ำ | H14: 1.1xxxxx 2.1xxxxx | I14: 4 | J14: 1 | K14: =L14 -> E4 | L14: =IF(AND(J14=1,I14=1),"L16",IF(AND(J14=1,I14=2),"L14",IF(AND(J14=1,I14=3),"M11",IF(AND(J14=1,I14=4),"E4",IF(AND(J14=2,I14=1),"L15",IF(AND(J14=2,I14=2),"M12",IF(AND(J14=2,I14=3),"H7",IF(AND(J14=2,I14=4),"E3",IF(AND(J14=3,I14=1),"M13",IF(AND(J14=3,I14=2),"H9",IF(AND(J14=3,I14=3),"E6",IF(AND(J14=4,I14=4),"E2",IF(AND(J14=4,I14=1),"H10",IF(AND(I14=2,J14=4),"H8",IF(AND(J14=4,I14=3),"E5",IF(AND(J14=4,I14=4),"E1",FALSE)))))))))))))))) -> E4 | M14: ='2.2 BIA Process'!N17 -> 7 วัน | N14: ='2.2 BIA Process'!O17 -> 7 วัน | O14: ='2.2 BIA Process'!P17 -> 1 | P14: 1.ให้มีทีมซ่อมบำรุง และชิ้นส่วนอะไหล่ ตลอด24 ชม. เพื่อไม่ต้องเสียเวลาในการรอคอย ในขณะที่ตาม oncall 2.หาแหล่งน้ำอื่นๆเช่น BFW จาก CUP3 ส่งให้ลูกค้าแทนได้ | Q14: Jan | R14: Dec | S14: Maintenance | T14: 3 | U14: 1 | V14: =W14 -> M11 | W14: =IF(AND(U14=1,T14=1),"L16",IF(AND(U14=1,T14=2),"L14",IF(AND(U14=1,T14=3),"M11",IF(AND(U14=1,T14=4),"E4",IF(AND(U14=2,T14=1),"L15",IF(AND(U14=2,T14=2),"M12",IF(AND(U14=2,T14=3),"H7",IF(AND(U14=2,T14=4),"E3",IF(AND(U14=3,T14=1),"M13",IF(AND(U14=3,T14=2),"H9",IF(AND(U14=3,T14=3),"E6",IF(AND(U14=4,T14=4),"E2",IF(AND(U14=4,T14=1),"H10",IF(AND(U14=2,T14=4),"H8",IF(AND(U14=4,T14=3),"E5",IF(AND(U14=4,T14=4),"E1",FALSE)))))))))))))))) -> M11
A15: 11 | B15: 2.การผลิตไอน้ำ | C15: เดินเครื่อง Aux Boiler , HRSG และ Emission Control. | D15: Operational Management | E15: 6.กระบวนการทางธุรกิจและการปฏิบัติการ | G15: 1. การผลิตไอน้ำหยุดเนื่องจากไม่มีกระแสไฟฟ้า 2.การผลิตไอน้ำหยุดเนื่องจากไม่มีน้ำ 3.การผลิตไอน้ำหยุดเนื่องจากไม่มีเชื้อเพลิง 4.การผลิตไอน้ำหยุดเนื่องจากปริมาณสารเคมีไม่พอใช้งาน 5.ไม่สอดคล้องตามกฏหมาย ค่า Emission เกินมาตราฐาน เนื่องจากไม่มีสารเคมีใช้ในกระบวนการผลิต (No chemical) | H15: 1.1มีสัญญาการรับไฟฟ้าจากการไฟฟ้า 2.1xxxx 3.1xxxxx 4.1มี On call ผู้จำหน่ายสารเคมี (12 ชม.) 4.2มีการควบคุมปริมาณขั้นต่ำ (Max-Min) สารเคมี 5.1 มีระบบควบคุม Emission และระบบเตือนเมื่อค่าเกิดค่าที่ควบคุม | I15: 3 | J15: 2 | K15: =L15 -> H7 | L15: =IF(AND(J15=1,I15=1),"L16",IF(AND(J15=1,I15=2),"L14",IF(AND(J15=1,I15=3),"M11",IF(AND(J15=1,I15=4),"E4",IF(AND(J15=2,I15=1),"L15",IF(AND(J15=2,I15=2),"M12",IF(AND(J15=2,I15=3),"H7",IF(AND(J15=2,I15=4),"E3",IF(AND(J15=3,I15=1),"M13",IF(AND(J15=3,I15=2),"H9",IF(AND(J15=3,I15=3),"E6",IF(AND(J15=4,I15=4),"E2",IF(AND(J15=4,I15=1),"H10",IF(AND(I15=2,J15=4),"H8",IF(AND(J15=4,I15=3),"E5",IF(AND(J15=4,I15=4),"E1",FALSE)))))))))))))))) -> H7 | M15: ='2.2 BIA Process'!N18 -> 7 วัน | N15: ='2.2 BIA Process'!O18 -> 7 วัน | O15: ='2.2 BIA Process'!P18 -> 1 | P15: 1.ให้มีทีมซ่อมบำรุง และชิ้นส่วนอะไหล่ ตลอด24 ชม. เพื่อไม่ต้องเสียเวลาในการรอคอย ในขณะที่ตาม oncall 2.หาแหล่งไอน้ำอื่นๆ เช่น รับจาก CUP3,CUP4&GLOW ส่งให้ลูกค้าแทนได้ | Q15: Jan | R15: Dec | S15: Maintenance | T15: 2 | U15: 2 | V15: =W15 -> M12 | W15: =IF(AND(U15=1,T15=1),"L16",IF(AND(U15=1,T15=2),"L14",IF(AND(U15=1,T15=3),"M11",IF(AND(U15=1,T15=4),"E4",IF(AND(U15=2,T15=1),"L15",IF(AND(U15=2,T15=2),"M12",IF(AND(U15=2,T15=3),"H7",IF(AND(U15=2,T15=4),"E3",IF(AND(U15=3,T15=1),"M13",IF(AND(U15=3,T15=2),"H9",IF(AND(U15=3,T15=3),"E6",IF(AND(U15=4,T15=4),"E2",IF(AND(U15=4,T15=1),"H10",IF(AND(U15=2,T15=4),"H8",IF(AND(U15=4,T15=3),"E5",IF(AND(U15=4,T15=4),"E1",FALSE)))))))))))))))) -> M12
A16: 12 | B16: 1.การผลิตไฟฟ้า | C16: เดินเครื่องระบบ GTG | D16: Operational Management | E16: 6.กระบวนการทางธุรกิจและการปฏิบัติการ | G16: 1. การผลิตไฟฟ้าหยุดเนื่องจากไม่มีกระแสไฟฟ้า 2.การผลิตไฟฟ้าหยุดเนื่องจากไม่มีก๊าซ หรือก๊าซไม่เพียงพอ 3.ไฟไหม้ | H16: 1.1xxx 2.1xxx 3.1มีระบบควบคุมอัตโนมัติ (Emergency) และระบบป้องกันอุปกรณ์(Protection)) เพื่อป้องกันเครื่องจักรเสียหาย 3.2มีการจัดทำแผนตอบโต้ฉุกเฉิน ตาม Mitigation plan ภายในการเดินเครื่อง 3.3มีแผนซ่อมบำรุงรักษาประจำปี/ ประจำเดือน 3.4มีแผนการตรวจสอบระบบเครื่องจักร ตามระยะเวลาที่กำหนด | I16: 4 | J16: 2 | K16: =L16 -> E3 | L16: =IF(AND(J16=1,I16=1),"L16",IF(AND(J16=1,I16=2),"L14",IF(AND(J16=1,I16=3),"M11",IF(AND(J16=1,I16=4),"E4",IF(AND(J16=2,I16=1),"L15",IF(AND(J16=2,I16=2),"M12",IF(AND(J16=2,I16=3),"H7",IF(AND(J16=2,I16=4),"E3",IF(AND(J16=3,I16=1),"M13",IF(AND(J16=3,I16=2),"H9",IF(AND(J16=3,I16=3),"E6",IF(AND(J16=4,I16=4),"E2",IF(AND(J16=4,I16=1),"H10",IF(AND(I16=2,J16=4),"H8",IF(AND(J16=4,I16=3),"E5",IF(AND(J16=4,I16=4),"E1",FALSE)))))))))))))))) -> E3 | M16: ='2.2 BIA Process'!N19 -> 140 วัน | N16: ='2.2 BIA Process'!O19 -> 140 วัน | O16: ='2.2 BIA Process'!P19 -> 1 | P16: 1.ให้มีทีมซ่อมบำรุง และชิ้นส่วนอะไหล่ ตลอด24 ชม. เพื่อไม่ต้องเสียเวลาในการรอคอย ในขณะที่ตาม oncall 2.หาแหล่งไฟฟ้าอื่นๆ เช่น รับจาก PEA,CUP4&GLOW ส่งให้ลูกค้าแทนได้ | Q16: Jan | R16: Dec | S16: Maintenance | T16: 3 | U16: 2 | V16: =W16 -> H7 | W16: =IF(AND(U16=1,T16=1),"L16",IF(AND(U16=1,T16=2),"L14",IF(AND(U16=1,T16=3),"M11",IF(AND(U16=1,T16=4),"E4",IF(AND(U16=2,T16=1),"L15",IF(AND(U16=2,T16=2),"M12",IF(AND(U16=2,T16=3),"H7",IF(AND(U16=2,T16=4),"E3",IF(AND(U16=3,T16=1),"M13",IF(AND(U16=3,T16=2),"H9",IF(AND(U16=3,T16=3),"E6",IF(AND(U16=4,T16=4),"E2",IF(AND(U16=4,T16=1),"H10",IF(AND(U16=2,T16=4),"H8",IF(AND(U16=4,T16=3),"E5",IF(AND(U16=4,T16=4),"E1",FALSE)))))))))))))))) -> H7
A17: 13 | B17: 1.การผลิตไฟฟ้า | C17: เดินเครื่องระบบส่งผ่านผลิตภัณฑ์ (สายไฟฟ้า) | D17: Operational Management | E17: 6.กระบวนการทางธุรกิจและการปฏิบัติการ | G17: 1.ไม่มีกระแสไฟฟ้า 2.สายส่งไฟฟ้าชำรุดจึงไม่สามารถส่งกระแสไฟฟ้าให้กับลูกค้าได้ | H17: 1.1xxx 2.1มีการตรวจสอบอุปกรณ์ป้องกัน โดยพนักงานเดินเครื่อง และสายส่งโดยทีมงานซ่อมบำรุง อย่างประจำ 2.2มีแผนการซ่อมบำรุงรักษาระบบส่งจ่ายไฟฟ้ารายปี มีแผนการตรวจสอบระบบส่งจ่ายไฟฟ้าตามระยะเวลาที่กำหนด 2.3มีทีมปฏิบัติการในกรณีฉุกเฉิน (on-call) ตลอด 24 ชม. สำหรับงานซ่อมเร่งด่วน 2.4จัดเตรียมสายไฟฟ้าสำรองไว้เปลี่ยนในกรณีเกิดเหตุฉุกเฉิน 2.5 มีระบบควบคุมอัตโนมัติ (Emergency) และระบบป้องกันอุปกรณ์(Protection) เพื่อป้องกันเครื่องจักรเสียหาย | I17: 3 | J17: 1 | K17: =L17 -> M11 | L17: =IF(AND(J17=1,I17=1),"L16",IF(AND(J17=1,I17=2),"L14",IF(AND(J17=1,I17=3),"M11",IF(AND(J17=1,I17=4),"E4",IF(AND(J17=2,I17=1),"L15",IF(AND(J17=2,I17=2),"M12",IF(AND(J17=2,I17=3),"H7",IF(AND(J17=2,I17=4),"E3",IF(AND(J17=3,I17=1),"M13",IF(AND(J17=3,I17=2),"H9",IF(AND(J17=3,I17=3),"E6",IF(AND(J17=4,I17=4),"E2",IF(AND(J17=4,I17=1),"H10",IF(AND(I17=2,J17=4),"H8",IF(AND(J17=4,I17=3),"E5",IF(AND(J17=4,I17=4),"E1",FALSE)))))))))))))))) -> M11 | M17: ='2.2 BIA Process'!N20 -> 7 วัน | N17: ='2.2 BIA Process'!O20 -> 7 วัน | O17: ='2.2 BIA Process'!P20 -> 1 | P17: 1.เพิ่มระบบสายส่งเป็น 2 Feeder ใช้งาน 1 Feeder Standby เตรียมพร้อมอีก 1 Feeder (EGAT) 2.สลับแหล่งจ่ายไฟลูกค้า GPSC ไปรับยัง บริษัท Glow | Q17: Jan | R17: Dec | S17: Operation | T17: 2 | U17: 1 | V17: =W17 -> L14 | W17: =IF(AND(U17=1,T17=1),"L16",IF(AND(U17=1,T17=2),"L14",IF(AND(U17=1,T17=3),"M11",IF(AND(U17=1,T17=4),"E4",IF(AND(U17=2,T17=1),"L15",IF(AND(U17=2,T17=2),"M12",IF(AND(U17=2,T17=3),"H7",IF(AND(U17=2,T17=4),"E3",IF(AND(U17=3,T17=1),"M13",IF(AND(U17=3,T17=2),"H9",IF(AND(U17=3,T17=3),"E6",IF(AND(U17=4,T17=4),"E2",IF(AND(U17=4,T17=1),"H10",IF(AND(U17=2,T17=4),"H8",IF(AND(U17=4,T17=3),"E5",IF(AND(U17=4,T17=4),"E1",FALSE)))))))))))))))) -> L14
... A23: 19 | B23: 1.การผลิตไฟฟ้า | C23: ระบบควบคุมการผลิต ( UPS ,DCS) | D23: Operational Management | E23: 6.กระบวนการทางธุรกิจและการปฏิบัติการ | G23: 1.ไม่มีกระแสไฟฟ้าจ่ายเข้าระบบ 2.ระบบ UPS failedและ หรือ ระบบ DCS failed | H23: 1.1มีระบบควบคุมเป็นแบบ ขนาน 2 ระบบ 2.1มีการตรวจสอบ PM ระบบ 2.2ในกรณีที่ระบบ failed จะมีการแจ้งเตือนและระบบ สำรองจะเข้ามาควบคุมแทน 2.3มี manual valve ที่หน้างาน 2.4มีby pass control valve ที่หน้างาน 2.5มีชำนาญการระบบ DCS vender oncall 24ชม. | I23: 4 | J23: 2 | K23: =L23 -> E3 | L23: =IF(AND(J23=1,I23=1),"L16",IF(AND(J23=1,I23=2),"L14",IF(AND(J23=1,I23=3),"M11",IF(AND(J23=1,I23=4),"E4",IF(AND(J23=2,I23=1),"L15",IF(AND(J23=2,I23=2),"M12",IF(AND(J23=2,I23=3),"H7",IF(AND(J23=2,I23=4),"E3",IF(AND(J23=3,I23=1),"M13",IF(AND(J23=3,I23=2),"H9",IF(AND(J23=3,I23=3),"E6",IF(AND(J23=4,I23=4),"E2",IF(AND(J23=4,I23=1),"H10",IF(AND(I23=2,J23=4),"H8",IF(AND(J23=4,I23=3),"E5",IF(AND(J23=4,I23=4),"E1",FALSE)))))))))))))))) -> E3 | M23: ='2.2 BIA Process'!N26 -> 60 วัน | N23: ='2.2 BIA Process'!O26 -> 60 วัน | O23: ='2.2 BIA Process'!P26 -> 1 | P23: 1.ให้มีทีมซ่อมบำรุงชำนาญเฉพาะทาง ประสานงานกับทาง Vender และมีการเตรียมชิ้นส่วนอะไหล่ ตลอด24 ชม. เพื่อใช้งานและไม่ต้องเสียเวลาในการรอคอย ในขณะที่ตาม oncall 2.ให้มีทีมซ่อมสายส่งของ Vender (Contactor)ตลอด24ชม. | Q23: Jan | R23: Dec | S23: Maintenance | T23: 3 | U23: 2 | V23: =W23 -> H7 | W23: =IF(AND(U23=1,T23=1),"L16",IF(AND(U23=1,T23=2),"L14",IF(AND(U23=1,T23=3),"M11",IF(AND(U23=1,T23=4),"E4",IF(AND(U23=2,T23=1),"L15",IF(AND(U23=2,T23=2),"M12",IF(AND(U23=2,T23=3),"H7",IF(AND(U23=2,T23=4),"E3",IF(AND(U23=3,T23=1),"M13",IF(AND(U23=3,T23=2),"H9",IF(AND(U23=3,T23=3),"E6",IF(AND(U23=4,T23=4),"E2",IF(AND(U23=4,T23=1),"H10",IF(AND(U23=2,T23=4),"H8",IF(AND(U23=4,T23=3),"E5",IF(AND(U23=4,T23=4),"E1",FALSE)))))))))))))))) -> H7

Sheet Risk Criteria
A2: เกณฑ์การประเมินโอกาสเกิด
B3: ระดับ
A4: เกณฑ์การประเมินโอกาสเกิด | B4: ต่ำ | C4: ปานกลาง | D4: สูง | E4: รุนแรง
B5: 1 | C5: 2 | D5: 3 | E5: 4
A6: โอกาสเกิด | B6: <10% | C6: >10% ถึง <20% | D6: >20% ถึง <50% | E6: >50%
B7: ไม่เคย/เคยเกิด 1 ครั้งใน 5 ปี | C7: เคยเกิด 1 ครั้งใน 3 ปี | D7: เคยเกิด 1 ครั้งใน 1 ปี | E7: เคยเกิดขึ้น>1ครั้งใน 1 ปี
A13: เกณฑ์การประเมินความรุนแรง
A14: เกณฑ์การประเมินผลกระทบ (Impact) | C14: ระดับ
C15: ต่ำ | D15: ปานกลาง | E15: สูง | F15: รุนแรง
C16: 1 | D16: 2 | E16: 3 | F16: 4
B17: กำไรสุทธิต่ำกว่าเป้าหมาย | C17: < 1.25% | D17: >1.25% ถึง <2.5% | E17: >2.5% ถึง <5% | F17: >5%
B18: (Net Profit)
B19: กำไรขั้นต่ำกว่าเป้าหมาย | C19: < 1.25% | D19: >1.25% ถึง <2.5% | E19: >2.5% ถึง <5% | F19: >5%
A20: -1 | B20: (EBITDA)
A21: ด้านการเงิน (Financial) | B21: รายได้ต่ำกว่าเป้าหมาย | C21: < 1.25% | D21: >1.25% ถึง <2.5% | E21: >2.5% ถึง <5% | F21: >5%
B22: (Revenue)
B23: ค่าใช้จ่ายสูงกว่าเป้าหมาย | C23: < 1.25% | D23: >1.25% ถึง <2.5% | E23: >2.5% ถึง <5% | F23: >5%
B24: (Expense)
B25: ผลตอบแทนการลงทุนต่ำกว่าเป้าหมาย | C25: < 5% | D25: >5% ถึง <10% | E25: >10% ถึง <15% | F25: >15%
B26: (Project Return Equity IRR) | C26: จาก base case | D26: จาก base case | E26: จาก base case | F26: จาก base case
B27: มูลค่าความเสียหายต่อการผลิตและเครื่องจักร/อุปกรณ์ | C27: < 75 ล้านบาท | D27: >75 ถึง <150 ล้านบาท | E27: >150 ถึง <300 ล้านบาท | F27: >300 ล้านบาท
B28: งบประมานลงทุนสูงกว่าที่ได้รับอนุมัติ | C28: < 1.25% | D28: >1.25% ถึง <2.5% | E28: >2.5% ถึง <5% | F28: >5%
B29: (Project Cost Overrun) | C29: จาก base case | D29: จาก base case | E29: จาก base case | F29: จาก base case
A31: เกณฑ์การประเมินผลกระทบ (Impact) | C31: ระดับ
C32: ต่ำ | D32: ปานกลาง | E32: สูง | F32: รุนแรง
C33: 1 | D33: 2 | E33: 3 | F33: 4
A34: -2 | B34: การปฏิบัติตามกฏหมาย/ กฏระเบียบ/ ข้อบังคับ | C34: ขัดต่อกฎระเบียบ/ข้อบังคับ/ข้อกำหนดตามมาตรฐานต่างๆ ของบริษัท | D34: ขัดต่อกฎหมาย กฎระเบียบของหน่วยงานภายนอกที่กำกับดูแล ซึ่งกระทบต่อการดำเนินงานของบริษัท แต่สามารถดำเนินการแก้ไขได้ทันที | E34: ขัดต่อกฎหมาย กฎระเบียบของหน่วยงานภายนอกที่กำกับดูแล โดยได้รับบทลงโทษตามกฎหมาย หรือต้องแก้ไขตามคำสั้่งของหน่วยงานภายนอกที่กำกับดูแล | F34: ขัดต่อกฎหมาย กฎระเบียบของหน่วยงานภายนอกที่กำกับดูแลโดยถูกเพิกถอนใบอนุญาตหรือถูกปิดกิจการ
A35: กฏหมาย กฏระเบียบ ข้อบังคับ และสัญญา / ข้อตกลงระดับของการให้บริการ
A36: (Regulation) | B36: ข้อตกลงระดับของการให้บริการ | C36: ได้รับคำแจ้งเตือนจากลูกค้าและพิจารณาดำเนินการแก้ไข | D36: เริ่มดำเนินการแก้ไขภายใต้สัญญา | E36: ดำเนินการแก้ไขตามที่สัญญากำหนดไว้ | F36: ไม่สามารถดำเนินการแก้ไขตามสัญญา ทำให้ลูกค้ายกเลิกสัญญา
A38: เกณฑ์การประเมินผลกระทบ (Impact) | C38: ระดับ
C39: ต่ำ | D39: ปานกลาง | E39: สูง | F39: รุนแรง
C40: 1 | D40: 2 | E40: 3 | F40: 4
C41: พนักงาน ลูกค้า คู่ค้า หรือผู้มีส่วนได้ส่วนเสียได้รับบาดเจ็บจนต้องได้รับการปฐมพาบาลทางการแพทย์ แต่ไม่หยุดงาน | D41: พนักงาน ลูกค้า คู่ค้า หรือผู้มีส่วนได้ส่วนเสียได้รับบาดเจ็บจนต้องได้รับการรักษาทางการแพทย์ (OPD) โดยไม่ต้องเข้าพักรักษาในโรงพยาบาล | E41: พนักงาน ลูกค้า คู่ค้า หรือผู้มีส่วนได้ส่วนเสียได้รับบาดเจ็บหนักจนต้องเข้ารับการรักษาในโรงพยาบาล (IPD) | F41: พนักงาน ลูกค้า คู่ค้า หรือผู้มีส่วนได้ส่วนเสียได้รับบาดเจ็บหนักจนทุพลภาพ หรือเสียชีวิต
B43: อาชีวอนามัยและ
A44: -3 | B44: ความปลอดภัย
A45: ความปลอดภัย
A46: อาชีวอนามัยของบุคลากร
A47: (Occupational Health & Safety) | C47: พนักงานเกิดความไม่พอใจ แต่สามารถแก้ไขได้ภายในหน่วยงาน | D47: พนักงานเกิดความไม่พอใจ และจำเป็นต้องอาศัยหน่วยงานกลาง (HR) ในการดำเนินการแก้ไข | E47: พนักงานเกิดความไม่พอใจสูง และเกิดดารร้องเรียนผ่านช่องทางภายในบริษัท | F47: พนักงานเกิดความไม่พอใจอย่างรุนแรง เช่นนัดหยุดงาน พนักงานลาออกจำนวนมากและส่งผลให้การดำเนินธุรกิจหยุดชะงักหรือเกิดข้อพิพาทจนต้องเข้าสู่กระบวนการทางกฏหมาย
B50: ความพึงพอใจของพนักงาน
A52: เกณฑ์การประเมินผลกระทบ (Impact) | C52: ระดับ
C53: ต่ำ | D53: ปานกลาง | E53: สูง | F53: รุนแรง
C54: 1 | D54: 2 | E54: 3 | F54: 4
C55: เกิดผลกระทบต่อส่งแวดล้อมในบริเวณข้างเคียงเล็กน้อย แก้ไขได้โดยไม่ต้องมีมาตรการดำเนินการแก้ไข | D55: เกิดผลกระทบต่อสิ่งแวดล้อมโดยสามารถดำเนินการแก้ไขภายใน 1 วันหรือใช้ระยะเวลาฟื้นฟูให้กลับคืนสภาพได้ ภายในระยะเวลา < 1 ปี | E55: เกิดผลกระทบต่อสิ่งแวดล้อมรุนแรงโดยสามารถดำเนินการแก้ไขในระยะเวลามากกว่า 1 วัน แต่ไม่เกิน 1 เดือนหรือใช้ระยะเวลาฟื้นฟูให้กลับคืนสภาพได้ ภายในระยะเวลา 1-5 ปี | F55: เกิดผลกระทบต่อสิ่งแวดล้อมรุนแรงมากโดยสามารถดำเนินการแก้ไขในระยะเวลามากกว่า 1 เดือน หรือใช้ระยะเวลามากกว่า 5 ปีขึ้นไป ในการบรรเทา ฟื้นฟู หรือเสียหายจนยากต่อการฟื้นฟู
A57: -4
A58: สิ่งแวดล้อม | B58: สิ่งแวดล้อม
A59: (Environment)
A61: เกณฑ์การประเมินผลกระทบ (Impact) | C61: ระดับ
C62: ต่ำ | D62: ปานกลาง | E62: สูง | F62: รุนแรง
C63: 1 | D63: 2 | E63: 3 | F63: 4
B64: ปริมาณการขายผลิตภัณฑ์ของ GPSC | C64: ลูกค้าที่ไม่ใช่ลูกค้าหลัก ลดการซื้อ ผลิตภัณฑ์/บริการ | D64: ลูกค้าที่ไม่ใช่ลูกค้าหลัก เลิกซื้อ ผลิตภัณฑ์/บริการ | E64: ลูกค้าหลัก ลดการซื้อ ผลิตภัณฑ์/บริการ | F64: ลูกค้าหลัก เลิกซื้อ ผลิตภัณฑ์/บริการ
A65: -5
A66: ลูกค้า คู่ค้า
A67: (Customer) | B67: ความพึงพอใจของลูกค้า คู่ค้า | C67: ไม่มีผลกระทบ | D67: ลูกค้า คู่ค้า แสดงความไม่พอใจร้องเรียนมาที่บริษัท | E67: ลูกค้าแสดงความไม่พอใจผ่านสื่อต่างๆ | F67: ลูกค้า คู่ค้า ฟ้องร้องบริษัท
A69: เกณฑ์การประเมินผลกระทบ (Impact) | C69: ระดับ
C70: ต่ำ | D70: ปานกลาง | E70: สูง | F70: รุนแรง
C71: 1 | D71: 2 | E71: 3 | F71: 4
C72: มีผลกระทบต่อกระบวนการผลิต กระบวนการดำเนินงานเล็กน้อย โดยอยู่ในระดับที่สามารถ ควบคุมและแก้ไขได้ด้วยตัวเอง | D72: มีผลกระทบต่อกระบวนการผลิต กระบวนการดำเนินงาน โดยอยู่ในระดับที่สามารถ ควบคุมและแก้ไขได้โดยหน่วยงานที่เกี่ยวข้อง | E72: ผลกระทบต่อกระบวนการผลิต กระบวนการดำเนินงาน โดยจำเป็นต้องหยุด ชะลอการดหเนินงานหลักบางส่วน | F72: ผลกระทบต่อกระบวนการผลิต กระบวนการดำเนินงานอย่างรุนแรง โดยส่งผลกระทบต่อการส่งมอบ ผลิตภัณฑ์แก่ลูกค้า / การดำเนินงานและเป้าหมายตามแผนงาน
B74: ประสิทธิผลของกระบวนการ
A79: -6 | B79: ผลิตภัณฑ์หรือ บริการ | C79: ไม่มีผลกระทบในการส่งมอบผลิตภัณฑ์/ บริการ | D79: เกิดความล่าช้าในการส่งมอบผลิตภัณฑ์ บริการ หรือ ผลิตภัณฑ์ /บริการ ไม่ได้คุณภาพตามข้อกำหนด | E79: ไม่สามารถส่งมอบผลิตภัณฑ์ บริการได้ | F79: ไม่สามารถส่งมอบผลิตภัณฑ์ บริการได้ ซึ่งทางบริษัทมีค่าใช้จ่ายเพิ่ม หรือถูกเรียกร้องค่าเสียหาย
A80: กระบวนการทางธุรกิจ และการปฏิบัติการ | B80: ระยะเวลาการดำเนินโครงการล่าช้า
A81: (Operational) | B81: (ตั้งแต่ BOD Approval จนถึง COD) | C81: <3% จากแผนงานหรือ<1เดือน | D81: 3% < X <5% จากแผนงานหรือ< 2เดือน | E81: 5% < X <10% จากแผนงานหรือ< 3เดือน | F81: ล่าช้าจากแผนงาน 10% หรือ > 3 เดือน
B82: การกำกับดูแล | C82: ดำเนินงานเป็นไปตามแนวทาง/ นโยบาย GPSC โดยสามารถควบคุมได้ | D82: ดำเนินงานเป็นไปตามแนวทาง/ นโยบาย GPSC โดยไม่สามารถควบคุมได้ | E82: ไม่ดำเนินงานเตามแนวทาง/ นโยบาย ของGPSC | F82: ไม่ดำเนินงานเตามแนวทาง/ นโยบาย ของGPSC และส่งผลเสียหายต่อ GPSC
A84: เกณฑ์การประเมินผลกระทบ (Impact) | C84: ระดับ
C85: ต่ำ | D85: ปานกลาง | E85: สูง | F85: รุนแรง
C86: 1 | D86: 2 | E86: 3 | F86: 4
D87: ทำให้เกิดความไม่พอใจต่อสาธารณะ เช่นการเขียนบทความวิจารย์ | E87: ทำให้เกิดความไม่พอใจอย่างมากต่อสาธารณะ เช่นการแสดงความเห็นคัดค้านผ่านสื่อต่างๆ | F87: ทำให้เกิดการต่อต้านรุนแรงจากสาธารณะ เช่นการประท้วงจากชุมชน
B88: ภาพลักษณ์ของ GPSC ต่อสาธารณะ สื่อ | C88: ไม่มีผลกระทบ
A90: -7
A91: ชื่อเสียงภาพลักษณ์ต่อองค์กร
A92: (Image) | C92: มีผลกระทบต่อชุมชน รอบสถานประกอบการ โรงงานเล็กน้อย โดยได้รับคำติเตือนข้อครหาอย่างไม่เป็นทางการผ่านช่องทางต่างๆของบริษัท | D92: มีผลกระทบต่อชุมชน รอบสถานประกอบการโดยได้ข้อร้องเรียนเป็นลายลักษณ์อักษร | E92: มีผลกระทบต่อชุมชน รอบสถานประกอบการโดยได้ข้อร้องเรียนเป็นลายลักษณ์อักษรและถูกดำเนินการตรวจ สอบจากหน่วยงานกำกับดูแลจากภายนอก | F92: มีผลกระทบรุนแรงต่อชุมชนเป็นบริเวณกว้าง โดยได้รับคำสั่งหยุดการดำเนินการ หรือถูกประท้วงจากมวลชนจนไม่สามารถดำเนินธุรกิจได้
B94: ภาพลักษณ์ GPSC
B95: ต่อชุมชน

Sheet 1.3 BIA Plant incident
A1: Product & Service | B1: Impact Category | C1: 1 Hour | D1: 4 Hour | E1: 8 Hour | F1: 12 Hour | G1: 24 Hour | H1: 3 Days | I1: 14 Days | J1: 30 Days | K1: Serverity over time (scores) | L1: Financial impact (level)
A2: ABCT breaker 5YB-01 trip by relay 87L operate | B2: 1. การเงิน | C2: 1 | D2: 1 | E2: 1 | F2: 1 | G2: 1 | H2: 1 | I2: 2 | J2: 2 | K2: 39 | L2: 2
A3: Plant islanding due to ban chang substation switching line to bay spare (inter trip not support this function) | B3: 1. การเงิน | C3: 1 | D3: 1 | E3: 1 | F3: 1 | G3: 1 | H3: 1 | I3: 2 | J3: 2 | K3: 39 | L3: 3
A4: GTG-11 trip by 1391VA979HH and PEA 1YB-01 OPEN plant Islanding by relay 21/21N Zone1 | B4: 1. การเงิน | C4: 1 | D4: 1 | E4: 1 | F4: 1 | G4: 1 | H4: 1 | I4: 2 | J4: 2 | K4: 39 | L4: 3
A5: GTG-14 was tripped by Load GEAR#1&2 AXIS VIBRAT.high | B5: 1. การเงิน | C5: 1 | D5: 1 | E5: 1 | F5: 1 | G5: 1 | H5: 1 | I5: 2 | J5: 2 | K5: 39 | L5: 3
A6: GTG-11 was tripped by alarm "TAHH 534-541 Brg.Metal Temp high trip" | B6: 1. การเงิน | C6: 1 | D6: 1 | E6: 1 | F6: 1 | G6: 1 | H6: 1 | I6: 2 | J6: 2 | K6: 39 | L6: 3
A7: GTG11 was tripped by "Generator Vibration high trip" | B7: 1. การเงิน | C7: 1 | D7: 1 | E7: 1 | F7: 1 | G7: 1 | H7: 1 | I7: 2 | J7: 2 | K7: 39 | L7: 3
A8: Close 52Aux (GTG-12) 87T operate 52L1 Open,52G Open and GTG-12 trip | B8: 1. การเงิน | C8: 1 | D8: 1 | E8: 1 | F8: 1 | G8: 1 | H8: 1 | I8: 2 | J8: 2 | K8: 39 | L8: 3
A9: Aux Boiler trip by burner inlet fuel gas pressure low low | B9: 1. การเงิน | C9: 1 | D9: 1 | E9: 1 | F9: 1 | G9: 1 | H9: 1 | I9: 1 | J9: 1 | K9: 36 | L9: 3
A10: Plant islanding, 1YB01 open by inter trip 5YB01 operate from Banchang substation | B10: 1. การเงิน | C10: 1 | D10: 1 | E10: 1 | F10: 1 | G10: 1 | H10: 1 | I10: 2 | J10: 2 | K10: 39 | L10: 3
A11: PEA Maptaphut3 substation tripped. This event impacted to customers (MIGP ,ABCT, LLDPE2) tripped. | B11: 1. การเงิน | C11: 1 | D11: 1 | E11: 1 | F11: 1 | G11: 1 | H11: 1 | I11: 2 | J11: 2 | K11: 39 | L11: 3
A12: GTG11&HRSG11 and GTG12&HRSG12 tripped. | B12: 1. การเงิน | C12: 1 | D12: 1 | E12: 1 | F12: 1 | G12: 1 | H12: 1 | I12: 2 | J12: 2 | K12: 39 | L12: 3
A13: GTG15&HRSG15 tripped. | B13: 1. การเงิน | C13: 1 | D13: 1 | E13: 1 | F13: 1 | G13: 1 | H13: 1 | I13: 2 | J13: 2 | K13: 39 | L13: 3
... A26: PTTAC 115 kV CB 7YB-01 opened to PTTAC was tripped by alarm reverse power relay | B26: 1. การเงิน | C26: 1 | D26: 1 | E26: 1 | F26: 1 | G26: 1 | H26: 1 | I26: 2 | J26: 2 | K26: 39 | L26: 2

Sheet 1.2 Plant incident 
A1: ทะเบียนรายการกิจกรรม (การดำเนินงาน/กระบวนการผลิต/เครื่องจักร) / พื้นที่
A3: ผู้ประเมิน | B3: OCOT/OC1M | C3: วันที่ประเมิน | D3: 28/09/2565
A4: วิธีการประเมิน | B4: ประเมินแบบพื้นที่ | C4: ทบทวนครั้งที่ | D4: 4
A5: ชื่อหน่วยงาน | B5: ส่วนปฏิบัติการผลิต CUP1
A6: ชื่อพื้นที่ประเมิน | B6: GPSC RYG : CUP-1
A8: วันเดือนปีที่เกิดเหตุ | B8: รายละเอียด | C8: ระดับความรุนแรง | D8: ความสำคัญในการประเมิน BIA
A9: 43899 | B9: ABCT breaker 5YB-01 trip by relay 87L operate | C9: 2 | D9: สำคัญ
A10: 43975 | B10: Plant islanding due to ban chang substation switching line to bay spare (inter trip not support this function) | C10: 3 | D10: ไม่สำคัญ
A11: 44004 | B11: GTG-11 trip by 1391VA979HH and PEA 1YB-01 OPEN plant Islanding by relay 21/21N Zone1 | C11: 3 | D11: ไม่สำคัญ
A12: 44009 | B12: GTG-14 was tripped by Load GEAR#1&2 AXIS VIBRAT.high | C12: 3 | D12: ไม่สำคัญ
A13: 44056 | B13: GTG-11 was tripped by alarm "TAHH 534-541 Brg.Metal Temp high trip" | C13: 3 | D13: ไม่สำคัญ
A14: 44075 | B14: GTG11 was tripped by "Generator Vibration high trip" | C14: 3 | D14: ไม่สำคัญ
A15: 44161 | B15: Close 52Aux (GTG-12) 87T operate 52L1 Open,52G Open and GTG-12 trip | C15: 3 | D15: ไม่สำคัญ
A16: 44252 | B16: Aux Boiler trip by burner inlet fuel gas pressure low low | C16: 3 | D16: ไม่สำคัญ
A17: 44246 | B17: 16:00 Plant islanding, 1YB01 open by inter trip 5YB01 operate from Banchang substation | C17: 3 | D17: ไม่สำคัญ
A18: 44299 | B18: 02:39 PEA Maptaphut3 substation tripped. This event impacted to customers (MIGP ,ABCT, LLDPE2) tripped. | C18: 3 | D18: ไม่สำคัญ
A19: 44300 | B19: 11:15 GTG11&HRSG11 and GTG12&HRSG12 tripped. | C19: 3 | D19: ไม่สำคัญ
A20: 44300 | B20: 11:28 GTG15&HRSG15 tripped. | C20: 3 | D20: ไม่สำคัญ
... A33: 44527 | B33: 11:42 PTTAC 115 kV CB 7YB-01 opened to PTTAC was tripped by alarm reverse power relay | C33: 2 | D33: สำคัญ

Sheet 3.RA Crisis
A1: การประเมินความเสี่ยงด้านความต่อเนื่องทางธุรกิจ
A3: ผู้ประเมิน | C3: =#REF! -> #REF! | E3: ชื่อหน่วยงาน | F3: =#REF! -> #REF! | H3: วันที่ประเมิน | J3: =#REF! -> #REF!
A4: วิธีการประเมิน | C4: =#REF! -> #REF! | E4: ชื่อพื้นที่ประเมิน | F4: =#REF! -> #REF! | H4: ทบทวนครั้งที่ | J4: =#REF! -> #REF!
A6: No. | B6: Crisis Senario ภาวะวิกฤต | D6: Risk Category ประเภทความเสี่ยง | E6: Impact Type ประเภทผลกระทบ | F6: Posible Risk ความเสี่ยงที่เป็นไปได้ | G6: Existing Control มาตรการควบคุมที่มีอยู่ | H6: Risk Assessment | O6: Mitigation Plan (new countermeasure to reduce threats) | P6: Time Frame | R6: Responsible Person | S6: Target
H7: I | I7: L | J7: R | K7: R | L7: MTPD | M7: RTO | N7: MBCO | P7: From | Q7: To | S7: I | T7: L | U7: R | V7: R
A8: 1 | B8: ไม่มีก๊าซธรรมชาติเนื่องจากแท่นขุดเจาะหยุดการผลิต (No fuel (Natural Gas)) และกรณีท่อก๊าซภายนอกชำรุดเนื่องจากเกิดอุบัติเหตุทางถนน | D8: Operational Management | E8: 6.กระบวนการทางธุรกิจและการปฏิบัติการ | F8: 1. ไม่สามารถทราบปริมาณเชื้อเพลิง ที่จะนำมาผลิตกระแสไฟฟ้าได้ 2. ไม่สามารถผลิตไฟฟ้า และไอน้ำส่งให้กับลูกค้าได้ 3. สูญเสียรายได้ | G8: 1. ติดตามสถานการณ์ คุณภาพและปริมาณ ก๊าซธรรมชาติ ผ่าน SMS 2. แจ้ง PTT เพื่อใช้มาตราการแผนสำรองปริมาณ LNG ที่ PTT. เตรียมการไว้ 3. ติดต่อ PTT เพื่อให้ช่วยจัดส่งก๊าซธรรมชาติอย่างเร่งด่วน 4. ดำเนินการซ่อมโดยทีม PTT | H8: 4 | I8: 1 | J8: =K8 -> E4 | K8: =IF(AND(I8=1,H8=1),"L16",IF(AND(I8=1,H8=2),"L14",IF(AND(I8=1,H8=3),"M11",IF(AND(I8=1,H8=4),"E4",IF(AND(I8=2,H8=1),"L15",IF(AND(I8=2,H8=2),"M12",IF(AND(I8=2,H8=3),"H7",IF(AND(I8=2,H8=4),"E3",IF(AND(I8=3,H8=1),"M13",IF(AND(I8=3,H8=2),"H9",IF(AND(I8=3,H8=3),"E6",IF(AND(I8=4,H8=4),"E2",IF(AND(I8=4,H8=1),"H10",IF(AND(H8=2,I8=4),"H8",IF(AND(I8=4,H8=3),"E5",IF(AND(I8=4,H8=4),"E1",FALSE)))))))))))))))) -> E4 | M8: 24 ชม | N8: 1 | O8: 1.ทำระบบไฟฟ้าส่งจ่ายจาก GLOW มาจ่ายให้กับลูกค้าแทน 2.ทำระบบท่อไอน้ำจาก GLOW มาจ่ายให้กับลูกค้า | P8: Jan | Q8: Dec | R8: Engineering | S8: 3 | T8: 1 | U8: =V8 -> M11 | V8: =IF(AND(T8=1,S8=1),"L16",IF(AND(T8=1,S8=2),"L14",IF(AND(T8=1,S8=3),"M11",IF(AND(T8=1,S8=4),"E4",IF(AND(T8=2,S8=1),"L15",IF(AND(T8=2,S8=2),"M12",IF(AND(T8=2,S8=3),"H7",IF(AND(T8=2,S8=4),"E3",IF(AND(T8=3,S8=1),"M13",IF(AND(T8=3,S8=2),"H9",IF(AND(T8=3,S8=3),"E6",IF(AND(T8=4,S8=4),"E2",IF(AND(T8=4,S8=1),"H10",IF(AND(T8=2,S8=4),"H8",IF(AND(T8=4,S8=3),"E5",IF(AND(T8=4,S8=4),"E1",FALSE)))))))))))))))) -> M11
A9: 2 | B9: ไม่มีน้ำ (No water) กรณีภัยแล้งและท่อน้ำภายนอกชำรุด | D9: Operational Management | E9: 6.กระบวนการทางธุรกิจและการปฏิบัติการ | F9: 1. ไม่สามารถผลิตกระแสไฟฟ้าได้ 2. ไม่สามารถผลิตน้ำอุตสาหกรรม ใช้ในกระบวนการผลิตไอน้ำ และไฟฟ้า และส่งให้กับลูกค้าได้ 3. สูญเสียรายได้ | G9: 1. มีการติดตามสถานการณ์น้ำอยู่เสมอ 2. ประเมินสถานการณ์น้ำ เพื่อกรณีสุดวิสัยจำเป็นต้อง Shutdown ระบบ 3.มีถังเก็บกักน้ำสำรอง เพื่อเก็บไว้ใช้ 4. แจ้งลูกค้าหากไม่สามารถจ่ายน้ำ เพื่อลดการใช้น้ำ 5.ต่อท่อระบบน้ำCUP1-CUP3--GLOW ให้เป็นระบบเครือข่าย | H9: 4 | I9: 1 | J9: =K9 -> E4 | K9: =IF(AND(I9=1,H9=1),"L16",IF(AND(I9=1,H9=2),"L14",IF(AND(I9=1,H9=3),"M11",IF(AND(I9=1,H9=4),"E4",IF(AND(I9=2,H9=1),"L15",IF(AND(I9=2,H9=2),"M12",IF(AND(I9=2,H9=3),"H7",IF(AND(I9=2,H9=4),"E3",IF(AND(I9=3,H9=1),"M13",IF(AND(I9=3,H9=2),"H9",IF(AND(I9=3,H9=3),"E6",IF(AND(I9=4,H9=4),"E2",IF(AND(I9=4,H9=1),"H10",IF(AND(H9=2,I9=4),"H8",IF(AND(I9=4,H9=3),"E5",IF(AND(I9=4,H9=4),"E1",FALSE)))))))))))))))) -> E4 | L9: 24 ชม | M9: 24 ชม | N9: 1 | O9: 1.ปรับลดปริมาณการใช้น้ำในกระบวนการผลิต 2.พิจารณาหาแหล่งน้ำสำรอง เช่น รถขนส่งน้ำจากภายนอก 3.หาแหล่งน้ำดิบเพิ่มอีกแหล่ง เช่น จากบริษัท EAST WATER | P9: Jan | Q9: Dec | R9: Operation | S9: 3 | T9: 1 | U9: =V9 -> M11 | V9: =IF(AND(T9=1,S9=1),"L16",IF(AND(T9=1,S9=2),"L14",IF(AND(T9=1,S9=3),"M11",IF(AND(T9=1,S9=4),"E4",IF(AND(T9=2,S9=1),"L15",IF(AND(T9=2,S9=2),"M12",IF(AND(T9=2,S9=3),"H7",IF(AND(T9=2,S9=4),"E3",IF(AND(T9=3,S9=1),"M13",IF(AND(T9=3,S9=2),"H9",IF(AND(T9=3,S9=3),"E6",IF(AND(T9=4,S9=4),"E2",IF(AND(T9=4,S9=1),"H10",IF(AND(T9=2,S9=4),"H8",IF(AND(T9=4,S9=3),"E5",IF(AND(T9=4,S9=4),"E1",FALSE)))))))))))))))) -> M11
A10: 3 | B10: Emergency Cases ไฟใหม้ระบบการผลิต | D10: Operational Management | E10: B - ประสิทธิผลของกระบวนการ | F10: 1.ไม่สามารถผลิตกระแสไฟฟ้าส่งให้กับลูกค้าได้ 2.ไม่สามารถผลิตไอน้ำ ส่งให้แก่ลูกค้าได้ 3.ไม่สามารถผลิต น้ำอุตสาหกรรมเพื่อใช้เอง และส่งผ่านให้กับลูกค้าได้ 4.สูญเสียรายได้ | G10: 1.มีการจัดทีมซ้อมแผนฉุกเฉินประจำปี โดยเมื่อเกิดเหตุ มีการแจ้งโดยเสียงตามสาย ประเมินสถานการณ์และอพยพผู้ไม่เกี่ยวข้องไปยังจุดรวมพล 2. ตัดแยกระบบเพื่อไม่ให้เกิดการลุกลามและทำให้อุปกรณ์อื่นๆเสียหาย 3. มีการแจ้งเตือนชุมชมโดย CSR เมื่อมีควันจากไฟไหม้ 4. มีทดสอบอุปกรณ์แจ้งเตือนเหตุเพลิงไหม้ และอุปกรณ์ดับเพลิงอย่างเป็นประจำ 5. มีการตรวจสอบความพร้อมและสภาพของเครื่องจักร โดยพนักงานเดินเครื่อง และพนักงานซ่อมบำรุงป็นประจำอย่างต่อเนื่อง 6.เพิ่มทักษะให้กับพนักงานโดยการส่งไปอบรมการดับเพลิง ภายนอก 7. รับไฟฟ้าจากEGAT '8.มีระบบ PMC ควบคุมระบบจ่ายไฟ และระบบ Shedding ก็นีที่ไฟไม่พอ เพื่อให้ระบบเดินได้ต่อเนื่อง 9.ส่งทีม safety ไปอบรมดับเพลิงขั้นสูง | H10: 4 | I10: 1 | J10: =K10 -> E4 | K10: =IF(AND(I10=1,H10=1),"L16",IF(AND(I10=1,H10=2),"L14",IF(AND(I10=1,H10=3),"M11",IF(AND(I10=1,H10=4),"E4",IF(AND(I10=2,H10=1),"L15",IF(AND(I10=2,H10=2),"M12",IF(AND(I10=2,H10=3),"H7",IF(AND(I10=2,H10=4),"E3",IF(AND(I10=3,H10=1),"M13",IF(AND(I10=3,H10=2),"H9",IF(AND(I10=3,H10=3),"E6",IF(AND(I10=4,H10=4),"E2",IF(AND(I10=4,H10=1),"H10",IF(AND(H10=2,I10=4),"H8",IF(AND(I10=4,H10=3),"E5",IF(AND(I10=4,H10=4),"E1",FALSE)))))))))))))))) -> E4 | L10: 24 ชม | M10: 24 ชม | N10: 1 | O10: 1.ทำสัญญา NPC S&E ในการจัดจ้าง รปภ. เป็น Fireman และรถดับเพลิงในกรณีฉุกเฉิน 2.มีผู้ชำนาญการเรื่องการดับเพลิง ประจำบริษัท เพื่อแนะนำและจัดฝึกอบรมภายใน | P10: Jan | Q10: Dec | R10: SSHE | S10: 3 | T10: 1 | U10: =V10 -> M11 | V10: =IF(AND(T10=1,S10=1),"L16",IF(AND(T10=1,S10=2),"L14",IF(AND(T10=1,S10=3),"M11",IF(AND(T10=1,S10=4),"E4",IF(AND(T10=2,S10=1),"L15",IF(AND(T10=2,S10=2),"M12",IF(AND(T10=2,S10=3),"H7",IF(AND(T10=2,S10=4),"E3",IF(AND(T10=3,S10=1),"M13",IF(AND(T10=3,S10=2),"H9",IF(AND(T10=3,S10=3),"E6",IF(AND(T10=4,S10=4),"E2",IF(AND(T10=4,S10=1),"H10",IF(AND(T10=2,S10=4),"H8",IF(AND(T10=4,S10=3),"E5",IF(AND(T10=4,S10=4),"E1",FALSE)))))))))))))))) -> M11
A11: 4 | B11: ระบบสายส่งชำรุด เกิดจากสายส่งขาด/ระเบิดเนื่องจากการลัดวงจร | D11: Operational Management | E11: 6.กระบวนการทางธุรกิจและการปฏิบัติการ | F11: 1. ไม่สามารถส่งกระแสไฟฟ้าได้ 2. สูญเสียรายได้ | G11: 1.มีการตรวจสอบอุปกรณ์ป้องกัน โดยพนักงานเดินเครื่อง และสายส่งโดยทีมงานซ่อมบำรุง อย่างประจำ 2. มีแผนการซ่อมบำรุงรักษาระบบส่งจ่ายไฟฟ้ารายปี 3. มีแผนการตรวจสอบระบบส่งจ่ายไฟฟ้าตามระยะเวลาที่กำหนด 4.มีทีมปฏิบัติการในกรณีฉุกเฉิน (on-call) ตลอด 24 ชม. สำหรับงานซ่อมเร่งด่วน 5.จัดเตรียมสายไฟฟ้าสำรองไว้เปลี่ยนในกรณีเกิดเหตุฉุกเฉิน | H11: 4 | I11: 1 | J11: =K11 -> E4 | K11: =IF(AND(I11=1,H11=1),"L16",IF(AND(I11=1,H11=2),"L14",IF(AND(I11=1,H11=3),"M11",IF(AND(I11=1,H11=4),"E4",IF(AND(I11=2,H11=1),"L15",IF(AND(I11=2,H11=2),"M12",IF(AND(I11=2,H11=3),"H7",IF(AND(I11=2,H11=4),"E3",IF(AND(I11=3,H11=1),"M13",IF(AND(I11=3,H11=2),"H9",IF(AND(I11=3,H11=3),"E6",IF(AND(I11=4,H11=4),"E2",IF(AND(I11=4,H11=1),"H10",IF(AND(H11=2,I11=4),"H8",IF(AND(I11=4,H11=3),"E5",IF(AND(I11=4,H11=4),"E1",FALSE)))))))))))))))) -> E4 | L11: 7 วัน | M11: 7 วัน | N11: 1 | O11: 1.ให้มีทีมซ่อมบำรุง และชิ้นส่วนอะไหล่ ตลอด24 ชม. เพื่อไม่ต้องเสียเวลาในการรอคอย ในขณะที่ตาม oncall 2.ให้มีทีม ซ่อมสายส่ง ตลอด24ชม. | P11: Jan | Q11: Dec | R11: Maintenance | S11: 3 | T11: 1 | U11: =V11 -> M11 | V11: =IF(AND(T11=1,S11=1),"L16",IF(AND(T11=1,S11=2),"L14",IF(AND(T11=1,S11=3),"M11",IF(AND(T11=1,S11=4),"E4",IF(AND(T11=2,S11=1),"L15",IF(AND(T11=2,S11=2),"M12",IF(AND(T11=2,S11=3),"H7",IF(AND(T11=2,S11=4),"E3",IF(AND(T11=3,S11=1),"M13",IF(AND(T11=3,S11=2),"H9",IF(AND(T11=3,S11=3),"E6",IF(AND(T11=4,S11=4),"E2",IF(AND(T11=4,S11=1),"H10",IF(AND(T11=2,S11=4),"H8",IF(AND(T11=4,S11=3),"E5",IF(AND(T11=4,S11=4),"E1",FALSE)))))))))))))))) -> M11
A12: 5 | B12: ระบบท่อส่งไอน้ำชำรุด เนื่องจากอุบัติเหตุทางถนนทำให้ท่อขาด | D12: Operational Management | E12: 6.กระบวนการทางธุรกิจและการปฏิบัติการ | F12: 1. ไม่สามารถส่งไอน้ำได้ 2. ไม่สามารถส่งไอน้ำให้กับลูกค้าได้ 3. กระบวนการผลิตและส่งไอน้ำเกิดการหยุดชะงักได้ 4. สูญเสียรายได้ | G12: 1.ติดตั้งอุปกรณ์ป้องกันความเสียหายที่มีโอกาสเกิดกับระบบเชื่อมต่อ เช่น Barrior กันรถชน 2. มีแผนการซ่อมบำรุงรักษาระบบส่งจ่ายไอน้ำรายปี 3. มีแผนการตรวจสอบระบบส่งจ่ายไอน้ำตามระยะเวลาที่กำหนด 4.มีทีมปฏิบัติการในกรณีฉุกเฉิน (on-call) ตลอด 24 ชม. สำหรับงานซ่อมเร่งด่วน 5.จัดเตรียม อะไหล่ที่ไว้ใช้ซ่อมท่อ ให้พร้อม พร้อมทีม ซ่อม online stop leak 6.มีการประสานกับ Supplier ให้พร้อมกับการซ่อมระบบท่อ ตลอด 24 ชั่วโมง | H12: 4 | I12: 1 | J12: =K12 -> E4 | K12: =IF(AND(I12=1,H12=1),"L16",IF(AND(I12=1,H12=2),"L14",IF(AND(I12=1,H12=3),"M11",IF(AND(I12=1,H12=4),"E4",IF(AND(I12=2,H12=1),"L15",IF(AND(I12=2,H12=2),"M12",IF(AND(I12=2,H12=3),"H7",IF(AND(I12=2,H12=4),"E3",IF(AND(I12=3,H12=1),"M13",IF(AND(I12=3,H12=2),"H9",IF(AND(I12=3,H12=3),"E6",IF(AND(I12=4,H12=4),"E2",IF(AND(I12=4,H12=1),"H10",IF(AND(H12=2,I12=4),"H8",IF(AND(I12=4,H12=3),"E5",IF(AND(I12=4,H12=4),"E1",FALSE)))))))))))))))) -> E4 | L12: 4 วัน | M12: 3 วัน | N12: 1 | O12: 1.ให้มีทีมซ่อมบำรุงชำนาญเฉพาะทาง ประสานงานกับทาง Vender และมีการเตรียมชิ้นส่วนอะไหล่ ตลอด24 ชม. เพื่อใช้งานและไม่ต้องเสียเวลาในการรอคอย ในขณะที่ตาม oncall 2.ให้มีทีมซ่อมสายส่งของ Vender (Contactor)ตลอด24ชม. | P12: Jan | Q12: Dec | R12: Maintenance | S12: 3 | T12: 1 | U12: =V12 -> M11 | V12: =IF(AND(T12=1,S12=1),"L16",IF(AND(T12=1,S12=2),"L14",IF(AND(T12=1,S12=3),"M11",IF(AND(T12=1,S12=4),"E4",IF(AND(T12=2,S12=1),"L15",IF(AND(T12=2,S12=2),"M12",IF(AND(T12=2,S12=3),"H7",IF(AND(T12=2,S12=4),"E3",IF(AND(T12=3,S12=1),"M13",IF(AND(T12=3,S12=2),"H9",IF(AND(T12=3,S12=3),"E6",IF(AND(T12=4,S12=4),"E2",IF(AND(T12=4,S12=1),"H10",IF(AND(T12=2,S12=4),"H8",IF(AND(T12=4,S12=3),"E5",IF(AND(T12=4,S12=4),"E1",FALSE)))))))))))))))) -> M11
A13: 6 | B13: เครื่องจักรสำคัญเสียหาย กรณี UPS ไม่สามารถจ่ายกระแสไฟฟ้าเนื่องจากอุปกรณ์ภายในเสียหายต่อระบบSubstation /GIS /TR เกิดการลัดวงจร | D13: Operational Management | E13: 6.กระบวนการทางธุรกิจและการปฏิบัติการ | F13: 1.ไม่สามารถขนานเครื่องเข้าระบบได้ ทำให้ไม่สามารถส่งมอบผลิตภัณฑ์ให้ลูกค้า 2. สูญเสียรายได้ 3.ไม่สามารถส่งมอบผลิตภัณฑ์ให้กับลูกค้าได้ 4.ระบบเครื่องจักรการผลิตหยุดชะงัก | G13: 1. มีแผนซ่อมบำรุงรักษาประจำปี/ ประจำเดือน โดยบริษัทผู้ผลิต 2. มีการติดตั้งอุปกรณ์สำรอง UPS Redundant 3. มีการจด log sheet เพื่อประเมินค่าของอุปกรณ์ว่าผิดปกติหรือไม่และ Vitual check ขณะทำการจด log sheet 4. มีระบบควบคุมอัตโนมัติ (Emergency) และระบบป้องกันอุปกรณ์(Protection)) เพื่อป้องกันเครื่องจักรเสียหาย | H13: 4 | I13: 1 | J13: =K13 -> E4 | K13: =IF(AND(I13=1,H13=1),"L16",IF(AND(I13=1,H13=2),"L14",IF(AND(I13=1,H13=3),"M11",IF(AND(I13=1,H13=4),"E4",IF(AND(I13=2,H13=1),"L15",IF(AND(I13=2,H13=2),"M12",IF(AND(I13=2,H13=3),"H7",IF(AND(I13=2,H13=4),"E3",IF(AND(I13=3,H13=1),"M13",IF(AND(I13=3,H13=2),"H9",IF(AND(I13=3,H13=3),"E6",IF(AND(I13=4,H13=4),"E2",IF(AND(I13=4,H13=1),"H10",IF(AND(H13=2,I13=4),"H8",IF(AND(I13=4,H13=3),"E5",IF(AND(I13=4,H13=4),"E1",FALSE)))))))))))))))) -> E4 | L13: 1 วัน | M13: 1 ชม | N13: 1 | O13: 1.ให้มีทีมซ่อมบำรุงชำนาญเฉพาะทาง ประสานงานกับทาง Vender และมีการเตรียมชิ้นส่วนอะไหล่ ตลอด24 ชม. เพื่อใช้งานและไม่ต้องเสียเวลาในการรอคอย ในขณะที่ตาม oncall 2.ให้มีทีมซ่อมสายส่งของ Vender (Contactor) ตลอด24ชม. | P13: Jan | Q13: Dec | R13: Maintenance | S13: 3 | T13: 1 | U13: =V13 -> M11 | V13: =IF(AND(T13=1,S13=1),"L16",IF(AND(T13=1,S13=2),"L14",IF(AND(T13=1,S13=3),"M11",IF(AND(T13=1,S13=4),"E4",IF(AND(T13=2,S13=1),"L15",IF(AND(T13=2,S13=2),"M12",IF(AND(T13=2,S13=3),"H7",IF(AND(T13=2,S13=4),"E3",IF(AND(T13=3,S13=1),"M13",IF(AND(T13=3,S13=2),"H9",IF(AND(T13=3,S13=3),"E6",IF(AND(T13=4,S13=4),"E2",IF(AND(T13=4,S13=1),"H10",IF(AND(T13=2,S13=4),"H8",IF(AND(T13=4,S13=3),"E5",IF(AND(T13=4,S13=4),"E1",FALSE)))))))))))))))) -> M11
A14: 7 | B14: ระบบเทคโนโลยีสารสนเทศไม่สามารถใช้งานการโจมตีทางไซเบอร์ (Cyber Attack) | D14: Operational Management | E14: 6.กระบวนการทางธุรกิจและการปฏิบัติการ | F14: 1.ไม่สามารถเข้าใช้งานระบบงานและ Application ที่สำคัญได้ 2.ไม่สามารถทำธุรกรรมทางการเงินผ่านระบบสารสนเทศได้ 3.มีผลกระทบต่อชื่อเสียงของบริษัท | G14: 1.มีการติดตั้ง Software ในการป้องกันไวรัสโจมตี 2.มีการเฝ้าระวังการโจมตีทาง Cyber จาก PTT Digital ตลอด 24 ชม 3.ทบทวนรายงานผลการตรวจสอบประสิทธิภาพการทำงานประจำวัน | H14: 4 | I14: 1 | J14: =K14 -> E4 | K14: =IF(AND(I14=1,H14=1),"L16",IF(AND(I14=1,H14=2),"L14",IF(AND(I14=1,H14=3),"M11",IF(AND(I14=1,H14=4),"E4",IF(AND(I14=2,H14=1),"L15",IF(AND(I14=2,H14=2),"M12",IF(AND(I14=2,H14=3),"H7",IF(AND(I14=2,H14=4),"E3",IF(AND(I14=3,H14=1),"M13",IF(AND(I14=3,H14=2),"H9",IF(AND(I14=3,H14=3),"E6",IF(AND(I14=4,H14=4),"E2",IF(AND(I14=4,H14=1),"H10",IF(AND(H14=2,I14=4),"H8",IF(AND(I14=4,H14=3),"E5",IF(AND(I14=4,H14=4),"E1",FALSE)))))))))))))))) -> E4 | L14: 1 วัน | M14: 1 วัน | N14: 1 | O14: 1.งดทำธุรกรรมทางการเงินผ่านระบบเทคโนโลยีสารสนเทศทั้งหมด 2.สื่อสารให้คนที่ได้รับผลกระทบทราบ ให้ใช้ระบบ Manual 3.ปิดระบบ IT ทั้งหมด จนกว่าจะดำเนินการแก้ไขเสร็จ | P14: Jan | Q14: Dec | R14: ICT | S14: 3 | T14: 1 | U14: =V14 -> M11 | V14: =IF(AND(T14=1,S14=1),"L16",IF(AND(T14=1,S14=2),"L14",IF(AND(T14=1,S14=3),"M11",IF(AND(T14=1,S14=4),"E4",IF(AND(T14=2,S14=1),"L15",IF(AND(T14=2,S14=2),"M12",IF(AND(T14=2,S14=3),"H7",IF(AND(T14=2,S14=4),"E3",IF(AND(T14=3,S14=1),"M13",IF(AND(T14=3,S14=2),"H9",IF(AND(T14=3,S14=3),"E6",IF(AND(T14=4,S14=4),"E2",IF(AND(T14=4,S14=1),"H10",IF(AND(T14=2,S14=4),"H8",IF(AND(T14=4,S14=3),"E5",IF(AND(T14=4,S14=4),"E1",FALSE)))))))))))))))) -> M11
A15: 8 | B15: สายส่งไฟฟ้า 115 KV PEA /EGAT ชำรุด ไม่สามารถจ่ายไฟมายัง GPSC ได้เป็นระยะเวลานานเกิน 24 ชั่วโมง | D15: Operational Management | E15: 6.กระบวนการทางธุรกิจและการปฏิบัติการ | F15: 1.Plant Blackout ไม่สามารถทำการผลิตได้ | G15: 1.มีระบบป้องกัน Relay protection และมีการตรวจสอบตามระยะเวลาที่กำหนด 2.ออกแบบให้ระบบสามารถเดินเครื่องแบบ Icelanding 3.มีการตรวจวัดความร้อนของสายส่ง 4.มีทีม Hot line oncall 24 hrs. 5.มีระบบในการรับไฟฟ้าได้ 2 แหล่งได้แก่ Sub บ้านฉ่าง และ มาบตาพุต | H15: 3 | I15: 1 | J15: =K15 -> M11 | K15: =IF(AND(I15=1,H15=1),"L16",IF(AND(I15=1,H15=2),"L14",IF(AND(I15=1,H15=3),"M11",IF(AND(I15=1,H15=4),"E4",IF(AND(I15=2,H15=1),"L15",IF(AND(I15=2,H15=2),"M12",IF(AND(I15=2,H15=3),"H7",IF(AND(I15=2,H15=4),"E3",IF(AND(I15=3,H15=1),"M13",IF(AND(I15=3,H15=2),"H9",IF(AND(I15=3,H15=3),"E6",IF(AND(I15=4,H15=4),"E2",IF(AND(I15=4,H15=1),"H10",IF(AND(H15=2,I15=4),"H8",IF(AND(I15=4,H15=3),"E5",IF(AND(I15=4,H15=4),"E1",FALSE)))))))))))))))) -> M11 | L15: 1 วัน | M15: 1 วัน | N15: 1 | O15: 1.มีการแจ้งประสานงานกับ PEA / EGATกรณีพบความผิดปกติของสายส่ง | P15: Jan | Q15: Dec | R15: Maintenance | S15: 2 | T15: 1 | U15: =V15 -> L14 | V15: =IF(AND(T15=1,S15=1),"L16",IF(AND(T15=1,S15=2),"L14",IF(AND(T15=1,S15=3),"M11",IF(AND(T15=1,S15=4),"E4",IF(AND(T15=2,S15=1),"L15",IF(AND(T15=2,S15=2),"M12",IF(AND(T15=2,S15=3),"H7",IF(AND(T15=2,S15=4),"E3",IF(AND(T15=3,S15=1),"M13",IF(AND(T15=3,S15=2),"H9",IF(AND(T15=3,S15=3),"E6",IF(AND(T15=4,S15=4),"E2",IF(AND(T15=4,S15=1),"H10",IF(AND(T15=2,S15=4),"H8",IF(AND(T15=4,S15=3),"E5",IF(AND(T15=4,S15=4),"E1",FALSE)))))))))))))))) -> L14

Sheet 1.4 RA Plant Incident 
A1: No. | B1: Product & Service ผลิตภัณฑ์และบริการ | C1: Process กระบวนการผลิต | D1: Risk Category ประเภทความเสี่ยง | E1: Impact Type ประเภทผลกระทบ | F1: Posible Risk ความเสี่ยงที่เป็นไปได้ | G1: Existing Control มาตรการควบคุมที่มีอยู่ | H1: Risk Assessment | O1: Mitigation Plan (new countermeasure to reduce threats) | P1: Time Frame | R1: Responsible Person | S1: Target
H2: I | I2: L | J2: R | K2: R | L2: MTPD | M2: RTO | N2: MBCO | P2: From | Q2: To | S2: I | T2: L | U2: R | V2: R
A3: 1 | B3: 1. Plant incident | C3: ABCT breaker 5YB-01 trip by relay 87L operate | D3: Operational Management | E3: 5. ลูกค้า คู่ค้า | F3: 1.ไม่สามารถส่งกระแสไฟฟ้าให้กับลูกค้าได้ 2. แรงดันของไอน้ำในระบบลดลง | G3: 1. มีการประชุมกับลูกค้าเพื่อวางแผนซ่อมบำรุงรักษาประจำปี/ ประจำเดือน 2.มีแผนการตรวจสอบระบบเครื่องจักร ตามระยะเวลาที่กำหนด 3. มีการจด log sheet เพื่อประเมินค่าของอุปกรณ์ว่าผิดปกติหรือไม่และ Visual check ขณะทำการจด log sheet 4.มีระบบควบคุมอัตโนมัติ (Emergency) และระบบป้องกันอุปกรณ์(Protection)) เพื่อป้องกันเครื่องจักรเสียหาย 5.มีระบบควบคุมไฟฟ้าโดยอัติโนมัติโดยโปรแกรม PMC 6.มีการจัดทำแผนตอบโต้ฉุกเฉิน ตาม Mitigation plan ภายในการเดินเครื่อง 7.มีระบบควบคุมแรงดันไอน้ำแบบอัตโนมัติ | H3: 2 | I3: 2 | J3: =K3 -> M12 | K3: =IF(AND(I3=1,H3=1),"L16",IF(AND(I3=1,H3=2),"L14",IF(AND(I3=1,H3=3),"M11",IF(AND(I3=1,H3=4),"E4",IF(AND(I3=2,H3=1),"L15",IF(AND(I3=2,H3=2),"M12",IF(AND(I3=2,H3=3),"H7",IF(AND(I3=2,H3=4),"E3",IF(AND(I3=3,H3=1),"M13",IF(AND(I3=3,H3=2),"H9",IF(AND(I3=3,H3=3),"E6",IF(AND(I3=4,H3=4),"E2",IF(AND(I3=4,H3=1),"H10",IF(AND(H3=2,I3=4),"H8",IF(AND(I3=4,H3=3),"E5",IF(AND(I3=4,H3=4),"E1",FALSE)))))))))))))))) -> M12 | L3: ='2.2.2 BIA Plant Incident 2'!N8 -> 24 ชม | M3: ='2.2.2 BIA Plant Incident 2'!O8 -> 1 ชม | N3: ='2.2.2 BIA Plant Incident 2'!P8 -> 1 | O3: 1.ให้มีทีมซ่อมบำรุง และชิ้นส่วนอะไหล่ ตลอด24 ชม. เพื่อไม่ต้องเสียเวลาในการรอคอย ในขณะที่ตาม oncall 2.จัดทีมคณะทำงานลดการเกิด Incident เรื่อง Trip reduction | P3: Jan | Q3: Dec | R3: O&M | S3: 1 | T3: 2 | U3: =V3 -> L15 | V3: =IF(AND(T3=1,S3=1),"L16",IF(AND(T3=1,S3=2),"L14",IF(AND(T3=1,S3=3),"M11",IF(AND(T3=1,S3=4),"E4",IF(AND(T3=2,S3=1),"L15",IF(AND(T3=2,S3=2),"M12",IF(AND(T3=2,S3=3),"H7",IF(AND(T3=2,S3=4),"E3",IF(AND(T3=3,S3=1),"M13",IF(AND(T3=3,S3=2),"H9",IF(AND(T3=3,S3=3),"E6",IF(AND(T3=4,S3=4),"E2",IF(AND(T3=4,S3=1),"H10",IF(AND(T3=2,S3=4),"H8",IF(AND(T3=4,S3=3),"E5",IF(AND(T3=4,S3=4),"E1",FALSE)))))))))))))))) -> L15
A4: 2 | B4: 1. Plant incident | C4: CUP1 plant blackout. | D4: Operational Management | E4: 5. ลูกค้า คู่ค้า | F4: 1.ไม่สามารถส่งกระแสไฟฟ้าให้กับลูกค้าได้ 2. แรงดันของไอน้ำในระบบลดลง | G4: 1. มีแผนซ่อมบำรุงรักษาประจำปี/ ประจำเดือน 2.มีแผนการตรวจสอบระบบเครื่องจักร ตามระยะเวลาที่กำหนด 3. มีการจด log sheet เพื่อประเมินค่าของอุปกรณ์ว่าผิดปกติหรือไม่และ Visual check ขณะทำการจด log sheet 4.มีระบบควบคุมอัตโนมัติ (Emergency) และระบบป้องกันอุปกรณ์(Protection)) เพื่อป้องกันเครื่องจักรเสียหาย 5.มีการจัดทำแผนตอบโต้ฉุกเฉิน ตาม Mitigation plan ภายในการเดินเครื่อง 6.มีระบบควบคุมแรงดันไอน้ำแบบอัตโนมัติ | H4: 3 | I4: 2 | J4: =K4 -> H7 | K4: =IF(AND(I4=1,H4=1),"L16",IF(AND(I4=1,H4=2),"L14",IF(AND(I4=1,H4=3),"M11",IF(AND(I4=1,H4=4),"E4",IF(AND(I4=2,H4=1),"L15",IF(AND(I4=2,H4=2),"M12",IF(AND(I4=2,H4=3),"H7",IF(AND(I4=2,H4=4),"E3",IF(AND(I4=3,H4=1),"M13",IF(AND(I4=3,H4=2),"H9",IF(AND(I4=3,H4=3),"E6",IF(AND(I4=4,H4=4),"E2",IF(AND(I4=4,H4=1),"H10",IF(AND(H4=2,I4=4),"H8",IF(AND(I4=4,H4=3),"E5",IF(AND(I4=4,H4=4),"E1",FALSE)))))))))))))))) -> H7 | L4: 24 ชม | M4: 2 ชม | N4: 1 | O4: 1.ให้มีทีมซ่อมบำรุง และชิ้นส่วนอะไหล่ ตลอด24 ชม. เพื่อไม่ต้องเสียเวลาในการรอคอย ในขณะที่ตาม oncall 2.จัดทีมคณะทำงานลดการเกิด Incident เรื่อง Trip reduction | P4: Jan | Q4: Dec | R4: O&M | S4: 2 | T4: 2 | U4: =V4 -> M12 | V4: =IF(AND(T4=1,S4=1),"L16",IF(AND(T4=1,S4=2),"L14",IF(AND(T4=1,S4=3),"M11",IF(AND(T4=1,S4=4),"E4",IF(AND(T4=2,S4=1),"L15",IF(AND(T4=2,S4=2),"M12",IF(AND(T4=2,S4=3),"H7",IF(AND(T4=2,S4=4),"E3",IF(AND(T4=3,S4=1),"M13",IF(AND(T4=3,S4=2),"H9",IF(AND(T4=3,S4=3),"E6",IF(AND(T4=4,S4=4),"E2",IF(AND(T4=4,S4=1),"H10",IF(AND(T4=2,S4=4),"H8",IF(AND(T4=4,S4=3),"E5",IF(AND(T4=4,S4=4),"E1",FALSE)))))))))))))))) -> M12
A5: 3 | B5: 1. Plant incident | C5: PTTAC 115 kV CB 7YB-01 opened to PTTAC was tripped by alarm reverse power relay | D5: Operational Management | E5: 5. ลูกค้า คู่ค้า | F5: 1.ไม่สามารถส่งกระแสไฟฟ้าให้กับลูกค้าได้ 2. แรงดันของไอน้ำในระบบลดลง | G5: 1. มีแผนซ่อมบำรุงรักษาประจำปี/ ประจำเดือน 2.มีแผนการตรวจสอบระบบเครื่องจักร ตามระยะเวลาที่กำหนด 3. มีการจด log sheet เพื่อประเมินค่าของอุปกรณ์ว่าผิดปกติหรือไม่และ Visual check ขณะทำการจด log sheet 4.มีระบบควบคุมอัตโนมัติ (Emergency) และระบบป้องกันอุปกรณ์(Protection)) เพื่อป้องกันเครื่องจักรเสียหาย 5.มีการจัดทำแผนตอบโต้ฉุกเฉิน ตาม Mitigation plan ภายในการเดินเครื่อง 6.มีระบบควบคุมแรงดันไอน้ำแบบอัตโนมัติ | H5: 2 | I5: 2 | J5: =K5 -> M12 | K5: =IF(AND(I5=1,H5=1),"L16",IF(AND(I5=1,H5=2),"L14",IF(AND(I5=1,H5=3),"M11",IF(AND(I5=1,H5=4),"E4",IF(AND(I5=2,H5=1),"L15",IF(AND(I5=2,H5=2),"M12",IF(AND(I5=2,H5=3),"H7",IF(AND(I5=2,H5=4),"E3",IF(AND(I5=3,H5=1),"M13",IF(AND(I5=3,H5=2),"H9",IF(AND(I5=3,H5=3),"E6",IF(AND(I5=4,H5=4),"E2",IF(AND(I5=4,H5=1),"H10",IF(AND(H5=2,I5=4),"H8",IF(AND(I5=4,H5=3),"E5",IF(AND(I5=4,H5=4),"E1",FALSE)))))))))))))))) -> M12 | L5: 24 ชม | M5: 1 ชม | N5: 1 | O5: 1.ให้มีทีมซ่อมบำรุง และชิ้นส่วนอะไหล่ ตลอด24 ชม. เพื่อไม่ต้องเสียเวลาในการรอคอย ในขณะที่ตาม oncall 2.จัดทีมคณะทำงานลดการเกิด Incident เรื่อง Trip reduction | P5: Jan | Q5: Dec | R5: O&M | S5: 1 | T5: 2 | U5: =V5 -> L15 | V5: =IF(AND(T5=1,S5=1),"L16",IF(AND(T5=1,S5=2),"L14",IF(AND(T5=1,S5=3),"M11",IF(AND(T5=1,S5=4),"E4",IF(AND(T5=2,S5=1),"L15",IF(AND(T5=2,S5=2),"M12",IF(AND(T5=2,S5=3),"H7",IF(AND(T5=2,S5=4),"E3",IF(AND(T5=3,S5=1),"M13",IF(AND(T5=3,S5=2),"H9",IF(AND(T5=3,S5=3),"E6",IF(AND(T5=4,S5=4),"E2",IF(AND(T5=4,S5=1),"H10",IF(AND(T5=2,S5=4),"H8",IF(AND(T5=4,S5=3),"E5",IF(AND(T5=4,S5=4),"E1",FALSE)))))))))))))))) -> L15

Sheet 2. BIA Product
A1: แบบวิเคราะห์ผลกระทบทางธุรกิจ Business Impact Analysis Form
A3: ผู้ประเมิน | B3: =#REF! -> #REF! | D3: ชื่อหน่วยงาน | F3: =#REF! -> #REF! | M3: วันที่ประเมิน | N3: =#REF! -> #REF! | AE3: =AE8&AE9&AE10&AE11 -> ปตท. WHA PEA EGAT
A4: วิธีการประเมิน | B4: =#REF! -> #REF! | D4: ชื่อพื้นที่ประเมิน | F4: =#REF! -> #REF! | M4: ทบทวนครั้งที่ | N4: =#REF! -> #REF! | AE4: ปตท.WHAPEAEGAT
A6: Product & Service ผลิตภัณฑ์และบริการ | B6: Impact Category ประเภทของผลกระทบที่เกิดขึ้น | C6: Severity of Impact Over Time ระดับผลกระทบที่เพิ่มขึ้นในแต่ละวัน | M6: Maximum Tolerable Period of Disruption (MTPD) | N6: Recovery Time Objective (RTO) | O6: Minimum Business Continuity Objective (MBCO) | P6: Crisis ภัยคุกคาม | Q6: Resource ทรัพยากร
C7: 1 Hour | D7: 4 Hour | E7: 8 Hour | F7: 12 Hour | G7: 24 Hour | H7: 3 Days | I7: 14 Days | J7: 30 Days | K7: รวมคะแนน | L7: การจัดลำดับ | Q7: People บุคลากร (ปกติ) | R7: People บุคลากร (ฉุกเฉิน) | S7: Information สารสนเทศและข้อมูล (ปกติ) | T7: Information สารสนเทศและข้อมูล (ฉุกเฉิน) | U7: Building โครงสร้างพื้นฐานทางกายภาพ เช่นอาคาร (ปกติ) | V7: Building โครงสร้างพื้นฐานทางกายภาพ เช่นอาคาร (ฉุกเฉิน) | W7: Equipment อุปกรณ์และโภคภัณฑ์ (ปกติ) | X7: Equipment อุปกรณ์และโภคภัณฑ์ (ฉุกเฉิน) | Y7: ICT ระบบเทคโนโลยีสารสนเทศและการสื่อสาร (ปกติ) | Z7: ICT ระบบเทคโนโลยีสารสนเทศและการสื่อสาร (ฉุกเฉิน) | AA7: Logistics การขนส่งและโลจิสติกส์ (ปกติ) | AB7: Logistics การขนส่งและโลจิสติกส์ (ฉุกเฉิน) | AC7: Finance การเงิน (ปกติ) | AD7: Finance การเงิน (ฉุกเฉิน) | AE7: Supplier หุ้นส่วนและผู้ส่งมอบ (ปกติ) | AF7: Supplier หุ้นส่วนและผู้ส่งมอบ (ฉุกเฉิน)
A8: ควบคุมการผลิตไฟฟ้าและดูแลการปฏิบัติการผลิตให้กับลูกค้า | B8: 1. การเงิน | C8: 2 | D8: 2 | E8: 2 | F8: 3 | G8: 4 | H8: 4 | I8: 4 | J8: 4 | K8: =SUM(C8*8)+(D8*7)+(E8*6)+(F8*5)+(G8*4)+(H8*3)+(I8*2)+(J8*1) -> 97 | L8: =IF(K8<=36,"Priority4",IF(K8<=72,"Priority3",IF(K8<=99,"Priority2",IF(K8>=100,"Priority1")))) -> Priority2 | M8: 24 Hours | N8: 24 Hours | O8: 50% (80 MW) | P8: 1.Water loss 2.Steam loss 3.Power loss 4.NG loss 5.ไฟใหม้ 6.Cyber attack 7.โรคระบาด | Q8: Operation 9 คน Maintenance 4 คน Safety 1 คน | R8: Operation 16 คน Maintenance 4 คน Safety 1 คน | S8: Procedure / WI P&ID Production plan Single Line Diagram Contract Agreement | T8: Procedure / WI P&ID Production plan Single Line Diagram Contract Agreement | U8: Control Room | V8: 1.Emergency Control Center (ECC) 2.CCB | W8: คอมพิวเตอร์ 8 วิทยุสื่อสาร 13 โทรศัพท์มือถือ 1 โทรศัพท์ Plant 3 Hot Line 3 | X8: วิทยุสื่อสาร 13 คอมพิวเตอร์ 8 โทรศัพท์ 4 ทีมซ่อมบำรุง และชิ้นส่วนอะไหล่ ตลอด 24 ชม. | Y8: ระบบ VPN Internet PI | Z8: ระบบ VPN Internet PI | AA8: รถยนต์ 1 คัน | AB8: รถยนต์ 1 คัน | AC8: - | AD8: เงินสำรอง | AE8: ปตท. WHA PEA EGAT | AF8: ปตท. WHA PEA EGAT
B9: 2. กฏหมาย กฏระเบียบ ข้อบังคับ และสัญญา / ข้อตกลงระดับของการให้บริการ | C9: 2 | D9: 3 | E9: 3 | F9: 3 | G9: 4 | H9: 4 | I9: 4 | J9: 4 | K9: =SUM(C9*8)+(D9*7)+(E9*6)+(F9*5)+(G9*4)+(H9*3)+(I9*2)+(J9*1) -> 110 | L9: =IF(K9<=36,"Priority4",IF(K9<=72,"Priority3",IF(K9<=99,"Priority2",IF(K9>=100,"Priority1")))) -> Priority1
B10: 3. ความปลอดภัยอาชีวอนามัยของบุคลากร | C10: 1 | D10: 1 | E10: 1 | F10: 1 | G10: 1 | H10: 1 | I10: 1 | J10: 1 | K10: =SUM(C10*8)+(D10*7)+(E10*6)+(F10*5)+(G10*4)+(H10*3)+(I10*2)+(J10*1) -> 36 | L10: =IF(K10<=36,"Priority4",IF(K10<=72,"Priority3",IF(K10<=99,"Priority2",IF(K10>=100,"Priority1")))) -> Priority4
B11: 4. สิ่งแวดล้อม | C11: 2 | D11: 2 | E11: 2 | F11: 2 | G11: 2 | H11: 2 | I11: 2 | J11: 2 | K11: =SUM(C11*8)+(D11*7)+(E11*6)+(F11*5)+(G11*4)+(H11*3)+(I11*2)+(J11*1) -> 72 | L11: =IF(K11<=36,"Priority4",IF(K11<=72,"Priority3",IF(K11<=99,"Priority2",IF(K11>=100,"Priority1")))) -> Priority3
B12: 5. ลูกค้า คู่ค้า | C12: 2 | D12: 3 | E12: 3 | F12: 3 | G12: 4 | H12: 4 | I12: 4 | J12: 4 | K12: =SUM(C12*8)+(D12*7)+(E12*6)+(F12*5)+(G12*4)+(H12*3)+(I12*2)+(J12*1) -> 110 | L12: =IF(K12<=36,"Priority4",IF(K12<=72,"Priority3",IF(K12<=99,"Priority2",IF(K12>=100,"Priority1")))) -> Priority1
B13: 6. กระบวนการทางธุรกิจ และการปฏิบัติการ | C13: 2 | D13: 2 | E13: 2 | F13: 2 | G13: 4 | H13: 4 | I13: 4 | J13: 4 | K13: =SUM(C13*8)+(D13*7)+(E13*6)+(F13*5)+(G13*4)+(H13*3)+(I13*2)+(J13*1) -> 92 | L13: =IF(K13<=36,"Priority4",IF(K13<=72,"Priority3",IF(K13<=99,"Priority2",IF(K13>=100,"Priority1")))) -> Priority2
B14: 7. ชื่อเสียงภาพลักษณ์ต่อองค์กร | C14: 1 | D14: 2 | E14: 2 | F14: 3 | G14: 4 | H14: 4 | I14: 4 | J14: 4 | K14: =SUM(C14*8)+(D14*7)+(E14*6)+(F14*5)+(G14*4)+(H14*3)+(I14*2)+(J14*1) -> 89 | L14: =IF(K14<=36,"Priority4",IF(K14<=72,"Priority3",IF(K14<=99,"Priority2",IF(K14>=100,"Priority1")))) -> Priority2
A15: ควบคุมการผลิตไอน้ำและดูแลการปฏิบัติการผลิตให้กับลูกค้า | B15: 1. การเงิน | C15: 2 | D15: 2 | E15: 2 | F15: 3 | G15: 4 | H15: 4 | I15: 4 | J15: 4 | K15: =SUM(C15*8)+(D15*7)+(E15*6)+(F15*5)+(G15*4)+(H15*3)+(I15*2)+(J15*1) -> 97 | L15: =IF(K15<=36,"Priority4",IF(K15<=72,"Priority3",IF(K15<=99,"Priority2",IF(K15>=100,"Priority1")))) -> Priority2 | M15: 24 Hours | N15: 24 Hours | O15: 68% (410 t/h) | P15: 1.Water loss 2.Steam loss 3.Power loss 4.NG loss 5.ไฟใหม้ 6.Cyber attack 7.โรคระบาด | Q15: Operation 9 คน Maintenance 4 คน Safety 1 คน | R15: Operation 16 คน Maintenance 4 คน Safety 1 คน | S15: Procedure / WI P&ID Production plan Single Line Diagram Contract Agreement | T15: Procedure / WI P&ID Production plan Single Line Diagram Contract Agreement | U15: Control Room | V15: 1.Emergency Control Center (ECC) 2.CCB | W15: คอมพิวเตอร์ 8 วิทยุสื่อสาร 13 โทรศัพท์มือถือ 1 โทรศัพท์ Plant 3 Hot Line 3 | X15: วิทยุสื่อสาร 13 คอมพิวเตอร์ 8 โทรศัพท์ 4 ทีมซ่อมบำรุง และชิ้นส่วนอะไหล่ ตลอด 24 ชม. | Y15: ระบบ VPN Internet PI | Z15: ระบบ VPN Internet PI | AA15: รถยนต์ 1 คัน | AB15: รถยนต์ 1 คัน | AC15: - | AD15: เงินสำรอง | AE15: ปตท. WHA PEA EGAT | AF15: ปตท. WHA PEA EGAT
B16: 2. กฏหมาย กฏระเบียบ ข้อบังคับ และสัญญา / ข้อตกลงระดับของการให้บริการ | C16: 2 | D16: 3 | E16: 3 | F16: 3 | G16: 4 | H16: 4 | I16: 4 | J16: 4 | K16: =SUM(C16*8)+(D16*7)+(E16*6)+(F16*5)+(G16*4)+(H16*3)+(I16*2)+(J16*1) -> 110 | L16: =IF(K16<=36,"Priority4",IF(K16<=72,"Priority3",IF(K16<=99,"Priority2",IF(K16>=100,"Priority1")))) -> Priority1
B17: 3. ความปลอดภัยอาชีวอนามัยของบุคลากร | C17: 1 | D17: 1 | E17: 1 | F17: 1 | G17: 1 | H17: 1 | I17: 1 | J17: 1 | K17: =SUM(C17*8)+(D17*7)+(E17*6)+(F17*5)+(G17*4)+(H17*3)+(I17*2)+(J17*1) -> 36 | L17: =IF(K17<=36,"Priority4",IF(K17<=72,"Priority3",IF(K17<=99,"Priority2",IF(K17>=100,"Priority1")))) -> Priority4
B18: 4. สิ่งแวดล้อม | C18: 2 | D18: 2 | E18: 2 | F18: 2 | G18: 2 | H18: 2 | I18: 2 | J18: 2 | K18: =SUM(C18*8)+(D18*7)+(E18*6)+(F18*5)+(G18*4)+(H18*3)+(I18*2)+(J18*1) -> 72 | L18: =IF(K18<=36,"Priority4",IF(K18<=72,"Priority3",IF(K18<=99,"Priority2",IF(K18>=100,"Priority1")))) -> Priority3
B19: 5. ลูกค้า คู่ค้า | C19: 2 | D19: 3 | E19: 3 | F19: 3 | G19: 4 | H19: 4 | I19: 4 | J19: 4 | K19: =SUM(C19*8)+(D19*7)+(E19*6)+(F19*5)+(G19*4)+(H19*3)+(I19*2)+(J19*1) -> 110 | L19: =IF(K19<=36,"Priority4",IF(K19<=72,"Priority3",IF(K19<=99,"Priority2",IF(K19>=100,"Priority1")))) -> Priority1
B20: 6. กระบวนการทางธุรกิจ และการปฏิบัติการ | C20: 2 | D20: 2 | E20: 2 | F20: 2 | G20: 4 | H20: 4 | I20: 4 | J20: 4 | K20: =SUM(C20*8)+(D20*7)+(E20*6)+(F20*5)+(G20*4)+(H20*3)+(I20*2)+(J20*1) -> 92 | L20: =IF(K20<=36,"Priority4",IF(K20<=72,"Priority3",IF(K20<=99,"Priority2",IF(K20>=100,"Priority1")))) -> Priority2
B21: 7. ชื่อเสียงภาพลักษณ์ต่อองค์กร | C21: 1 | D21: 2 | E21: 2 | F21: 3 | G21: 4 | H21: 4 | I21: 4 | J21: 4 | K21: =SUM(C21*8)+(D21*7)+(E21*6)+(F21*5)+(G21*4)+(H21*3)+(I21*2)+(J21*1) -> 89 | L21: =IF(K21<=36,"Priority4",IF(K21<=72,"Priority3",IF(K21<=99,"Priority2",IF(K21>=100,"Priority1")))) -> Priority2
A22: ควบคุมการผลิตน้ำและดูแลการปฏิบัติการผลิตให้กับลูกค้า | B22: 1. การเงิน | C22: 2 | D22: 2 | E22: 2 | F22: 3 | G22: 4 | H22: 4 | I22: 4 | J22: 4 | K22: =SUM(C22*8)+(D22*7)+(E22*6)+(F22*5)+(G22*4)+(H22*3)+(I22*2)+(J22*1) -> 97 | L22: =IF(K22<=36,"Priority4",IF(K22<=72,"Priority3",IF(K22<=99,"Priority2",IF(K22>=100,"Priority1")))) -> Priority2 | M22: 24 Hours | N22: 24 Hours | O22: 100% (430 m3/h) | P22: 1.Water loss 2.Steam loss 3.Power loss 4.NG loss 5.ไฟใหม้ 6.Cyber attack 7.โรคระบาด | Q22: Operation 9 คน Maintenance 4 คน Safety 1 คน | R22: Operation 16 คน Maintenance 4 คน Safety 1 คน | S22: Procedure / WI P&ID Production plan Single Line Diagram Contract Agreement | T22: Procedure / WI P&ID Production plan Single Line Diagram Contract Agreement | U22: Control Room | V22: 1.Emergency Control Center (ECC) 2.CCB | W22: คอมพิวเตอร์ 8 วิทยุสื่อสาร 13 โทรศัพท์มือถือ 1 โทรศัพท์ Plant 3 Hot Line 3 | X22: วิทยุสื่อสาร 13 คอมพิวเตอร์ 8 โทรศัพท์ 4 ทีมซ่อมบำรุง และชิ้นส่วนอะไหล่ ตลอด 24 ชม. | Y22: ระบบ VPN Internet PI | Z22: ระบบ VPN Internet PI | AA22: รถยนต์ 1 คัน | AB22: รถยนต์ 1 คัน | AC22: - | AD22: เงินสำรอง | AE22: ปตท. WHA PEA EGAT | AF22: ปตท. WHA PEA EGAT
B23: 2. กฏหมาย กฏระเบียบ ข้อบังคับ และสัญญา / ข้อตกลงระดับของการให้บริการ | C23: 2 | D23: 3 | E23: 3 | F23: 3 | G23: 4 | H23: 4 | I23: 4 | J23: 4 | K23: =SUM(C23*8)+(D23*7)+(E23*6)+(F23*5)+(G23*4)+(H23*3)+(I23*2)+(J23*1) -> 110 | L23: =IF(K23<=36,"Priority4",IF(K23<=72,"Priority3",IF(K23<=99,"Priority2",IF(K23>=100,"Priority1")))) -> Priority1
B24: 3. ความปลอดภัยอาชีวอนามัยของบุคลากร | C24: 1 | D24: 1 | E24: 1 | F24: 1 | G24: 1 | H24: 1 | I24: 1 | J24: 1 | K24: =SUM(C24*8)+(D24*7)+(E24*6)+(F24*5)+(G24*4)+(H24*3)+(I24*2)+(J24*1) -> 36 | L24: =IF(K24<=36,"Priority4",IF(K24<=72,"Priority3",IF(K24<=99,"Priority2",IF(K24>=100,"Priority1")))) -> Priority4
B25: 4. สิ่งแวดล้อม | C25: 2 | D25: 2 | E25: 2 | F25: 2 | G25: 2 | H25: 2 | I25: 2 | J25: 2 | K25: =SUM(C25*8)+(D25*7)+(E25*6)+(F25*5)+(G25*4)+(H25*3)+(I25*2)+(J25*1) -> 72 | L25: =IF(K25<=36,"Priority4",IF(K25<=72,"Priority3",IF(K25<=99,"Priority2",IF(K25>=100,"Priority1")))) -> Priority3
B26: 5. ลูกค้า คู่ค้า | C26: 2 | D26: 3 | E26: 3 | F26: 3 | G26: 4 | H26: 4 | I26: 4 | J26: 4 | K26: =SUM(C26*8)+(D26*7)+(E26*6)+(F26*5)+(G26*4)+(H26*3)+(I26*2)+(J26*1) -> 110 | L26: =IF(K26<=36,"Priority4",IF(K26<=72,"Priority3",IF(K26<=99,"Priority2",IF(K26>=100,"Priority1")))) -> Priority1
B27: 6. กระบวนการทางธุรกิจ และการปฏิบัติการ | C27: 2 | D27: 2 | E27: 2 | F27: 2 | G27: 4 | H27: 4 | I27: 4 | J27: 4 | K27: =SUM(C27*8)+(D27*7)+(E27*6)+(F27*5)+(G27*4)+(H27*3)+(I27*2)+(J27*1) -> 92 | L27: =IF(K27<=36,"Priority4",IF(K27<=72,"Priority3",IF(K27<=99,"Priority2",IF(K27>=100,"Priority1")))) -> Priority2
B28: 7. ชื่อเสียงภาพลักษณ์ต่อองค์กร | C28: 1 | D28: 2 | E28: 2 | F28: 3 | G28: 4 | H28: 4 | I28: 4 | J28: 4 | K28: =SUM(C28*8)+(D28*7)+(E28*6)+(F28*5)+(G28*4)+(H28*3)+(I28*2)+(J28*1) -> 89 | L28: =IF(K28<=36,"Priority4",IF(K28<=72,"Priority3",IF(K28<=99,"Priority2",IF(K28>=100,"Priority1")))) -> Priority2

Sheet 2.2 BIA Process
A1: แบบวิเคราะห์ผลกระทบทางธุรกิจ Business Impact Analysis Form
A3: ผู้ประเมิน | B3: =#REF! -> #REF! | D3: ชื่อหน่วยงาน | F3: =#REF! -> #REF! | N3: วันที่ประเมิน | O3: =#REF! -> #REF!
A4: วิธีการประเมิน | B4: =#REF! -> #REF! | D4: ชื่อพื้นที่ประเมิน | F4: =#REF! -> #REF! | N4: ทบทวนครั้งที่ | O4: =#REF! -> #REF!
A6: Process กระบวนการผลิต | B6: Impact Category ประเภทของผลกระทบที่เกิดขึ้น | C6: Severity of Impact Over Time ระดับผลกระทบที่เพิ่มขึ้นในแต่ละวัน | N6: Maximum Tolerable Period of Disruption (MTPD) | O6: Recovery Time Objective (RTO) | P6: Minimum Business Continuity Objective (MBCO)
C7: 1 Hour | D7: 4 Hour | E7: 8 Hour | F7: 12 Hour | G7: 24 Hour | H7: 3 Days | I7: 5 Days | J7: 7 Days | K7: 14 Days | L7: 21 Days | M7: 30 Days
A8: การรับวัตถุดิบ (น้ำDemin) | B8: D.การหยุดชะงักของการปฏิบัติงาน/หน้าที่และงานประจำวัน | C8: 1 | D8: 1 | E8: 1 | F8: 1 | G8: 4 | H8: 4 | I8: 4 | J8: 4 | K8: 4 | L8: 4 | M8: 4 | N8: 24 ชม | O8: 1 ชม | P8: 1
A9: การรับวัตถุดิบ (น้ำ Clearify water) | B9: D.การหยุดชะงักของการปฏิบัติงาน/หน้าที่และงานประจำวัน | C9: 1 | D9: 1 | E9: 1 | F9: 1 | G9: 4 | H9: 4 | I9: 4 | J9: 4 | K9: 4 | L9: 4 | M9: 4 | N9: 24 ชม | O9: 1 ชม | P9: 1
A10: การรับวัตถุดิบ (สารเคมี) | B10: D.การหยุดชะงักของการปฏิบัติงาน/หน้าที่และงานประจำวัน | C10: 1 | D10: 1 | E10: 1 | F10: 1 | G10: 4 | H10: 4 | I10: 4 | J10: 4 | K10: 4 | L10: 4 | M10: 4 | N10: 24 ชม | O10: 1 ชม | P10: 1
A11: การรับวัตถุดิบ (ก๊าซเชื้อเพลิง) | B11: D.การหยุดชะงักของการปฏิบัติงาน/หน้าที่และงานประจำวัน | C11: 1 | D11: 1 | E11: 1 | F11: 1 | G11: 2 | H11: 4 | I11: 4 | J11: 4 | K11: 4 | L11: 4 | M11: 4 | N11: 48 ชม | O11: 1 ชม | P11: 1
A12: การรับวัตถุดิบ (น้ำมันเชื้อเพลิงสำหรับระบบดับเพลิง) | B12: D.การหยุดชะงักของการปฏิบัติงาน/หน้าที่และงานประจำวัน | C12: 1 | D12: 1 | E12: 1 | F12: 1 | G12: 2 | H12: 4 | I12: 4 | J12: 4 | K12: 4 | L12: 4 | M12: 4 | N12: 48 ชม | O12: 1 ชม | P12: 1
A13: การรับวัตถุดิบ (ไฟฟ้าสำหรับ Start up process) | B13: D.การหยุดชะงักของการปฏิบัติงาน/หน้าที่และงานประจำวัน | C13: 1 | D13: 1 | E13: 1 | F13: 1 | G13: 2 | H13: 4 | I13: 4 | J13: 4 | K13: 4 | L13: 4 | M13: 4 | N13: 24 ชม | O13: 1 ชม | P13: 1
A14: เดินเครื่องระบบ BOP (Cooling, Air Compressor ) | B14: D.การหยุดชะงักของการปฏิบัติงาน/หน้าที่และงานประจำวัน | C14: 2 | D14: 2 | E14: 2 | F14: 2 | G14: 3 | H14: 3 | I14: 3 | J14: 4 | K14: 4 | L14: 4 | M14: 4 | N14: 7 วัน | O14: 7 วัน | P14: 1
A15: เดินเครื่องระบบ Fuel Gas | B15: D.การหยุดชะงักของการปฏิบัติงาน/หน้าที่และงานประจำวัน | C15: 2 | D15: 2 | E15: 2 | F15: 2 | G15: 3 | H15: 3 | I15: 3 | J15: 4 | K15: 4 | L15: 4 | M15: 4 | N15: 7 วัน | O15: 7 วัน | P15: 1
A16: เดินเครื่องระบบ Demin, Condensate และ Neutralization. | B16: D.การหยุดชะงักของการปฏิบัติงาน/หน้าที่และงานประจำวัน | C16: 2 | D16: 2 | E16: 2 | F16: 2 | G16: 3 | H16: 3 | I16: 3 | J16: 4 | K16: 4 | L16: 4 | M16: 4 | N16: 7 วัน | O16: 7 วัน | P16: 1
A17: เดินเครื่องระบบ BFW และ Deaerator | B17: D.การหยุดชะงักของการปฏิบัติงาน/หน้าที่และงานประจำวัน | C17: 2 | D17: 2 | E17: 2 | F17: 2 | G17: 3 | H17: 3 | I17: 3 | J17: 4 | K17: 4 | L17: 4 | M17: 4 | N17: 7 วัน | O17: 7 วัน | P17: 1
A18: เดินเครื่อง Aux Boiler , HRSG และ Emission Control. | B18: D.การหยุดชะงักของการปฏิบัติงาน/หน้าที่และงานประจำวัน | C18: 2 | D18: 2 | E18: 2 | F18: 2 | G18: 3 | H18: 3 | I18: 3 | J18: 4 | K18: 4 | L18: 4 | M18: 4 | N18: 7 วัน | O18: 7 วัน | P18: 1
A19: เดินเครื่องระบบ GTG | B19: D.การหยุดชะงักของการปฏิบัติงาน/หน้าที่และงานประจำวัน | C19: 2 | D19: 2 | E19: 2 | F19: 2 | G19: 3 | H19: 3 | I19: 3 | J19: 4 | K19: 4 | L19: 4 | M19: 4 | N19: 140 วัน | O19: 140 วัน | P19: 1
... A26: ระบบควบคุมการผลิต ( UPS ,DCS) | B26: D.การหยุดชะงักของการปฏิบัติงาน/หน้าที่และงานประจำวัน | C26: 1 | D26: 2 | E26: 2 | F26: 2 | G26: 2 | H26: 3 | I26: 3 | J26: 3 | K26: 3 | L26: 3 | M26: 4 | N26: 60 วัน | O26: 60 วัน | P26: 1

Sheet 2.2.2 BIA Plant Incident 2
A1: แบบวิเคราะห์ผลกระทบทางธุรกิจ Business Impact Analysis Form
A3: ผู้ประเมิน | B3: ='1.2 Plant incident '!B3 -> OCOT/OC1M | D3: ชื่อหน่วยงาน | F3: ='1.2 Plant incident '!B5 -> ส่วนปฏิบัติการผลิต CUP1 | N3: วันที่ประเมิน | O3: ='1.2 Plant incident '!D3 -> 28/09/2565
A4: วิธีการประเมิน | B4: ='1.2 Plant incident '!B4 -> ประเมินแบบพื้นที่ | D4: ชื่อพื้นที่ประเมิน | F4: ='1.2 Plant incident '!B6 -> GPSC RYG : CUP-1 | N4: ทบทวนครั้งที่ | O4: ='1.2 Plant incident '!D4 -> 4
A6: Plant incident | B6: Impact Category ประเภทของผลกระทบที่เกิดขึ้น | C6: Severity of Impact Over Time ระดับผลกระทบที่เพิ่มขึ้นในแต่ละวัน | N6: Maximum Tolerable Period of Disruption (MTPD) | O6: Recovery Time Objective (RTO) | P6: Minimum Business Continuity Objective (MBCO)
C7: 1 Hour | D7: 4 Hour | E7: 8 Hour | F7: 12 Hour | G7: 24 Hour | H7: 3 Days | I7: 5 Days | J7: 7 Days | K7: 14 Days | L7: 21 Days | M7: 30 Days
A8: ABCT breaker 5YB-01 trip by relay 87L operate | B8: B.ผลกระทบต่อลูกค้า | C8: 3 | D8: 3 | E8: 3 | F8: 3 | G8: 4 | H8: 4 | I8: 4 | J8: 4 | K8: 4 | L8: 4 | M8: 4 | N8: 24 ชม | O8: 1 ชม | P8: 1
A9: Plant islanding due to ban chang substation switching line to bay spare (inter trip not support this function) | B9: A. สูญเสียรายได้โดยตรง | C9: 2 | D9: 2 | E9: 3 | F9: 3 | G9: 4 | H9: 4 | I9: 4 | J9: 4 | K9: 4 | L9: 4 | M9: 4 | N9: 24 ชม | O9: 1 ชม | P9: 1
A10: GTG-11 trip by 1391VA979HH and PEA 1YB-01 OPEN plant Islanding by relay 21/21N Zone1 | B10: A. สูญเสียรายได้โดยตรง | C10: 2 | D10: 2 | E10: 3 | F10: 3 | G10: 4 | H10: 4 | I10: 4 | J10: 4 | K10: 4 | L10: 4 | M10: 4 | N10: 24 ชม | O10: 1 ชม | P10: 1
A11: GTG-14 was tripped by Load GEAR#1&2 AXIS VIBRAT.high | B11: A. สูญเสียรายได้โดยตรง | C11: 2 | D11: 2 | E11: 3 | F11: 3 | G11: 4 | H11: 4 | I11: 4 | J11: 4 | K11: 4 | L11: 4 | M11: 4 | N11: 24 ชม | O11: 12 ชม | P11: 1
A12: GTG-11 was tripped by alarm "TAHH 534-541 Brg.Metal Temp high trip" | B12: A. สูญเสียรายได้โดยตรง | C12: 2 | D12: 2 | E12: 3 | F12: 3 | G12: 4 | H12: 4 | I12: 4 | J12: 4 | K12: 4 | L12: 4 | M12: 4 | N12: 24 ชม | O12: 12 ชม | P12: 1
A13: GTG11 was tripped by "Generator Vibration high trip" | B13: A. สูญเสียรายได้โดยตรง | C13: 2 | D13: 2 | E13: 3 | F13: 3 | G13: 4 | H13: 4 | I13: 4 | J13: 4 | K13: 4 | L13: 4 | M13: 4 | N13: 24 ชม | O13: 12 ชม | P13: 1
A14: Close 52Aux (GTG-12) 87T operate 52L1 Open,52G Open and GTG-12 trip | B14: A. สูญเสียรายได้โดยตรง | C14: 2 | D14: 2 | E14: 3 | F14: 3 | G14: 4 | H14: 4 | I14: 4 | J14: 4 | K14: 4 | L14: 4 | M14: 4 | N14: 24 ชม | O14: 12 ชม | P14: 1
A15: Aux Boiler trip by burner inlet fuel gas pressure low low | B15: D.การหยุดชะงักของการปฏิบัติงาน/หน้าที่และงานประจำวัน | C15: 2 | D15: 2 | E15: 2 | F15: 2 | G15: 4 | H15: 4 | I15: 4 | J15: 4 | K15: 4 | L15: 4 | M15: 4 | N15: 24 ชม | O15: 12 ชม | P15: 1

Sheet Risk Heat Map Criteria

Sheet Scenarios
